{"content": {"A": [], "\u6b93\u9b42\u5168\u6587\u9605\u8bfb/\u6b93\u9b42\u6b63\u6587/\u6587\u5b57\u7248/\u624b\u6253\u7248": [{"id": 970179, "book_url": "\u6b93\u9b42/970179", "title": "\u7b2c\u4e00\u7ae0\uff1a\u5927\u51fa\u6ba1\u4e4b\u5f00\u7bc7"}, {"id": 970183, "book_url": "\u6b93\u9b42/970183", "title": "\u7b2c\u4e94\u7ae0\uff1a\u5723\u517d\u96ea\u989c\u9b54\u8c82"}, {"id": 970180, "book_url": "\u6b93\u9b42/970180", "title": "\u7b2c\u4e8c\u7ae0\uff1a\u6b7b\u4e0d\u7791\u76ee"}, {"id": 970184, "book_url": "\u6b93\u9b42/970184", "title": "\u7b2c\u516d\u7ae0\uff1a\u878d\u5408"}, {"id": 970181, "book_url": "\u6b93\u9b42/970181", "title": "\u7b2c\u4e09\u7ae0\uff1a\u5929\u5e08"}, {"id": 970185, "book_url": "\u6b93\u9b42/970185", "title": "\u7b2c\u4e03\u7ae0\uff1a\u4e22\u9b42"}, {"id": 970182, "book_url": "\u6b93\u9b42/970182", "title": "\u7b2c\u56db\u7ae0\uff1a\u4e94\u9b3c\u9b45\u86c7"}, {"id": 970186, "book_url": "\u6b93\u9b42/970186", "title": "\u7b2c\u516b\u7ae0\uff1a\u649e\u5ffd"}, {"id": 970187, "book_url": "\u6b93\u9b42/970187", "title": "\u7b2c\u4e5d\u7ae0\uff1a\u516d\u6708\u96ea"}, {"id": 970191, "book_url": "\u6b93\u9b42/970191", "title": "\u7b2c\u5341\u4e09\u7ae0\uff1a\u960e\u738b\u6765\u7535"}, {"id": 970188, "book_url": "\u6b93\u9b42/970188", "title": "\u7b2c\u5341\u7ae0\uff1a\u9b3c\u5dee\u4e0a\u95e8"}, {"id": 970192, "book_url": "\u6b93\u9b42/970192", "title": "\u7b2c\u5341\u56db\u7ae0\uff1a\u4fee\u8865\u672f"}, {"id": 970189, "book_url": "\u6b93\u9b42/970189", "title": "\u7b2c\u5341\u4e00\u7ae0\uff1a\u524d\u4e16"}, {"id": 970193, "book_url": "\u6b93\u9b42/970193", "title": "\u7b2c\u5341\u4e94\u7ae0\uff1a\u751f\u6d25\u7389"}, {"id": 970190, "book_url": "\u6b93\u9b42/970190", "title": "\u7b2c\u5341\u4e8c\u7ae0\uff1a\u5bbf\u547d"}, {"id": 970194, "book_url": "\u6b93\u9b42/970194", "title": "\u7b2c\u5341\u516d\u7ae0\uff1a\u7206\u4f53"}, {"id": 970195, "book_url": "\u6b93\u9b42/970195", "title": "\u7b2c\u5341\u4e03\u7ae0\uff1a\u5361\u7075"}, {"id": 970199, "book_url": "\u6b93\u9b42/970199", "title": "\u7b2c\u4e8c\u5341\u4e00\u7ae0\uff1a\u521d\u89c1\u9ec4\u9f99"}, {"id": 970196, "book_url": "\u6b93\u9b42/970196", "title": "\u7b2c\u5341\u516b\u7ae0\uff1a\u88f8\u5973\u68a6\u6e38"}, {"id": 970200, "book_url": "\u6b93\u9b42/970200", "title": "\u7b2c\u4e8c\u5341\u4e8c\u7ae0\uff1a\u4e09\u715e\u5c40"}, {"id": 970197, "book_url": "\u6b93\u9b42/970197", "title": "\u7b2c\u5341\u4e5d\u7ae0\uff1a\u6f47\u6d12\u5361\u7075"}, {"id": 970201, "book_url": "\u6b93\u9b42/970201", "title": "\u7b2c\u4e8c\u5341\u4e09\u7ae0\uff1a\u4eba\u9aa8\u593a\u9b42\u9489"}, {"id": 970198, "book_url": "\u6b93\u9b42/970198", "title": "\u7b2c\u4e8c\u5341\u7ae0\uff1a\u9b3c\u529b\u7a7a\u95f4"}, {"id": 970202, "book_url": "\u6b93\u9b42/970202", "title": "\u7b2c\u4e8c\u5341\u56db\u7ae0\uff1a\u56f0\u9f99\u9635"}, {"id": 970203, "book_url": "\u6b93\u9b42/970203", "title": "\u7b2c\u4e8c\u5341\u4e94\u7ae0\uff1a\u516b\u5366\u955c\u4e2d\u82b1"}, {"id": 970207, "book_url": "\u6b93\u9b42/970207", "title": "\u7b2c\u4e8c\u5341\u4e5d\u7ae0\uff1a\u661f\u6cb3\u6d1b"}, {"id": 970204, "book_url": "\u6b93\u9b42/970204", "title": "\u7b2c\u4e8c\u5341\u516d\u7ae0\uff1a\u5b7d\u7f18"}, {"id": 970208, "book_url": "\u6b93\u9b42/970208", "title": "\u7b2c\u4e09\u5341\u7ae0\uff1a\u9b3c\u642d\u80a9"}, {"id": 970205, "book_url": "\u6b93\u9b42/970205", "title": "\u7b2c\u4e8c\u5341\u4e03\u7ae0\uff1a\u591c\u660e\u73e0"}, {"id": 970209, "book_url": "\u6b93\u9b42/970209", "title": "\u7b2c\u4e09\u5341\u4e00\u7ae0\uff1a\u5947\u76d2"}, {"id": 970206, "book_url": "\u6b93\u9b42/970206", "title": "\u7b2c\u4e8c\u5341\u516b\u7ae0\uff1a\u9e70\u5730"}, {"id": 970210, "book_url": "\u6b93\u9b42/970210", "title": "\u7b2c\u4e09\u5341\u4e8c\u7ae0\uff1a\u9f0e\u7089"}, {"id": 970211, "book_url": "\u6b93\u9b42/970211", "title": "\u7b2c\u4e09\u5341\u4e09\u7ae0\uff1a\u53c8\u89c1\u75af\u5b50"}, {"id": 970215, "book_url": "\u6b93\u9b42/970215", "title": "\u7b2c\u4e09\u5341\u4e03\u7ae0\uff1a\u8840\u5657"}, {"id": 970212, "book_url": "\u6b93\u9b42/970212", "title": "\u7b2c\u4e09\u5341\u56db\u7ae0\uff1a\u7b26\u6c0f\u540e\u88d4"}, {"id": 970216, "book_url": "\u6b93\u9b42/970216", "title": "\u7b2c\u4e09\u5341\u516b\u7ae0\uff1a\u6e05\u5e7d\u77f3\u6d1e"}, {"id": 970213, "book_url": "\u6b93\u9b42/970213", "title": "\u7b2c\u4e09\u5341\u4e94\u7ae0\uff1a\u5fb7\u51c0\u7985\u5e08"}, {"id": 970217, "book_url": "\u6b93\u9b42/970217", "title": "\u7b2c\u4e09\u5341\u4e5d\u7ae0\uff1a\u5730\u4e0b\u6c34\u6676\u5bab"}, {"id": 970214, "book_url": "\u6b93\u9b42/970214", "title": "\u7b2c\u4e09\u5341\u516d\u7ae0\uff1a\u627f\u5929\u795e\u575b"}, {"id": 970218, "book_url": "\u6b93\u9b42/970218", "title": "\u7b2c\u56db\u5341\u7ae0\uff1a\u56da\u725b"}, {"id": 970219, "book_url": "\u6b93\u9b42/970219", "title": "\u7b2c\u56db\u5341\u4e00\u7ae0\uff1a\u9694\u5899\u6709\u8033"}, {"id": 970223, "book_url": "\u6b93\u9b42/970223", "title": "\u7b2c\u56db\u5341\u4e94\u7ae0\uff1a\u9b3c\u642d\u8bdd"}, {"id": 970220, "book_url": "\u6b93\u9b42/970220", "title": "\u7b2c\u56db\u5341\u4e8c\u7ae0\uff1a\u540e\u6e56\u4f20\u8bf4"}, {"id": 970224, "book_url": "\u6b93\u9b42/970224", "title": "\u7b2c\u56db\u5341\u516d\u7ae0\uff1a\u9f0e\u9505"}, {"id": 970221, "book_url": "\u6b93\u9b42/970221", "title": "\u7b2c\u56db\u5341\u4e09\u7ae0\uff1a\u6e56\u602a\u51fa\u73b0"}, {"id": 970225, "book_url": "\u6b93\u9b42/970225", "title": "\u7b2c\u56db\u5341\u4e03\u7ae0\uff1a\u89e3\u5bc6\u524d\u594f"}, {"id": 970222, "book_url": "\u6b93\u9b42/970222", "title": "\u7b2c\u56db\u5341\u56db\u7ae0\uff1a\u4eb2\u89c1\u591c\u6e38\u795e"}, {"id": 970226, "book_url": "\u6b93\u9b42/970226", "title": "\u7b2c\u56db\u5341\u516b\u7ae0\uff1a\u9aa8\u9488"}, {"id": 970227, "book_url": "\u6b93\u9b42/970227", "title": "\u7b2c\u56db\u5341\u4e5d\u7ae0\uff1a\u7591\u60d1\u4e0d\u89e3"}, {"id": 970231, "book_url": "\u6b93\u9b42/970231", "title": "\u7b2c\u4e94\u5341\u4e09\u7ae0\uff1a\u6b93\u9b42\u56fe\u89e3"}, {"id": 970228, "book_url": "\u6b93\u9b42/970228", "title": "\u7b2c\u4e94\u5341\u7ae0\uff1a\u9b3c\u773c\u6cea"}, {"id": 970232, "book_url": "\u6b93\u9b42/970232", "title": "\u7b2c\u4e94\u5341\u56db\u7ae0\uff1a"}, {"id": 970229, "book_url": "\u6b93\u9b42/970229", "title": "\u7b2c\u4e94\u5341\u4e00\u7ae0\uff1a\u9aa8\u9547"}, {"id": 970233, "book_url": "\u6b93\u9b42/970233", "title": "\u7b2c\u4e94\u5341\u4e94\u7ae0\uff1a\u5973\u9b3c\u7f20\u817f"}, {"id": 970230, "book_url": "\u6b93\u9b42/970230", "title": "\u7b2c\u4e94\u5341\u4e8c\u7ae0\uff1a\u5973\u9b3c"}, {"id": 970234, "book_url": "\u6b93\u9b42/970234", "title": "\u7b2c\u4e94\u5341\u516d\u7ae0\uff1a\u5973\u9b3c\u7f20\u817f\uff08\u4e0b\uff09"}, {"id": 970235, "book_url": "\u6b93\u9b42/970235", "title": "\u7b2c\u4e94\u5341\u4e03\u7ae0\uff1a\u9ed1\u9f0e"}, {"id": 970239, "book_url": "\u6b93\u9b42/970239", "title": "\u7b2c\u516d\u5341\u4e00\u7ae0\uff1a"}, {"id": 970236, "book_url": "\u6b93\u9b42/970236", "title": "\u7b2c\u4e94\u5341\u516b\u7ae0\uff1a\u78a7\u513f\u4e4b\u8c1c\uff081\uff09"}, {"id": 970240, "book_url": "\u6b93\u9b42/970240", "title": "\u7b2c\u516d\u5341\u4e8c\u7ae0\uff1a\u5b89\u5eb7\u533b\u9662\uff082\uff09"}, {"id": 970237, "book_url": "\u6b93\u9b42/970237", "title": "\u7b2c\u4e94\u5341\u4e5d\u7ae0\uff1a\u78a7\u513f\u4e4b\u8c1c\uff082\uff09"}, {"id": 970241, "book_url": "\u6b93\u9b42/970241", "title": "\u7b2c\u516d\u5341\u4e09\u7ae0\uff1a\u5b89\u5eb7\u533b\u9662\uff083\uff09"}, {"id": 970238, "book_url": "\u6b93\u9b42/970238", "title": "\u7b2c\u516d\u5341\u7ae0\uff1a\u89e3\u8c1c\uff081\uff09"}, {"id": 970242, "book_url": "\u6b93\u9b42/970242", "title": "\u7b2c\u516d\u5341\u56db\u7ae0\uff1a\u5b89\u5eb7\u533b\u9662\uff084\uff09"}, {"id": 970243, "book_url": "\u6b93\u9b42/970243", "title": "\u7b2c\u516d\u5341\u4e94\u7ae0\uff1a\u5b89\u5eb7\u533b\u9662\uff085\uff09"}, {"id": 970247, "book_url": "\u6b93\u9b42/970247", "title": "\u7b2c\u516d\u5341\u4e5d\u7ae0\uff1a\u5b89\u5eb7\u533b\u9662\uff089\uff09"}, {"id": 970244, "book_url": "\u6b93\u9b42/970244", "title": "\u7b2c\u516d\u5341\u516d\u7ae0\uff1a\u5b89\u5eb7\u533b\u9662\uff086\uff09"}, {"id": 970248, "book_url": "\u6b93\u9b42/970248", "title": "\u7b2c\u4e03\u5341\u7ae0\uff1a\u5b89\u5eb7\u533b\u9662\uff0810\uff09"}, {"id": 970245, "book_url": "\u6b93\u9b42/970245", "title": "\u7b2c\u516d\u5341\u4e03\u7ae0\uff1a\u5b89\u5eb7\u533b\u9662\uff087\uff09"}, {"id": 970249, "book_url": "\u6b93\u9b42/970249", "title": "\u7b2c\u4e03\u5341\u4e00\u7ae0\uff1a\u5b89\u5eb7\u533b\u9662\uff0811\uff09"}, {"id": 970246, "book_url": "\u6b93\u9b42/970246", "title": "\u7b2c\u516d\u5341\u516b\u7ae0\uff1a\u5b89\u5eb7\u533b\u9662\uff088\uff09"}, {"id": 970250, "book_url": "\u6b93\u9b42/970250", "title": "\u7b2c\u4e03\u5341\u4e8c\u7ae0\uff1a\u5b89\u5eb7\u533b\u9662\uff0812\uff09"}, {"id": 970251, "book_url": "\u6b93\u9b42/970251", "title": "\u7b2c\u4e03\u5341\u4e09\u7ae0\uff1a\u72ec\u89d2\u738b\u86c7"}, {"id": 970255, "book_url": "\u6b93\u9b42/970255", "title": "\u7b2c\u4e03\u5341\u4e03\u7ae0\uff1a\u610f\u5916\u4e2d\u7684\u610f\u5916\uff08\u4e0b\uff09"}, {"id": 970252, "book_url": "\u6b93\u9b42/970252", "title": "\u7b2c\u4e03\u5341\u56db\u7ae0\uff1a\u534e\u5b50\u9192\u6765"}, {"id": 970256, "book_url": "\u6b93\u9b42/970256", "title": "\u7b2c\u4e03\u5341\u516b\u7ae0\uff1a"}, {"id": 970253, "book_url": "\u6b93\u9b42/970253", "title": "\u7b2c\u4e03\u5341\u4e94\u7ae0\uff1a\u610f\u5916\u4e2d\u7684\u610f\u5916\uff08\u4e0a\uff09"}, {"id": 970257, "book_url": "\u6b93\u9b42/970257", "title": "\u7b2c\u4e03\u5341\u4e5d\u7ae0\uff1a\u5f02\u5ea6\u7a7a\u95f4"}, {"id": 970254, "book_url": "\u6b93\u9b42/970254", "title": "\u7b2c\u4e03\u5341\u516d\u7ae0\uff1a\u610f\u5916\u4e2d\u7684\u610f\u5916\uff08\u4e2d\uff09"}, {"id": 970258, "book_url": "\u6b93\u9b42/970258", "title": "\u7b2c\u516b\u5341\u7ae0\uff1a\u7f57\u5e9a"}, {"id": 970259, "book_url": "\u6b93\u9b42/970259", "title": "\u7b2c\u516b\u5341\u4e00\u7ae0\uff1a\u4e5d\u79bb\u4e5d\u9633\u5723\u8840"}, {"id": 970263, "book_url": "\u6b93\u9b42/970263", "title": "\u7b2c\u516b\u5341\u4e94\u7ae0\uff1a\u76d1\u72f1\u5730\u72f1"}, {"id": 970260, "book_url": "\u6b93\u9b42/970260", "title": "\u7b2c\u516b\u5341\u4e8c\u7ae0\uff1a\u4e5d\u79bb\u4e5d\u9633\u5723\u8840\uff08\u4e2d\uff09"}, {"id": 970264, "book_url": "\u6b93\u9b42/970264", "title": "\u7b2c\u516b\u5341\u516d\u7ae0\uff1a\u9b3c\u9053\u5929\u5e08\u51fa\u73b0\u502a\u7aef"}, {"id": 970261, "book_url": "\u6b93\u9b42/970261", "title": "\u7b2c\u516b\u5341\u4e09\u7ae0\uff1a\u4e5d\u79bb\u4e5d\u9633\u5723\u8840\uff08\u4e0b\uff09"}, {"id": 970265, "book_url": "\u6b93\u9b42/970265", "title": "\u7b2c\u516b\u5341\u4e03\u7ae0\uff1a\u7591\u4e91\u518d\u73b0"}, {"id": 970262, "book_url": "\u6b93\u9b42/970262", "title": "\u7b2c\u516b\u5341\u56db\u7ae0\uff1a\u9b3c\u5e02"}, {"id": 970266, "book_url": "\u6b93\u9b42/970266", "title": "\u7b2c\u516b\u5341\u516b\u7ae0\uff1a\u68a6\u9b54"}, {"id": 970267, "book_url": "\u6b93\u9b42/970267", "title": "\u7b2c\u516b\u5341\u4e5d\u7ae0\uff1a\u9648\u5927\u5e74vs\u75af\u5b50"}, {"id": 970271, "book_url": "\u6b93\u9b42/970271", "title": "\u7b2c\u4e5d\u5341\u4e09\u7ae0\uff1a\u5e7b\u9b3c\u738b"}, {"id": 970268, "book_url": "\u6b93\u9b42/970268", "title": "\u7b2c\u4e5d\u5341\u7ae0\uff1a\u6b93\u670d"}, {"id": 970272, "book_url": "\u6b93\u9b42/970272", "title": "\u7b2c\u4e5d\u5341\u56db\u7ae0\uff1a\u5e7b\u9b3c\u738b\uff08\u4e0b\uff09"}, {"id": 970269, "book_url": "\u6b93\u9b42/970269", "title": "\u7b2c\u4e5d\u5341\u4e00\u7ae0\uff1a\u9634\u9633\u9c7c"}, {"id": 970273, "book_url": "\u6b93\u9b42/970273", "title": "\u7b2c\u4e5d\u5341\u4e94\u7ae0\uff1a\u795e\u9f0e\u95e8"}, {"id": 970270, "book_url": "\u6b93\u9b42/970270", "title": "\u7b2c\u4e5d\u5341\u4e8c\u7ae0\uff1a\u9b54\u738b\u6492\u591a\u65af"}, {"id": 970274, "book_url": "\u6b93\u9b42/970274", "title": "\u7b2c\u4e5d\u5341\u516d\u7ae0\uff1a\u6ce8\u89e3"}, {"id": 970275, "book_url": "\u6b93\u9b42/970275", "title": "\u7b2c\u4e5d\u5341\u4e03\u7ae0\uff1a\u7384\u7075\u5080\u5121"}, {"id": 970279, "book_url": "\u6b93\u9b42/970279", "title": "\u7b2c\u4e00\u767e\u96f6\u4e00\u7ae0\uff1a\u65e0\u7aef\u4e89\u6597"}, {"id": 970276, "book_url": "\u6b93\u9b42/970276", "title": "\u7b2c\u4e5d\u5341\u516b\u7ae0\uff1a\u7075\u517d\u82b1\u6591\u79c3\u9888\u5b70\u6e56"}, {"id": 970280, "book_url": "\u6b93\u9b42/970280", "title": "\u7b2c\u4e00\u767e\u96f6\u4e8c\u7ae0\uff1a\u5c71\u96e8\u6b32\u6765\u98ce\u6ee1\u697c"}, {"id": 970277, "book_url": "\u6b93\u9b42/970277", "title": "\u7b2c\u4e5d\u5341\u4e5d\u7ae0\uff1a\u9690\u8eab\u7b26\uff08\u4e0a\uff09"}, {"id": 970281, "book_url": "\u6b93\u9b42/970281", "title": "\u7b2c\u4e00\u767e\u96f6\u4e09\u7ae0\uff1a\u660e\u706f\uff081\uff09"}, {"id": 970278, "book_url": "\u6b93\u9b42/970278", "title": "\u7b2c\u4e00\u767e\u7ae0\uff1a\u9690\u8eab\u7b26\uff08\u4e0b\uff09"}, {"id": 970282, "book_url": "\u6b93\u9b42/970282", "title": "\u7b2c\u4e00\u767e\u96f6\u56db\u7ae0\uff1a\u660e\u706f\uff082\uff09"}, {"id": 970283, "book_url": "\u6b93\u9b42/970283", "title": "\u7b2c\u4e00\u767e\u96f6\u4e94\u7ae0\uff1a\u660e\u706f\uff083\uff09"}, {"id": 970287, "book_url": "\u6b93\u9b42/970287", "title": "\u7b2c\u4e00\u767e\u96f6\u4e5d\u7ae0\uff1a\u4e8b\u60c5\u59cb\u672b\u7684\u89e3\u91ca\uff081\uff09"}, {"id": 970284, "book_url": "\u6b93\u9b42/970284", "title": "\u7b2c\u4e00\u767e\u96f6\u516d\u7ae0\uff1a\u660e\u706f\uff084\uff09"}, {"id": 970288, "book_url": "\u6b93\u9b42/970288", "title": "\u7b2c\u4e00\u767e\u4e00\u5341\u7ae0\uff1a\u5929\u8c61\u5f02\u52a8\uff08\u4e0a\uff09"}, {"id": 970285, "book_url": "\u6b93\u9b42/970285", "title": "\u7b2c\u4e00\u767e\u96f6\u4e03\u7ae0\uff1a\u660e\u706f\uff085\uff09"}, {"id": 970289, "book_url": "\u6b93\u9b42/970289", "title": "\u7b2c\u4e00\u767e\u4e00\u5341\u4e00\u7ae0\uff1a\u5929\u8c61\u5f02\u52a8\uff08\u4e0b\uff09"}, {"id": 970286, "book_url": "\u6b93\u9b42/970286", "title": "\u7b2c\u4e00\u767e\u96f6\u516b\u7ae0\uff1a\u660e\u706f\uff086\uff09"}, {"id": 970290, "book_url": "\u6b93\u9b42/970290", "title": "\u7b2c\u4e00\u767e\u4e00\u5341\u4e8c\u7ae0\uff1a\u4e0d\u80fd\u8bf4\u7684\u79d8\u5bc6"}, {"id": 970291, "book_url": "\u6b93\u9b42/970291", "title": "\u7b2c\u4e00\u767e\u4e00\u5341\u4e09\u7ae0\uff1a\u98a0\u5012\u9634\u8f6e\u9547"}, {"id": 970295, "book_url": "\u6b93\u9b42/970295", "title": "\u7b2c\u4e00\u767e\u4e00\u5341\u4e03\u7ae0\uff1a\u7a81\u7136\u800c\u81f3\u7684\u5c11\u5973\u5e08\u59d0\uff081\uff09"}, {"id": 970292, "book_url": "\u6b93\u9b42/970292", "title": "\u7b2c\u4e00\u767e\u4e00\u5341\u56db\u7ae0\uff1a\u60c5\u8ff7\u5c0f\u5361"}, {"id": 970296, "book_url": "\u6b93\u9b42/970296", "title": "\u7b2c\u4e00\u767e\u4e00\u5341\u516b\u7ae0\uff1a\u7a81\u5982\u800c\u6765\u7684\u5e08\u59d0\uff082\uff09"}, {"id": 970293, "book_url": "\u6b93\u9b42/970293", "title": "\u7b2c\u4e00\u767e\u4e00\u5341\u4e94\u7ae0\uff1a\u68a6\u5e7b\u9b54\u754c\u5e7b\u9b54\u65d7"}, {"id": 970297, "book_url": "\u6b93\u9b42/970297", "title": "\u7b2c\u4e00\u767e\u4e00\u5341\u4e5d\u7ae0\uff1a\u7a81\u5982\u800c\u6765\u7684\u5e08\u59d0\uff083\uff09"}, {"id": 970294, "book_url": "\u6b93\u9b42/970294", "title": "\u7b2c\u4e00\u767e\u4e00\u5341\u516d\u7ae0\uff1a\u5224\u82e5\u4e24\u4eba"}, {"id": 970298, "book_url": "\u6b93\u9b42/970298", "title": "\u7b2c\u4e00\u767e\u4e8c\u5341\u7ae0\uff1a\u5929\u8352\u7389\u9732"}, {"id": 970299, "book_url": "\u6b93\u9b42/970299", "title": "\u7b2c\u4e00\u767e\u4e8c\u5341\u4e00\u7ae0\uff1a\u65e0\u5c3d\u7965\u5149"}, {"id": 970303, "book_url": "\u6b93\u9b42/970303", "title": "\u7b2c\u4e00\u767e\u4e8c\u5341\u4e94\u7ae0\uff1a\u4e0d\u80fd\u4e0d\u4f5c\u51fa\u7684\u89e3\u91ca\uff084\uff09"}, {"id": 970300, "book_url": "\u6b93\u9b42/970300", "title": "\u7b2c\u4e00\u767e\u4e8c\u5341\u4e8c\u7ae0\uff1a\u4e0d\u80fd\u4e0d\u4f5c\u51fa\u7684\u89e3\u91ca\uff081\uff09"}, {"id": 970304, "book_url": "\u6b93\u9b42/970304", "title": "\u7b2c\u4e00\u767e\u4e8c\u5341\u516d\u7ae0\uff1a\u6e21\u6cd5"}, {"id": 970301, "book_url": "\u6b93\u9b42/970301", "title": "\u7b2c\u4e00\u767e\u4e8c\u5341\u4e09\u7ae0\uff1a\u4e0d\u80fd\u4e0d\u4f5c\u51fa\u7684\u89e3\u91ca\uff082\uff09"}, {"id": 970305, "book_url": "\u6b93\u9b42/970305", "title": "\u7b2c\u4e00\u767e\u4e8c\u5341\u4e03\u7ae0\uff1a\u665a\u9910"}, {"id": 970302, "book_url": "\u6b93\u9b42/970302", "title": "\u7b2c\u4e00\u767e\u4e8c\u5341\u56db\u7ae0\uff1a\u4e0d\u80fd\u4e0d\u4f5c\u51fa\u7684\u89e3\u91ca\uff083\uff09"}, {"id": 970306, "book_url": "\u6b93\u9b42/970306", "title": "\u7b2c\u4e00\u767e\u4e8c\u5341\u516b\u7ae0\uff1a\u5974\u513fVS\u5c0f\u767d"}, {"id": 970307, "book_url": "\u6b93\u9b42/970307", "title": "\u7b2c\u4e00\u767e\u4e8c\u5341\u4e5d\u7ae0\uff1a\u90aa\u9b54\u7591\u4e91"}, {"id": 970311, "book_url": "\u6b93\u9b42/970311", "title": "\u7b2c\u4e00\u767e\u4e09\u5341\u4e09\u7ae0\uff1a\u5343\u8bdb\u9b54\u706d\u9635"}, {"id": 970308, "book_url": "\u6b93\u9b42/970308", "title": "\u7b2c\u4e00\u767e\u4e09\u5341\u7ae0\uff1a\u8f6c\u5ac1\u795e\u529f"}, {"id": 970312, "book_url": "\u6b93\u9b42/970312", "title": "\u7b2c\u4e00\u767e\u4e09\u5341\u56db\u7ae0\uff1a\u9047\u9669"}, {"id": 970309, "book_url": "\u6b93\u9b42/970309", "title": "\u7b2c\u4e00\u767e\u4e09\u5341\u4e00\u7ae0\uff1a\u5929\u53f0\u91ca\u7591"}, {"id": 970313, "book_url": "\u6b93\u9b42/970313", "title": "\u7b2c\u4e00\u767e\u4e09\u5341\u4e94\u7ae0\uff1a\u4e2d\u9b54\uff081\uff09"}, {"id": 970310, "book_url": "\u6b93\u9b42/970310", "title": "\u7b2c\u4e00\u767e\u4e09\u5341\u4e8c\u7ae0\uff1a\u8f9f\u90aa\u73e0"}, {"id": 970314, "book_url": "\u6b93\u9b42/970314", "title": "\u7b2c\u4e00\u767e\u4e09\u5341\u516d\u7ae0\uff1a\u4e2d\u9b54\uff082\uff09"}, {"id": 970315, "book_url": "\u6b93\u9b42/970315", "title": "\u7b2c\u4e00\u767e\u4e09\u5341\u4e03\u7ae0\uff1a\u4e2d\u9b54\uff083\uff09"}, {"id": 970319, "book_url": "\u6b93\u9b42/970319", "title": "\u7b2c\u4e00\u767e\u56db\u5341\u4e00\u7ae0\uff1a\u4e07\u9b3c\u566c\u7075\uff083\uff09"}, {"id": 970316, "book_url": "\u6b93\u9b42/970316", "title": "\u7b2c\u4e00\u767e\u4e09\u5341\u516b\u7ae0\uff1a\u4e2d\u9b54\uff084\uff09"}, {"id": 970320, "book_url": "\u6b93\u9b42/970320", "title": "\u7b2c\u4e00\u767e\u56db\u5341\u4e8c\u7ae0\uff1a\u4e07\u9b3c\u566c\u7075\uff084\uff09"}, {"id": 970317, "book_url": "\u6b93\u9b42/970317", "title": "\u7b2c\u4e00\u767e\u4e09\u5341\u4e5d\u7ae0\uff1a\u4e07\u9b3c\u566c\u7075\uff081\uff09"}, {"id": 970321, "book_url": "\u6b93\u9b42/970321", "title": "\u7b2c\u4e00\u767e\u56db\u5341\u4e09\u7ae0\uff1a\u4e07\u9b3c\u566c\u7075\uff085\uff09"}, {"id": 970318, "book_url": "\u6b93\u9b42/970318", "title": "\u7b2c\u4e00\u767e\u56db\u5341\u7ae0\uff1a\u4e07\u9b3c\u566c\u7075\uff082\uff09"}, {"id": 970322, "book_url": "\u6b93\u9b42/970322", "title": "\u7b2c\u4e00\u767e\u56db\u5341\u56db\u7ae0\uff1a\u4e07\u9b3c\u566c\u7075\uff086\uff09"}, {"id": 970323, "book_url": "\u6b93\u9b42/970323", "title": "\u7b2c\u4e00\u767d\u56db\u5341\u4e94\u7ae0\uff1a\u68a6\u56de\u89e3\u8c1c\uff081\uff09"}, {"id": 970327, "book_url": "\u6b93\u9b42/970327", "title": "\u7b2c\u4e00\u767e\u56db\u5341\u4e5d\u7ae0\uff1a\u68a6\u56de\u89e3\u8c1c\uff085\uff09"}, {"id": 970324, "book_url": "\u6b93\u9b42/970324", "title": "\u7b2c\u4e00\u767e\u56db\u5341\u516d\u7ae0\uff1a\u68a6\u56de\u89e3\u8c1c\uff082\uff09"}, {"id": 970328, "book_url": "\u6b93\u9b42/970328", "title": "\u7b2c\u4e00\u767e\u4e94\u5341\u7ae0\uff1a\u68a6\u56de\u89e3\u8c1c\uff086\uff09"}, {"id": 970325, "book_url": "\u6b93\u9b42/970325", "title": "\u7b2c\u4e00\u767e\u56db\u5341\u4e03\u7ae0\uff1a\u68a6\u56de\u89e3\u8c1c\uff083\uff09"}, {"id": 970329, "book_url": "\u6b93\u9b42/970329", "title": "\u7b2c\u4e00\u767e\u4e94\u5341\u4e00\u7ae0\uff1a\u68a6\u56de\u89e3\u8c1c\uff087\uff09"}, {"id": 970326, "book_url": "\u6b93\u9b42/970326", "title": "\u7b2c\u4e00\u767e\u56db\u5341\u516b\u7ae0\uff1a\u68a6\u56de\u89e3\u8c1c\uff084\uff09"}, {"id": 970330, "book_url": "\u6b93\u9b42/970330", "title": "\u7b2c\u4e00\u767e\u4e94\u5341\u4e8c\u7ae0\uff1a\u68a6\u56de\u89e3\u8c1c\uff088\uff09"}, {"id": 970331, "book_url": "\u6b93\u9b42/970331", "title": "\u7b2c\u4e00\u767e\u4e94\u5341\u4e09\u7ae0\uff1a\u68a6\u56de\u89e3\u8c1c\uff089\uff09"}, {"id": 970335, "book_url": "\u6b93\u9b42/970335", "title": "\u7b2c\u4e00\u767e\u4e94\u5341\u4e03\u7ae0\uff1a\u7aa5\u5f97\u5929\u673a"}, {"id": 970332, "book_url": "\u6b93\u9b42/970332", "title": "\u7b2c\u4e00\u767e\u4e94\u5341\u56db\u7ae0\uff1a\u6539\u89c2\u5c40\u9762"}, {"id": 970336, "book_url": "\u6b93\u9b42/970336", "title": "\u7b2c\u4e00\u767e\u4e94\u5341\u516b\u7ae0\uff1a\u9aa8\u9547\u663e\u795e\u5a01"}, {"id": 970333, "book_url": "\u6b93\u9b42/970333", "title": "\u7b2c\u4e00\u767e\u4e94\u5341\u4e94\u7ae0\uff1a\u4ee5\u5e7b\u6cbb\u5e7b"}, {"id": 970337, "book_url": "\u6b93\u9b42/970337", "title": "\u7b2c\u4e00\u767e\u4e94\u5341\u4e5d\u7ae0\uff1a\u9669\u8c61\u73af\u751f"}, {"id": 970334, "book_url": "\u6b93\u9b42/970334", "title": "\u7b2c\u4e00\u767e\u4e94\u5341\u516d\u7ae0\uff1a\u53cc\u9b42"}, {"id": 970338, "book_url": "\u6b93\u9b42/970338", "title": "\u7b2c\u4e00\u767e\u516d\u5341\u7ae0\uff1a\u9762\u9986\u5bfb\u6839"}, {"id": 970339, "book_url": "\u6b93\u9b42/970339", "title": "\u7b2c\u4e00\u767e\u516d\u5341\u4e00\u7ae0\uff1a\u5929\u751f\u5f02\u8c61"}, {"id": 970343, "book_url": "\u6b93\u9b42/970343", "title": "\u7b2c\u4e00\u767e\u516d\u5341\u4e94\u7ae0\uff1a\u65e0\u826f\u5e08\u5144\u5f1f"}, {"id": 970340, "book_url": "\u6b93\u9b42/970340", "title": "\u7b2c\u4e00\u767e\u516d\u5341\u4e8c\u7ae0\uff1a\u78c1\u8c2d\u5723\u6c34"}, {"id": 970344, "book_url": "\u6b93\u9b42/970344", "title": "\u7b2c\u4e00\u767e\u516d\u5341\u516d\u7ae0\uff1a\u5bc6\u5ba4\u9759\u5fc3\u5492"}, {"id": 970341, "book_url": "\u6b93\u9b42/970341", "title": "\u7b2c\u4e00\u767e\u516d\u5341\u4e09\u7ae0\uff1a\u9a71\u9b54\u9999"}, {"id": 970345, "book_url": "\u6b93\u9b42/970345", "title": "\u7b2c\u4e00\u767e\u516d\u5341\u4e03\u7ae0\uff1a\u8fd8\u539f\u57fa\u672c\u6cd5"}, {"id": 970342, "book_url": "\u6b93\u9b42/970342", "title": "\u7b2c\u4e00\u767e\u516d\u5341\u56db\u7ae0\uff1a\u591c\u53c9\u62dc\u516b\u65b9"}, {"id": 970346, "book_url": "\u6b93\u9b42/970346", "title": "\u7b2c\u4e00\u767e\u516d\u5341\u516b\u7ae0\uff1a\u72fc\u72c8\u4e3a\u5978"}, {"id": 970347, "book_url": "\u6b93\u9b42/970347", "title": "\u7b2c\u4e00\u767e\u516d\u5341\u4e5d\u7ae0\uff1a\u6b7b\u4eba\u5f52\u6765"}, {"id": 970351, "book_url": "\u6b93\u9b42/970351", "title": "\u7b2c\u4e00\u767e\u4e03\u5341\u4e09\u7ae0\uff1a\u62d6\u5200\u8bb0"}, {"id": 970348, "book_url": "\u6b93\u9b42/970348", "title": "\u7b2c\u4e00\u767e\u4e03\u5341\u7ae0\uff1a\u5bc6\u5883\u6597\u6cd5\uff081\uff09"}, {"id": 970352, "book_url": "\u6b93\u9b42/970352", "title": "\u7b2c\u4e00\u767e\u4e03\u5341\u56db\u7ae0\uff1a\u5317\u6597\u4e03\u661f\u9aa8\u9547"}, {"id": 970349, "book_url": "\u6b93\u9b42/970349", "title": "\u7b2c\u4e00\u767e\u4e03\u5341\u4e00\u7ae0\uff1a\u7a81\u53d8"}, {"id": 970353, "book_url": "\u6b93\u9b42/970353", "title": "\u7b2c\u4e00\u767e\u4e03\u5341\u4e94\u7ae0\uff1a\u901a\u7384\u9547\u552c\u5947\u672f"}, {"id": 970350, "book_url": "\u6b93\u9b42/970350", "title": "\u7b2c\u4e00\u767e\u4e03\u5341\u4e8c\u7ae0\uff1a\u91cd\u9022"}, {"id": 970354, "book_url": "\u6b93\u9b42/970354", "title": "\u7b2c\u4e00\u767e\u4e03\u5341\u516d\u7ae0\uff1a\u9547\u552c\u4e4b\u9053"}, {"id": 970355, "book_url": "\u6b93\u9b42/970355", "title": "\u7b2c\u4e00\u767e\u4e03\u5341\u4e03\u7ae0\uff1a\u5c0f\u987b\u5f25\u56db\u5408\u9547"}, {"id": 970359, "book_url": "\u6b93\u9b42/970359", "title": "\u7b2c\u4e00\u767e\u516b\u5341\u4e00\u7ae0\uff1a\u53d8\u5f02"}, {"id": 970356, "book_url": "\u6b93\u9b42/970356", "title": "\u7b2c\u4e00\u767e\u4e03\u5341\u516b\u7ae0;\u6444\u9b42\u8f6c\u4f53\u5927\u6cd5"}, {"id": 970360, "book_url": "\u6b93\u9b42/970360", "title": "\u7b2c\u4e00\u767e\u516b\u5341\u4e8c\u7ae0\uff1a\u7edd\u5883"}, {"id": 970357, "book_url": "\u6b93\u9b42/970357", "title": "\u7b2c\u4e00\u767e\u4e03\u5341\u4e5d\u7ae0\uff1a\u4e09\u65b9\u91cd\u9022"}, {"id": 970361, "book_url": "\u6b93\u9b42/970361", "title": "\u7b2c\u4e00\u767e\u516b\u5341\u4e09\u7ae0\uff1a\u7b97\u8ba1\u960e\u738b"}, {"id": 970358, "book_url": "\u6b93\u9b42/970358", "title": "\u7b2c\u4e00\u767e\u516b\u5341\u7ae0\uff1a\u771f\u6b63\u7684\u9b3c\u738b\u5b9e\u529b"}, {"id": 970362, "book_url": "\u6b93\u9b42/970362", "title": "\u7b2c\u4e00\u767e\u516b\u5341\u56db\u7ae0\uff1a\u8f6e\u56de\u754c\u76d8"}, {"id": 970363, "book_url": "\u6b93\u9b42/970363", "title": "\u7b2c\u4e00\u767e\u516b\u5341\u4e94\u7ae0\uff1a\u5f62\u52bf\u9006\u8f6c"}, {"id": 970367, "book_url": "\u6b93\u9b42/970367", "title": "\u7b2c\u4e00\u767e\u516b\u5341\u4e5d\u7ae0\uff1a\u51fa\u6ba1\uff08\u5927\u7ed3\u5c40\uff09"}, {"id": 970364, "book_url": "\u6b93\u9b42/970364", "title": "\u7b2c\u4e00\u767e\u516b\u5341\u516d\u7ae0\uff1a\u56db\u6c34\u56db\u7075\u8f6c\u8bdb\u90aa"}, {"id": 970365, "book_url": "\u6b93\u9b42/970365", "title": "\u7b2c\u4e00\u767e\u516b\u5341\u4e03\u7ae0\uff1a\u56de\u5bb6"}, {"id": 970366, "book_url": "\u6b93\u9b42/970366", "title": "\u7b2c\u4e00\u767e\u516b\u5341\u516b\u7ae0\uff1a\u7ee7\u7eed\u5954\u4e27"}]}, "intro": "\u5e73\u51e1\u4e0d\u80fd\u518d\u5e73\u51e1\u7684\u67f3\u65e0\u534e\uff0c\u5374\u5728\u59e5\u7237\u53bb\u4e16\u4e4b\u540e\u4e0d\u518d\u5e73\u51e1\uff01\u9634\u9633\u6b8a\u9014\uff0c\u5374\u5728\u4e0a\u6f14\u4e00\u90e8\u60b2\u5207\u7684\u60c5\u611f\u3001\u9053\u5fb7\u3001\u4f26\u7406\u5927\u620f\uff01\n    \u5404\u79cd\u9677\u9631\u8bf1\u60d1\u63a5\u8e35\u800c\u81f3\uff0c\u5c06\u4e3b\u89d2\u63a8\u5411\u4e00\u4e2a\u63a5\u4e00\u4e2a\u7684\u9ad8\u5cf0\uff0c\u6700\u540e\u7684\u7ed3\u679c\u53c8\u662f\u4ec0\u4e48\u5462\uff1f\u91d1\u94b1\u3001\u7f8e\u5973\u3001\u6743\u5229\uff1f\u8fd8\u662f\u6210\u4e3a\u795e\u8bdd\uff01\n    \u53e4\u5893\u3001\u9057\u8ff9\u3001\u5343\u53e4\u4e4b\u8c1c\u5c3d\u5728\u5996\u9f0e\u6b93\u9b42\uff01\n    \u63a8\u8350\u300a\u7ea7\u70bc\u5668\u300b\u300a\u6e21\u795e\u4ed9\u300b\u300a\u5f02\u4e16\u4e4b\u795e\u6b66\u59276\u300b\u300a\u4e00\u7f15\u5e7d\u9b42\u95ef\u5f02\u4e16\u300b\u300a\u7537\u4eba\u662f\u72d7\u5973\u4eba\u662f\u732b\u300b", "name": "\u6b93\u9b42"}