{"content": {"A": [{"id": 412950, "book_url": "\u7eb8\u795e/412950", "title": "\u51fa\u573a\u4eba\u7269\u53ca\u80fd\u529b\u5217\u8868\uff08\u6309\u51fa\u573a\u987a\u5e8f\uff09"}, {"id": 412954, "book_url": "\u7eb8\u795e/412954", "title": "\u4f55\u8c13\u610f\u5883\u2014\u2014\u548c\u4e00\u4f4d\u9a6c\u6765\u897f\u4e9a\u8bfb\u8005\u7684\u8c08\u8bdd\u7eaa\u5f55"}, {"id": 412951, "book_url": "\u7eb8\u795e/412951", "title": "\u795e\u5175\u699c\u5355\u4e0e\u8bbe\u8ba1"}, {"id": 412955, "book_url": "\u7eb8\u795e/412955", "title": "\u5377\u4e2d\u5377\u4e00\uff1a\u4f5c\u5f0a\u5f00\u59cb"}, {"id": 412952, "book_url": "\u7eb8\u795e/412952", "title": "\u5076\u7684\u65b0\u4e66\uff08\u65b0\u4eba\uff09\u699c\u653b\u7565\u2014\u2014\u5c0f\u54c8\u5236\u9020"}, {"id": 412956, "book_url": "\u7eb8\u795e/412956", "title": "\u5377\u4e2d\u5377\u4e8c:\u7ee7\u7eed\u4f5c\u5f0a"}, {"id": 412953, "book_url": "\u7eb8\u795e/412953", "title": "\u7eb8\u795e\u5916\u7bc7\u4e4b\u98de\u8d8a\u5e73\u5b89\u591c"}, {"id": 412957, "book_url": "\u7eb8\u795e/412957", "title": "\u5377\u4e2d\u5377\u4e09:\u8fd8\u5728\u4f5c\u5f0a"}, {"id": 412958, "book_url": "\u7eb8\u795e/412958", "title": "\u5377\u4e2d\u5377\u56db:\u522b\u6253\u6270\u6211\u4eec\u4f5c\u5f0a"}, {"id": 412962, "book_url": "\u7eb8\u795e/412962", "title": "\u7b2c\u4e8c\u7ae0\uff1a\u91d1\u94c1(\u4fee)"}, {"id": 412959, "book_url": "\u7eb8\u795e/412959", "title": "\u5377\u4e2d\u5377\u4e94:\u6253\u6270\u4f5c\u5f0a\u8005\u6b7b"}, {"id": 412963, "book_url": "\u7eb8\u795e/412963", "title": "\u7b2c\u4e09\u7ae0\uff1a\u5c0f\u96e8(\u4fee)"}, {"id": 412960, "book_url": "\u7eb8\u795e/412960", "title": "\u5377\u4e2d\u5377\u516d\uff1a\u6df7\u4e71"}, {"id": 412964, "book_url": "\u7eb8\u795e/412964", "title": "\u7b2c\u56db\u7ae0\uff1a\u540c\u7c7b(\u4fee)"}, {"id": 412961, "book_url": "\u7eb8\u795e/412961", "title": "\u7b2c\u4e00\u7ae0\uff1a\u62a2\u52ab"}, {"id": 412965, "book_url": "\u7eb8\u795e/412965", "title": "\u7b2c\u4e94\u7ae0\uff1a\u5f71\u5b50(\u4fee)"}, {"id": 412966, "book_url": "\u7eb8\u795e/412966", "title": "\u7b2c\u516d\u7ae0\uff1a\u591c\u6218(\u4fee)"}, {"id": 412970, "book_url": "\u7eb8\u795e/412970", "title": "\u7b2c\u5341\u7ae0:\u8106\u5f31(\u4fee)"}, {"id": 412967, "book_url": "\u7eb8\u795e/412967", "title": "\u7b2c\u4e03\u7ae0\uff1a\u9ed1\u8863(\u4fee)"}, {"id": 412971, "book_url": "\u7eb8\u795e/412971", "title": "\u7b2c\u5341\u4e00\u7ae0\uff1a\u9ebb\u70e6(\u4fee)"}, {"id": 412968, "book_url": "\u7eb8\u795e/412968", "title": "\u7b2c\u516b\u7ae0\uff1a\u6b7b\u58eb(\u4fee)"}, {"id": 412972, "book_url": "\u7eb8\u795e/412972", "title": "\u7b2c\u5341\u4e8c\u7ae0\uff1a\u7535\u8bdd(\u4fee)"}, {"id": 412969, "book_url": "\u7eb8\u795e/412969", "title": "\u7b2c\u4e5d\u7ae0:\u652f\u914d(\u4fee)"}, {"id": 412973, "book_url": "\u7eb8\u795e/412973", "title": "\u7b2c\u5341\u4e09\u7ae0\uff1a\u60ca\u9669(\u4fee)"}, {"id": 412974, "book_url": "\u7eb8\u795e/412974", "title": "\u7b2c\u5341\u56db\u7ae0\uff1a\u80c1\u8feb(\u4fee)"}, {"id": 412978, "book_url": "\u7eb8\u795e/412978", "title": "\u7b2c\u5341\u516b\u7ae0\uff1a\u5929\u73e0(\u4fee)"}, {"id": 412975, "book_url": "\u7eb8\u795e/412975", "title": "\u7b2c\u5341\u4e94\u7ae0\uff1a\u6e29\u99a8(\u4fee)"}, {"id": 412979, "book_url": "\u7eb8\u795e/412979", "title": "\u7b2c\u5341\u4e5d\u7ae0\uff1a\u6536\u670d"}, {"id": 412976, "book_url": "\u7eb8\u795e/412976", "title": "\u7b2c\u5341\u516d\u7ae0\uff1a\u5165\u4fb5(\u4fee)"}, {"id": 412980, "book_url": "\u7eb8\u795e/412980", "title": "\u7b2c\u4e8c\u5341\u7ae0\uff1a\u79bb\u53bb(\u4fee)"}, {"id": 412977, "book_url": "\u7eb8\u795e/412977", "title": "\u7b2c\u5341\u4e03\u7ae0\uff1a\u767d\u8863"}, {"id": 412981, "book_url": "\u7eb8\u795e/412981", "title": "\u7b2c\u4e8c\u5341\u4e00\u7ae0\uff1a\u5951\u673a\uff08\u91cd\u4f20\uff09"}, {"id": 412982, "book_url": "\u7eb8\u795e/412982", "title": "\u7b2c\u4e8c\u5341\u4e8c\u7ae0\uff1a\u6252\u624b\uff08\u91cd\u4f20\uff09"}, {"id": 412986, "book_url": "\u7eb8\u795e/412986", "title": "\u7b2c\u4e8c\u5341\u516d\u7ae0\uff1a\u6c42\u5e08\uff08\u91cd\u4f20\uff09"}, {"id": 412983, "book_url": "\u7eb8\u795e/412983", "title": "\u7b2c\u4e8c\u5341\u4e09\u7ae0\uff1a\u6597\u6bb4\uff08\u91cd\u4f20\uff09"}, {"id": 412987, "book_url": "\u7eb8\u795e/412987", "title": "\u7b2c\u4e8c\u5341\u4e03\u7ae0:\u6f14\u6b66"}, {"id": 412984, "book_url": "\u7eb8\u795e/412984", "title": "\u7b2c\u4e8c\u5341\u56db\u7ae0\uff1a\u5c0f\u4e03\uff08\u91cd\u4f20\uff09"}, {"id": 412988, "book_url": "\u7eb8\u795e/412988", "title": "\u7b2c\u4e8c\u5341\u516b\u7ae0\uff1a\u629b\u5f03"}, {"id": 412985, "book_url": "\u7eb8\u795e/412985", "title": "\u7b2c\u4e8c\u5341\u4e94\u7ae0\uff1a\u8ffd\u5e08\uff08\u91cd\u4f20\uff09"}, {"id": 412989, "book_url": "\u7eb8\u795e/412989", "title": "\u4e8c\u5341\u4e5d\uff1a\u9ed1\u6697"}, {"id": 412990, "book_url": "\u7eb8\u795e/412990", "title": "\u7b2c\u4e09\u5341\u7ae0\uff1a\u6d4b\u9a8c"}, {"id": 412994, "book_url": "\u7eb8\u795e/412994", "title": "\u7b2c\u4e09\u5341\u56db\u7ae0\uff1a\u6f5c\u5165"}, {"id": 412991, "book_url": "\u7eb8\u795e/412991", "title": "\u7b2c\u4e09\u5341\u4e00\u7ae0:\u4efb\u52a1"}, {"id": 412995, "book_url": "\u7eb8\u795e/412995", "title": "\u7b2c\u4e09\u5341\u4e94\u7ae0\uff1a\u5077\u7a83"}, {"id": 412992, "book_url": "\u7eb8\u795e/412992", "title": "\u7b2c\u4e09\u5341\u4e8c\u7ae0\uff1a\u5200\u67aa"}, {"id": 412996, "book_url": "\u7eb8\u795e/412996", "title": "\u7b2c\u4e09\u5341\u516d\u7ae0\uff1a\u56de\u5bb6"}, {"id": 412993, "book_url": "\u7eb8\u795e/412993", "title": "\u7b2c\u4e09\u5341\u4e09\u7ae0\uff1a\u9634\u9669"}, {"id": 412997, "book_url": "\u7eb8\u795e/412997", "title": "\u7b2c\u4e09\u5341\u4e03\u7ae0:\u6697\u6f6e"}, {"id": 412998, "book_url": "\u7eb8\u795e/412998", "title": "\u7b2c\u4e09\u5341\u516b\u7ae0:\u7838\u644a"}, {"id": 413002, "book_url": "\u7eb8\u795e/413002", "title": "\u7b2c\u56db\u5341\u4e8c\u7ae0\uff1a\u9707\u60ca"}, {"id": 412999, "book_url": "\u7eb8\u795e/412999", "title": "\u7b2c\u4e09\u5341\u4e5d\u7ae0\uff1a\u518d\u89c1"}, {"id": 413003, "book_url": "\u7eb8\u795e/413003", "title": "\u7b2c\u56db\u5341\u4e09\u7ae0:\u5e78\u8fd0"}, {"id": 413000, "book_url": "\u7eb8\u795e/413000", "title": "\u7b2c\u56db\u5341\u7ae0\uff1a\u74f6\u9888"}, {"id": 413004, "book_url": "\u7eb8\u795e/413004", "title": "\u7b2c\u56db\u5341\u56db\u7ae0\uff1a\u65ad\u7edd"}, {"id": 413001, "book_url": "\u7eb8\u795e/413001", "title": "\u7b2c\u56db\u5341\u4e00\u7ae0:\u80fd\u529b"}, {"id": 413005, "book_url": "\u7eb8\u795e/413005", "title": "\u7b2c\u56db\u5341\u4e94\u7ae0:\u62cd\u82b1"}, {"id": 413006, "book_url": "\u7eb8\u795e/413006", "title": "\u7b2c\u56db\u5341\u516d\u7ae0\uff1a\u975e\u793c"}, {"id": 413010, "book_url": "\u7eb8\u795e/413010", "title": "\u7b2c\u4e94\u5341\u7ae0\uff1a\u65e0\u60c5"}, {"id": 413007, "book_url": "\u7eb8\u795e/413007", "title": "\u7b2c\u56db\u5341\u4e03\u7ae0\uff1a\u94ed\u8bb0"}, {"id": 413011, "book_url": "\u7eb8\u795e/413011", "title": "\u7b2c\u4e94\u5341\u4e00\u7ae0\uff1a\u8840\u8272"}, {"id": 413008, "book_url": "\u7eb8\u795e/413008", "title": "\u7b2c\u56db\u5341\u516b\u7ae0:\u65e0\u5984"}, {"id": 413012, "book_url": "\u7eb8\u795e/413012", "title": "\u7b2c\u4e94\u5341\u4e8c\u7ae0\uff1a\u8ffd\u88ad"}, {"id": 413009, "book_url": "\u7eb8\u795e/413009", "title": "\u7b2c\u56db\u5341\u4e5d\u7ae0\uff1a\u65e0\u8f9c"}, {"id": 413013, "book_url": "\u7eb8\u795e/413013", "title": "\u7b2c\u4e94\u5341\u4e09\u7ae0:\u793c\u82b1"}, {"id": 413014, "book_url": "\u7eb8\u795e/413014", "title": "\u7b2c\u4e94\u5341\u56db\u7ae0:\u5984\u4e3a"}, {"id": 413018, "book_url": "\u7eb8\u795e/413018", "title": "\u7b2c\u4e94\u5341\u516b\u7ae0\uff1a\u727a\u7272"}, {"id": 413015, "book_url": "\u7eb8\u795e/413015", "title": "\u7b2c\u4e94\u5341\u4e94\u7ae0:\u8868\u767d"}, {"id": 413019, "book_url": "\u7eb8\u795e/413019", "title": "\u7b2c\u4e94\u5341\u4e5d\u7ae0\uff1a\u9752\u6728"}, {"id": 413016, "book_url": "\u7eb8\u795e/413016", "title": "\u7b2c\u4e94\u5341\u516d\u7ae0\uff1a\u66b4\u6012"}, {"id": 413020, "book_url": "\u7eb8\u795e/413020", "title": "\u7b2c\u516d\u5341\u7ae0\uff1a\u4f0f\u51fb"}, {"id": 413017, "book_url": "\u7eb8\u795e/413017", "title": "\u7b2c\u4e94\u5341\u4e03\u7ae0\uff1a\u6076\u9b54"}, {"id": 413021, "book_url": "\u7eb8\u795e/413021", "title": "\u7b2c\u516d\u5341\u4e00\u7ae0\uff1a\u5e78\u8fd0"}, {"id": 413022, "book_url": "\u7eb8\u795e/413022", "title": "\u7b2c\u516d\u5341\u4e8c\u7ae0:\u91d1\u77f3"}, {"id": 413026, "book_url": "\u7eb8\u795e/413026", "title": "\u7b2c\u516d\u5341\u516d\u7ae0\uff1a\u5177\u8c61"}, {"id": 413023, "book_url": "\u7eb8\u795e/413023", "title": "\u7b2c\u516d\u5341\u4e09\u7ae0\uff1a\u7ae5\u771f"}, {"id": 413027, "book_url": "\u7eb8\u795e/413027", "title": "\u7b2c\u516d\u5341\u4e03\u7ae0\uff1a\u914d\u5408"}, {"id": 413024, "book_url": "\u7eb8\u795e/413024", "title": "\u7b2c\u516d\u5341\u56db\u7ae0\uff1a\u906d\u9047"}, {"id": 413028, "book_url": "\u7eb8\u795e/413028", "title": "\u7b2c\u516d\u5341\u516b\u7ae0\uff1a\u4ec7\u6068\u2014\u2014\u7b2c\u4e8c\u5377\u7ec8"}, {"id": 413025, "book_url": "\u7eb8\u795e/413025", "title": "\u7b2c\u516d\u5341\u4e94\u7ae0\uff1a\u795e\u5175"}, {"id": 413029, "book_url": "\u7eb8\u795e/413029", "title": "\u7b2c\u516d\u5341\u4e5d\u7ae0\uff1a\u5217\u8f66"}, {"id": 413030, "book_url": "\u7eb8\u795e/413030", "title": "\u7b2c\u4e03\u5341\u7ae0:\u4eb2\u621a"}, {"id": 413034, "book_url": "\u7eb8\u795e/413034", "title": "\u7b2c\u4e03\u5341\u56db\u7ae0\uff1a\u8f6e\u56de"}, {"id": 413031, "book_url": "\u7eb8\u795e/413031", "title": "\u7b2c\u4e03\u5341\u4e00\u7ae0\uff1a\u805a\u5934"}, {"id": 413035, "book_url": "\u7eb8\u795e/413035", "title": "\u7b2c\u4e03\u5341\u4e94\u7ae0\uff1a\u865a\u5047"}, {"id": 413032, "book_url": "\u7eb8\u795e/413032", "title": "\u7b2c\u4e03\u5341\u4e8c\u7ae0\uff1a\u5c40\u52bf"}, {"id": 413036, "book_url": "\u7eb8\u795e/413036", "title": "\u7b2c\u4e03\u5341\u516d\u7ae0\uff1a\u8ddf\u8e2a"}, {"id": 413033, "book_url": "\u7eb8\u795e/413033", "title": "\u7b2c\u4e03\u5341\u4e09\u7ae0\uff1a\u89c4\u5219"}, {"id": 413037, "book_url": "\u7eb8\u795e/413037", "title": "\u7b2c\u4e03\u5341\u4e03\u7ae0\uff1a\u72d9\u51fb"}, {"id": 413038, "book_url": "\u7eb8\u795e/413038", "title": "\u7b2c\u4e03\u5341\u516b\u7ae0:\u72c2\u5954"}, {"id": 413042, "book_url": "\u7eb8\u795e/413042", "title": "\u7b2c\u516b\u5341\u4e8c\u7ae0:\u852c\u83dc"}, {"id": 413039, "book_url": "\u7eb8\u795e/413039", "title": "\u7b2c\u4e03\u5341\u4e5d\u7ae0\uff1a\u534f\u8bae"}, {"id": 413043, "book_url": "\u7eb8\u795e/413043", "title": "\u7b2c\u516b\u5341\u4e09\u7ae0:\u732b\u5973"}, {"id": 413040, "book_url": "\u7eb8\u795e/413040", "title": "\u7b2c\u516b\u5341\u7ae0\uff1a\u6253\u624b"}, {"id": 413044, "book_url": "\u7eb8\u795e/413044", "title": "\u7b2c\u516b\u5341\u56db\u7ae0\uff1a\u9017\u732b"}, {"id": 413041, "book_url": "\u7eb8\u795e/413041", "title": "\u7b2c\u516b\u5341\u4e00\u7ae0\uff1a\u6df7\u6df7"}, {"id": 413045, "book_url": "\u7eb8\u795e/413045", "title": "\u7b2c\u516b\u5341\u4e94\u7ae0\uff1a\u5b50\u5f39"}, {"id": 413046, "book_url": "\u7eb8\u795e/413046", "title": "\u7b2c\u516b\u5341\u516d\u7ae0\uff1a\u6551\u547d"}, {"id": 413050, "book_url": "\u7eb8\u795e/413050", "title": "\u7b2c\u4e5d\u5341\u7ae0:\u8bd5\u63a2"}, {"id": 413047, "book_url": "\u7eb8\u795e/413047", "title": "\u7b2c\u516b\u5341\u4e03\u7ae0\uff1a\u56de\u5fc6"}, {"id": 413051, "book_url": "\u7eb8\u795e/413051", "title": "\u7b2c\u4e5d\u5341\u4e00\u7ae0\uff1a\u5206\u6563"}, {"id": 413048, "book_url": "\u7eb8\u795e/413048", "title": "\u7b2c\u516b\u5341\u516b\u7ae0\uff1a\u4f0f\u51fb"}, {"id": 413052, "book_url": "\u7eb8\u795e/413052", "title": "\u7b2c\u4e5d\u5341\u4e8c\u7ae0\uff1a\u4e0d\u653b"}, {"id": 413049, "book_url": "\u7eb8\u795e/413049", "title": "\u7b2c\u516b\u5341\u4e5d\u7ae0\uff1a\u878d\u5316"}, {"id": 413053, "book_url": "\u7eb8\u795e/413053", "title": "\u7b2c\u4e5d\u5341\u4e09\u7ae0\uff1a\u81ea\u7834"}, {"id": 413054, "book_url": "\u7eb8\u795e/413054", "title": "\u7b2c\u4e5d\u5341\u56db\u7ae0\uff1a\u8840\u6db2"}, {"id": 413058, "book_url": "\u7eb8\u795e/413058", "title": "\u7b2c\u4e5d\u5341\u516b\u7ae0:\u76f8\u4f3c"}, {"id": 413055, "book_url": "\u7eb8\u795e/413055", "title": "\u7b2c\u4e5d\u5341\u4e94\u7ae0\uff1a\u91d1\u5c5e"}, {"id": 413059, "book_url": "\u7eb8\u795e/413059", "title": "\u7b2c\u4e5d\u5341\u4e5d\u7ae0\uff1a\u91cd\u751f"}, {"id": 413056, "book_url": "\u7eb8\u795e/413056", "title": "\u7b2c\u4e5d\u5341\u516d\u7ae0\uff1a\u996d\u6876"}, {"id": 413060, "book_url": "\u7eb8\u795e/413060", "title": "\u7b2c\u4e00\u767e\u7ae0\uff1a\u7fc1\u5a7f"}, {"id": 413057, "book_url": "\u7eb8\u795e/413057", "title": "\u7b2c\u4e5d\u5341\u4e03\u7ae0\uff1a\u6539\u53d8"}, {"id": 413061, "book_url": "\u7eb8\u795e/413061", "title": "\u7b2c\u4e00\u96f6\u4e00\u7ae0:\u9009\u62e9"}, {"id": 413062, "book_url": "\u7eb8\u795e/413062", "title": "\u7b2c\u4e00\u96f6\u4e8c\u7ae0\uff1a\u72b6\u5143"}, {"id": 413066, "book_url": "\u7eb8\u795e/413066", "title": "\u7b2c\u4e00\u96f6\u516d\u7ae0:\u518d\u89c1\u706b\u62f3"}, {"id": 413063, "book_url": "\u7eb8\u795e/413063", "title": "\u7b2c\u4e00\u96f6\u4e09\u7ae0:\u76f8\u5904"}, {"id": 413067, "book_url": "\u7eb8\u795e/413067", "title": "\u7b2c\u4e00\u96f6\u4e03\u7ae0\uff1a\u6beb\u5b85\u591c\u5bbf"}, {"id": 413064, "book_url": "\u7eb8\u795e/413064", "title": "\u7b2c\u4e00\u96f6\u56db\u7ae0\uff1a\u5ac9\u5992"}, {"id": 413068, "book_url": "\u7eb8\u795e/413068", "title": "\u7b2c\u4e00\u96f6\u516b\u7ae0\uff1a\u5371\u9669\u63a5\u8fd1"}, {"id": 413065, "book_url": "\u7eb8\u795e/413065", "title": "\u7b2c\u4e00\u96f6\u4e94\u7ae0\uff1a\u521d\u5230\u4e91\u57ce"}, {"id": 413069, "book_url": "\u7eb8\u795e/413069", "title": "\u7b2c\u4e00\u767e\u96f6\u4e5d\u7ae0\uff1a\u706f\u5854\u6548\u5e94"}, {"id": 413070, "book_url": "\u7eb8\u795e/413070", "title": "\u7b2c\u4e00\u4e00\u96f6\u7ae0\uff1a\u6db2\u6001\u602a\u4eba&\u516c\u544a"}, {"id": 413074, "book_url": "\u7eb8\u795e/413074", "title": "\u7b2c\u4e00\u4e00\u56db\u7ae0\uff1a\u6f5c\u60a0\u632f\u5200"}, {"id": 413071, "book_url": "\u7eb8\u795e/413071", "title": "\u7b2c\u4e00\u4e00\u4e00\u7ae0\uff1a\u96c6\u4f53\u6f5c\u5165"}, {"id": 413075, "book_url": "\u7eb8\u795e/413075", "title": "\u7b2c\u4e00\u4e00\u4e94\u7ae0\uff1a\u843d\u8352\u800c\u9003"}, {"id": 413072, "book_url": "\u7eb8\u795e/413072", "title": "\u7b2c\u4e00\u4e00\u4e8c\u7ae0\uff1a\u53cc\u91cd\u8be1\u8ba1"}, {"id": 413076, "book_url": "\u7eb8\u795e/413076", "title": "\u7b2c\u4e00\u4e00\u516d\u7ae0\uff1a\u4fdd\u62a4\u534f\u5b9a"}, {"id": 413073, "book_url": "\u7eb8\u795e/413073", "title": "\u7b2c\u4e00\u4e00\u4e09\u7ae0\uff1a\u53cc\u4eba\u5408\u4f53"}, {"id": 413077, "book_url": "\u7eb8\u795e/413077", "title": "\u7b2c\u4e00\u4e00\u4e03\u7ae0\uff1a\u4f2f\u4f84\u76f8\u89c1"}, {"id": 413078, "book_url": "\u7eb8\u795e/413078", "title": "\u7b2c\u4e00\u4e00\u516b\u7ae0\uff1a\u4fdd\u9556\u62a5\u9053"}, {"id": 413082, "book_url": "\u7eb8\u795e/413082", "title": "\u7b2c\u4e00\u4e8c\u4e8c\u7ae0\uff1a\u7eb8\u9e64\u5f15\u8def"}, {"id": 413079, "book_url": "\u7eb8\u795e/413079", "title": "\u7b2c\u4e00\u4e00\u4e5d\u7ae0\uff1a\u81ea\u7531\u9633\u5149"}, {"id": 413083, "book_url": "\u7eb8\u795e/413083", "title": "\u7b2c\u4e00\u4e8c\u4e09\u7ae0\uff1a\u6a2a\u751f\u6ce2\u6298"}, {"id": 413080, "book_url": "\u7eb8\u795e/413080", "title": "\u7b2c\u4e00\u4e8c\u96f6\u7ae0\uff1a\u65b0\u7684\u51b3\u5b9a"}, {"id": 413084, "book_url": "\u7eb8\u795e/413084", "title": "\u7b2c\u4e00\u4e8c\u56db\u7ae0\uff1a\u7a7a\u4e2d\u8ffd\u51fb"}, {"id": 413081, "book_url": "\u7eb8\u795e/413081", "title": "\u7b2c\u4e00\u4e8c\u4e00\u7ae0\uff1a\u7b2c\u4e8c\u5206\u8eab"}, {"id": 413085, "book_url": "\u7eb8\u795e/413085", "title": "\u7b2c\u4e00\u4e8c\u4e94\u7ae0\uff1a\u8131\u7ebf\u7eb8\u9e64"}, {"id": 413086, "book_url": "\u7eb8\u795e/413086", "title": "\u7b2c\u4e00\u4e8c\u516d\u7ae0\uff1a\u9707\u64bc\u8fde\u8fde"}, {"id": 413090, "book_url": "\u7eb8\u795e/413090", "title": "\u7b2c\u4e00\u4e09\u96f6\u7ae0\uff1a\u59d0\u59d0\u5927\u4eba"}, {"id": 413087, "book_url": "\u7eb8\u795e/413087", "title": "\u7b2c\u4e00\u4e8c\u4e03\u7ae0:\u4f2f\u7236\u53ec\u5524"}, {"id": 413091, "book_url": "\u7eb8\u795e/413091", "title": "\u7b2c\u4e00\u4e09\u4e00\u7ae0\uff1a\u9e3f\u56fe\u5802\u5144"}, {"id": 413088, "book_url": "\u7eb8\u795e/413088", "title": "\u7b2c\u4e00\u4e8c\u516b\u7ae0\uff1a\u5c71\u96e8\u6b32\u6765"}, {"id": 413092, "book_url": "\u7eb8\u795e/413092", "title": "\u7b2c\u4e00\u4e09\u4e8c\u7ae0\uff1a\u9633\u5149\u6d88\u878d"}, {"id": 413089, "book_url": "\u7eb8\u795e/413089", "title": "\u7b2c\u4e00\u4e8c\u4e5d\u7ae0:\u76f4\u9762\u9752\u53d4"}, {"id": 413093, "book_url": "\u7eb8\u795e/413093", "title": "\u7b2c\u4e00\u4e09\u4e09\u7ae0:\u9488\u950b\u76f8\u5bf9"}, {"id": 413094, "book_url": "\u7eb8\u795e/413094", "title": "\u7b2c\u4e00\u4e09\u56db\u7ae0:\u5bb6\u4f20\u6f14\u6280"}, {"id": 413098, "book_url": "\u7eb8\u795e/413098", "title": "\u7b2c\u4e00\u4e09\u516b\u7ae0\uff1a\u795e\u5175\u4ed3\u5e93"}, {"id": 413095, "book_url": "\u7eb8\u795e/413095", "title": "\u7b2c\u4e00\u4e09\u4e94\u7ae0:\u5200\u950b\u6218\u58eb"}, {"id": 413099, "book_url": "\u7eb8\u795e/413099", "title": "\u7b2c\u4e00\u4e09\u4e5d\u7ae0\uff1a\u795e\u5175\u8bb2\u5ea7"}, {"id": 413096, "book_url": "\u7eb8\u795e/413096", "title": "\u7b2c\u4e00\u4e09\u516d\u7ae0\uff1a\u5200\u7247\u7eb8\u724c"}, {"id": 413100, "book_url": "\u7eb8\u795e/413100", "title": "\u7b2c\u4e00\u56db\u96f6\u7ae0\uff1a\u8d85\u7ea7\u731c\u60f3"}, {"id": 413097, "book_url": "\u7eb8\u795e/413097", "title": "\u7b2c\u4e00\u4e09\u4e03\u7ae0\uff1a\u4e5d\u5341\u4e5d\u5203"}, {"id": 413101, "book_url": "\u7eb8\u795e/413101", "title": "\u7b2c\u4e00\u56db\u4e00\u7ae0\uff1a\u6211\u7684\u795e\u5175"}, {"id": 413102, "book_url": "\u7eb8\u795e/413102", "title": "\u7b2c\u4e00\u56db\u4e8c\u7ae0\uff1a\u65b0\u7684\u4fdd\u9556"}, {"id": 413106, "book_url": "\u7eb8\u795e/413106", "title": "\u7b2c\u4e00\u56db\u516d\u7ae0\uff1a\u98de\u884c\u68a6\u60f3"}, {"id": 413103, "book_url": "\u7eb8\u795e/413103", "title": "\u7b2c\u4e00\u56db\u4e09\u7ae0\uff1a\u771f\u5047\u96be\u8fa8"}, {"id": 413107, "book_url": "\u7eb8\u795e/413107", "title": "\u7b2c\u4e00\u56db\u4e03\u7ae0\uff1a\u6355\u6d77\u4e1c\u9752"}, {"id": 413104, "book_url": "\u7eb8\u795e/413104", "title": "\u7b2c\u4e00\u56db\u56db\u7ae0\uff1a\u7ec4\u5efa\u90e8\u961f"}, {"id": 413108, "book_url": "\u7eb8\u795e/413108", "title": "\u7b2c\u4e00\u56db\u516b\u7ae0\uff1a\u7a7a\u6218\u5e8f\u66f2"}, {"id": 413105, "book_url": "\u7eb8\u795e/413105", "title": "\u7b2c\u4e00\u56db\u4e94\u7ae0\uff1a\u7a0b\u5e08\u89e3\u8ff7"}, {"id": 413109, "book_url": "\u7eb8\u795e/413109", "title": "\u7b2c\u4e00\u56db\u4e5d\u7ae0\uff1a\u4e71\u6597\u5f00\u59cb"}, {"id": 413110, "book_url": "\u7eb8\u795e/413110", "title": "\u7b2c\u4e00\u4e94\u96f6\u7ae0\uff1a\u534a\u4e2a\u6d88\u606f"}, {"id": 413114, "book_url": "\u7eb8\u795e/413114", "title": "\u7b2c\u4e00\u4e94\u56db\u7ae0\uff1a\u5f3a\u5f3a\u5bf9\u9635"}, {"id": 413111, "book_url": "\u7eb8\u795e/413111", "title": "\u7b2c\u4e00\u4e94\u4e00\u7ae0\uff1a\u6b63\u9762\u5bf9\u654c"}, {"id": 413115, "book_url": "\u7eb8\u795e/413115", "title": "\u7b2c\u4e00\u4e94\u4e94\u7ae0\uff1a\u5408\u4f53\u6218\u672f"}, {"id": 413112, "book_url": "\u7eb8\u795e/413112", "title": "\u7b2c\u4e00\u4e94\u4e8c\u7ae0\uff1a\u62a5\u7eb8\u8840\u6848"}, {"id": 413116, "book_url": "\u7eb8\u795e/413116", "title": "\u7b2c\u4e00\u4e94\u516d\u7ae0\uff1a\u7834\u683c\u5f55\u53d6"}, {"id": 413113, "book_url": "\u7eb8\u795e/413113", "title": "\u7b2c\u4e00\u4e94\u4e09\u7ae0\uff1a\u4e39\u9876\u767d\u9e64"}, {"id": 413117, "book_url": "\u7eb8\u795e/413117", "title": "\u7b2c\u4e00\u4e94\u4e03\u7ae0\uff1a\u7ecf\u8425\u7231\u60c5"}, {"id": 413118, "book_url": "\u7eb8\u795e/413118", "title": "\u7b2c\u4e00\u4e94\u516b\u7ae0:\u4eba\u9f20\u5927\u6218"}, {"id": 413122, "book_url": "\u7eb8\u795e/413122", "title": "\u7b2c\u4e00\u516d\u4e8c\u7ae0\uff1a\u592a\u516c\u9493\u9c7c"}, {"id": 413119, "book_url": "\u7eb8\u795e/413119", "title": "\u7b2c\u4e00\u4e94\u4e5d\u7ae0\uff1a\u51f6\u795e\u795e\u5175"}, {"id": 413123, "book_url": "\u7eb8\u795e/413123", "title": "\u7b2c\u4e00\u516d\u4e09\u7ae0:\u79d8\u7c4d\u8d29\u5b50"}, {"id": 413120, "book_url": "\u7eb8\u795e/413120", "title": "\u7b2c\u4e00\u516d\u96f6\u7ae0\uff1a\u5584\u826f\u7684\u5fc3"}, {"id": 413124, "book_url": "\u7eb8\u795e/413124", "title": "\u7b2c\u4e00\u516d\u56db\u7ae0:\u9e3f\u56fe\u79d8\u8ba1"}, {"id": 413121, "book_url": "\u7eb8\u795e/413121", "title": "\u7b2c\u4e00\u516d\u4e00\u7ae0:\u4e92\u76f8\u8bd5\u63a2"}, {"id": 413125, "book_url": "\u7eb8\u795e/413125", "title": "\u7b2c\u4e00\u516d\u4e94\u7ae0\uff1a\u706b\u8f66\u7591\u4e91"}, {"id": 413126, "book_url": "\u7eb8\u795e/413126", "title": "\u7b2c\u4e00\u516d\u516d\u7ae0\uff1a\u81f4\u547d\u9677\u9631"}, {"id": 413130, "book_url": "\u7eb8\u795e/413130", "title": "\u7b2c\u4e00\u4e03\u96f6\u7ae0\uff1a\u795e\u79d8\u4e58\u5ba2"}, {"id": 413127, "book_url": "\u7eb8\u795e/413127", "title": "\u7b2c\u4e00\u516d\u4e03\u7ae0\uff1a\u6b7b\u4ea1\u68cb\u5c40"}, {"id": 413131, "book_url": "\u7eb8\u795e/413131", "title": "\u7b2c\u4e00\u4e03\u4e00\u7ae0\uff1a\u98ce\u751f\u6c34\u8d77"}, {"id": 413128, "book_url": "\u7eb8\u795e/413128", "title": "\u7b2c\u4e00\u516d\u516b\u7ae0\uff1a\u6740\u5c40\u65e9\u73b0"}, {"id": 413132, "book_url": "\u7eb8\u795e/413132", "title": "\u7b2c\u4e00\u4e03\u4e8c\u7ae0\uff1a\u91cd\u529b\u80fd\u529b"}, {"id": 413129, "book_url": "\u7eb8\u795e/413129", "title": "\u7b2c\u4e00\u516d\u4e5d\u7ae0\uff1a\u9a6c\u524d\u5352\u5b50"}, {"id": 413133, "book_url": "\u7eb8\u795e/413133", "title": "\u7b2c\u4e00\u4e03\u4e09\u7ae0\uff1a\u97f3\u6740\u9ad8\u624b"}, {"id": 413134, "book_url": "\u7eb8\u795e/413134", "title": "\u7b2c\u4e00\u4e03\u56db\u7ae0\uff1a\u53cc\u65b9\u4f1a\u5408"}, {"id": 413138, "book_url": "\u7eb8\u795e/413138", "title": "\u7b2c\u4e00\u4e03\u516b\u7ae0\uff1a\u82e6\u8089\u4e4b\u8ba1"}, {"id": 413135, "book_url": "\u7eb8\u795e/413135", "title": "\u7b2c\u4e00\u4e03\u4e94\u7ae0\uff1a\u767d\u8863\u4e4d\u73b0"}, {"id": 413139, "book_url": "\u7eb8\u795e/413139", "title": "\u7b2c\u4e00\u4e03\u4e5d\u7ae0:\u9ed1\u8863\u4f20\u4e66"}, {"id": 413136, "book_url": "\u7eb8\u795e/413136", "title": "\u7b2c\u4e00\u4e03\u516d\u7ae0:\u9ec4\u96c0\u5728\u540e"}, {"id": 413140, "book_url": "\u7eb8\u795e/413140", "title": "\u7b2c\u4e00\u516b\u96f6\u7ae0\uff1a\u4f2f\u4f84\u591c\u8bdd"}, {"id": 413137, "book_url": "\u7eb8\u795e/413137", "title": "\u7b2c\u4e00\u4e03\u4e03\u7ae0\uff1a\u5c81\u6708\u788e\u5cb3"}, {"id": 413141, "book_url": "\u7eb8\u795e/413141", "title": "\u7b2c\u4e00\u516b\u4e00\u7ae0\uff1a\u75af\u72c2\u5ac9\u5992"}, {"id": 413142, "book_url": "\u7eb8\u795e/413142", "title": "\u7b2c\u4e00\u516b\u4e8c\u7ae0\uff1a\u4e0d\u662f\u72b9\u5927"}, {"id": 413146, "book_url": "\u7eb8\u795e/413146", "title": "\u7b2c\u4e00\u516b\u516d\u7ae0:\u7425\u73c0\u4e4b\u529b"}, {"id": 413143, "book_url": "\u7eb8\u795e/413143", "title": "\u7b2c\u4e00\u516b\u4e09\u7ae0:\u62a5\u590d\u8a93\u8a00"}, {"id": 413147, "book_url": "\u7eb8\u795e/413147", "title": "\u7b2c\u4e00\u516b\u4e03\u7ae0:\u7fbd\u9e64\u518d\u73b0"}, {"id": 413144, "book_url": "\u7eb8\u795e/413144", "title": "\u7b2c\u4e00\u516b\u56db\u7ae0:\u52ab\u6301\u65e7\u654c"}, {"id": 413148, "book_url": "\u7eb8\u795e/413148", "title": "\u7b2c\u4e00\u516b\u516b\u7ae0:\u53ef\u6015\u654c\u4eba"}, {"id": 413145, "book_url": "\u7eb8\u795e/413145", "title": "\u7b2c\u4e00\u516b\u4e94\u7ae0:\u843d\u5165\u9677\u9631"}, {"id": 413149, "book_url": "\u7eb8\u795e/413149", "title": "\u7b2c\u4e00\u516b\u4e5d\u7ae0:\u7eb8\u4e4b\u98ce\u66b4"}, {"id": 413150, "book_url": "\u7eb8\u795e/413150", "title": "\u7b2c\u4e00\u4e5d\u96f6\u7ae0:\u4eba\u975e\u8349\u6728"}, {"id": 413154, "book_url": "\u7eb8\u795e/413154", "title": "\u7b2c\u4e00\u4e5d\u56db\u7ae0\uff1a\u95f2\u8bdd\u957f\u751f"}, {"id": 413151, "book_url": "\u7eb8\u795e/413151", "title": "\u7b2c\u4e00\u4e5d\u4e00\u7ae0\uff1a\u9ed1\u8863\u5f52\u6765"}, {"id": 413155, "book_url": "\u7eb8\u795e/413155", "title": "\u7b2c\u4e00\u4e5d\u4e94\u7ae0\uff1a\u5f80\u4e8b\u60ca\u53d8"}, {"id": 413152, "book_url": "\u7eb8\u795e/413152", "title": "\u7b2c\u4e00\u4e5d\u4e8c\u7ae0\uff1a\u9ad8\u624b\u4e4b\u6218"}, {"id": 413156, "book_url": "\u7eb8\u795e/413156", "title": "\u7b2c\u4e00\u4e5d\u516d\u7ae0\uff1a\u9648\u7267\u5f52\u987a"}, {"id": 413153, "book_url": "\u7eb8\u795e/413153", "title": "\u7b2c\u4e00\u4e5d\u4e09\u7ae0\uff1a\u522b\u6765\u65e0\u6059"}, {"id": 413157, "book_url": "\u7eb8\u795e/413157", "title": "\u7b2c\u4e00\u4e5d\u4e03\u7ae0\uff1a\u4f2f\u4f84\u4e4b\u60c5"}, {"id": 413158, "book_url": "\u7eb8\u795e/413158", "title": "\u7b2c\u4e00\u4e5d\u516b\u7ae0\uff1a\u73cd\u7231\u4e4b\u7269"}, {"id": 413162, "book_url": "\u7eb8\u795e/413162", "title": "\u7b2c\u4e8c\u96f6\u4e8c\u7ae0\uff1a\u51e4\u7ffc\u6765\u5386"}, {"id": 413159, "book_url": "\u7eb8\u795e/413159", "title": "\u7b2c\u4e00\u4e5d\u4e5d\u7ae0\uff1a\u8ff7\u79bb\u4e4b\u68a6"}, {"id": 413163, "book_url": "\u7eb8\u795e/413163", "title": "\u7b2c\u4e8c\u96f6\u4e09\u7ae0\uff1a\u8001\u56db\u8715\u53d8"}, {"id": 413160, "book_url": "\u7eb8\u795e/413160", "title": "\u7b2c\u4e8c\u96f6\u96f6\u7ae0\uff1a\u7cbe\u795e\u9677\u9631"}, {"id": 413164, "book_url": "\u7eb8\u795e/413164", "title": "\u7b2c\u4e8c\u96f6\u56db\u7ae0\uff1a\u4f63\u5175\u516c\u4f1a"}, {"id": 413161, "book_url": "\u7eb8\u795e/413161", "title": "\u7b2c\u4e8c\u96f6\u4e00\u7ae0\uff1a\u539f\u6765\u662f\u4f60"}, {"id": 413165, "book_url": "\u7eb8\u795e/413165", "title": "\u7b2c\u4e8c\u96f6\u4e94\u7ae0\uff1a\u6258\u7ba1\u9633\u5149"}, {"id": 413166, "book_url": "\u7eb8\u795e/413166", "title": "\u7b2c\u4e8c\u96f6\u516d\u7ae0\uff1a\u8fd8\u6709\u68a6\u60f3"}, {"id": 413170, "book_url": "\u7eb8\u795e/413170", "title": "\u7b2c\u4e8c\u4e00\u96f6\u7ae0\uff1a\u7eb8\u9e64\u79bb\u6731"}, {"id": 413167, "book_url": "\u7eb8\u795e/413167", "title": "\u7b2c\u4e8c\u96f6\u4e03\u7ae0\uff1a\u732b\u5973\u518d\u73b0"}, {"id": 413171, "book_url": "\u7eb8\u795e/413171", "title": "\u7b2c\u4e8c\u4e00\u4e00\u7ae0\uff1a\u56db\u89d2\u5173\u7cfb"}, {"id": 413168, "book_url": "\u7eb8\u795e/413168", "title": "\u7b2c\u4e8c\u96f6\u516b\u7ae0\uff1a\u4ebf\u4e07\u8d4f\u91d1"}, {"id": 413172, "book_url": "\u7eb8\u795e/413172", "title": "\u7b2c\u4e8c\u4e00\u4e8c\u7ae0\uff1a\u732b\u5973\u4e4b\u4f24"}, {"id": 413169, "book_url": "\u7eb8\u795e/413169", "title": "\u7b2c\u4e8c\u96f6\u4e5d\u7ae0\uff1a\u56fd\u9645\u53cb\u4eba"}, {"id": 413173, "book_url": "\u7eb8\u795e/413173", "title": "\u7b2c\u4e8c\u4e00\u4e09\u7ae0\uff1a\u6fc0\u70c8\u4e89\u8bba"}, {"id": 413174, "book_url": "\u7eb8\u795e/413174", "title": "\u7b2c\u4e8c\u4e00\u56db\u7ae0\uff1a\u5177\u8c61\u80fd\u529b"}, {"id": 413178, "book_url": "\u7eb8\u795e/413178", "title": "\u7b2c\u4e8c\u4e00\u516b\u7ae0\uff1a\u518d\u6b21\u51b2\u7a81"}, {"id": 413175, "book_url": "\u7eb8\u795e/413175", "title": "\u7b2c\u4e8c\u4e00\u4e94\u7ae0\uff1a\u81ea\u4f5c\u806a\u660e"}, {"id": 413179, "book_url": "\u7eb8\u795e/413179", "title": "\u7b2c\u4e8c\u4e00\u4e5d\u5f20\uff1a\u58f0\u4e1c\u51fb\u897f"}, {"id": 413176, "book_url": "\u7eb8\u795e/413176", "title": "\u7b2c\u4e8c\u4e00\u516d\u7ae0\uff1a\u795e\u5175\u5177\u8c61"}, {"id": 413180, "book_url": "\u7eb8\u795e/413180", "title": "\u7b2c\u4e8c\u4e8c\u96f6\u7ae0\uff1a\u795e\u5175\u5e08\u5320"}, {"id": 413177, "book_url": "\u7eb8\u795e/413177", "title": "\u7b2c\u4e8c\u4e00\u4e03\u7ae0\uff1a\u878d\u4f1a\u8d2f\u901a"}, {"id": 413181, "book_url": "\u7eb8\u795e/413181", "title": "\u7b2c\u4e8c\u4e8c\u4e00\u7ae0\uff1a\u65b0\u7684\u51b3\u5b9a"}, {"id": 413182, "book_url": "\u7eb8\u795e/413182", "title": "\u7b2c\u4e8c\u4e8c\u4e8c\u7ae0\uff1a\u51b3\u5b9a\u79bb\u5f00"}, {"id": 413186, "book_url": "\u7eb8\u795e/413186", "title": "\u7b2c\u4e8c\u4e8c\u4e03\u7ae0\uff1a\u53c2\u4e0e\u89d2\u9010"}, {"id": 413183, "book_url": "\u7eb8\u795e/413183", "title": "\u7b2c\u4e8c\u4e8c\u56db\u7ae0\uff1a\u56de\u4e61\u8ba1\u5212"}, {"id": 413187, "book_url": "\u7eb8\u795e/413187", "title": "\u7b2c\u4e8c\u4e8c\u516b\u7ae0\uff1a\u6539\u5934\u6362\u9762"}, {"id": 413184, "book_url": "\u7eb8\u795e/413184", "title": "\u7b2c\u4e8c\u4e8c\u4e94\u7ae0\uff1a\u5404\u81ea\u53d1\u5c55"}, {"id": 413188, "book_url": "\u7eb8\u795e/413188", "title": "\u7b2c\u4e8c\u4e8c\u4e5d\u7ae0\uff1a\u6c7d\u8f66\u98de\u884c"}, {"id": 413185, "book_url": "\u7eb8\u795e/413185", "title": "\u7b2c\u4e8c\u4e8c\u516d\u7ae0\uff1a\u795e\u4e4b\u4e00\u6b65"}, {"id": 413189, "book_url": "\u7eb8\u795e/413189", "title": "\u7b2c\u4e8c\u4e09\u96f6\u7ae0\uff1a\u6700\u7ec8\u5e7b\u60f3"}, {"id": 413190, "book_url": "\u7eb8\u795e/413190", "title": "\u7b2c\u4e8c\u4e09\u4e00\u7ae0\uff1a\u5404\u6709\u5947\u62db"}, {"id": 413194, "book_url": "\u7eb8\u795e/413194", "title": "\u7b2c\u4e8c\u4e09\u4e94\u7ae0\uff1a\u8fdb\u5316\u4e4b\u59cb"}, {"id": 413191, "book_url": "\u7eb8\u795e/413191", "title": "\u7b2c\u4e8c\u4e09\u4e8c\u7ae0\uff1a\u4e00\u8a00\u4e0d\u5408"}, {"id": 413195, "book_url": "\u7eb8\u795e/413195", "title": "\u7b2c\u4e8c\u4e09\u516d\u7ae0\uff1a\u5168\u5458\u4f1a\u548c"}, {"id": 413192, "book_url": "\u7eb8\u795e/413192", "title": "\u7b2c\u4e8c\u4e09\u4e09\u7ae0\uff1a\u706b\u7130\u4e4b\u9f99"}, {"id": 413196, "book_url": "\u7eb8\u795e/413196", "title": "\u7b2c\u4e8c\u4e09\u4e03\u7ae0\uff1a\u9b42\u4e4b\u633d\u6b4c"}, {"id": 413193, "book_url": "\u7eb8\u795e/413193", "title": "\u7b2c\u4e8c\u4e09\u56db\u7ae0\uff1a\u7cbe\u795e\u7a7a\u95f4"}, {"id": 413197, "book_url": "\u7eb8\u795e/413197", "title": "\u7b2c\u4e8c\u4e09\u516b\u7ae0\uff1a\u56de\u5230\u8001\u57ce"}, {"id": 413198, "book_url": "\u7eb8\u795e/413198", "title": "\u7b2c\u4e8c\u4e09\u4e5d\u7ae0\uff1a\u7236\u4eb2\u7684\u4fe1"}, {"id": 413202, "book_url": "\u7eb8\u795e/413202", "title": "\u7b2c\u4e8c\u56db\u4e09\u7ae0\uff1a\u9ad8\u624b\u8fed\u51fa"}, {"id": 413199, "book_url": "\u7eb8\u795e/413199", "title": "\u7b2c\u4e8c\u56db\u96f6\u7ae0\uff1a\u4e8b\u60c5\u59cb\u672b"}, {"id": 413203, "book_url": "\u7eb8\u795e/413203", "title": "\u7b2c\u4e8c\u56db\u56db\u7ae0\uff1a\u62dc\u796d\u7236\u6bcd"}, {"id": 413200, "book_url": "\u7eb8\u795e/413200", "title": "\u7b2c\u4e8c\u56db\u4e00\u7ae0\uff1a\u4f17\u77e2\u4e4b\u7684"}, {"id": 413204, "book_url": "\u7eb8\u795e/413204", "title": "\u7b2c\u4e8c\u56db\u4e94\u7ae0\uff1a\u5144\u957f\u4e4b\u5893"}, {"id": 413201, "book_url": "\u7eb8\u795e/413201", "title": "\u7b2c\u4e8c\u56db\u4e8c\u7ae0\uff1a\u5343\u94a7\u4e00\u53d1"}, {"id": 413205, "book_url": "\u7eb8\u795e/413205", "title": "\u7b2c\u4e8c\u56db\u516d\u7ae0\uff1a\u6d17\u52ab\u5144\u957f"}, {"id": 413206, "book_url": "\u7eb8\u795e/413206", "title": "\u7b2c\u4e8c\u56db\u4e03\u7ae0\uff1a\u6df7\u4e71\u5893\u5ba4"}, {"id": 413210, "book_url": "\u7eb8\u795e/413210", "title": "\u7b2c\u4e8c\u4e94\u4e00\u7ae0\uff1a\u7ed1\u67b6\u5f1f\u5f1f"}, {"id": 413207, "book_url": "\u7eb8\u795e/413207", "title": "\u7b2c\u4e8c\u56db\u516b\u7ae0\uff1a\u7a81\u7834\u77f3\u5ba4"}, {"id": 413211, "book_url": "\u7eb8\u795e/413211", "title": "\u7b2c\u4e8c\u4e94\u4e8c\u7ae0\uff1a\u9065\u8fdc\u7684\u7231"}, {"id": 413208, "book_url": "\u7eb8\u795e/413208", "title": "\u7b2c\u4e8c\u56db\u4e5d\u7ae0\uff1a\u9ad8\u624b\u6742\u70e9"}, {"id": 413212, "book_url": "\u7eb8\u795e/413212", "title": "\u7b2c\u4e8c\u4e94\u4e09\u7ae0\uff1a\u540c\u4f4d\u5f02\u4f53"}, {"id": 413209, "book_url": "\u7eb8\u795e/413209", "title": "\u7b2c\u4e8c\u4e94\u96f6\u7ae0\uff1a\u62b9\u6740\u65f6\u95f4"}, {"id": 413213, "book_url": "\u7eb8\u795e/413213", "title": "\u7b2c\u4e8c\u4e94\u56db\u7ae0\uff1a\u91d1\u94c1\u62a5\u540d"}, {"id": 413214, "book_url": "\u7eb8\u795e/413214", "title": "\u7b2c\u4e8c\u4e94\u4e94\u7ae0\uff1a\u6f5c\u60a0\u5f52\u6765"}, {"id": 413218, "book_url": "\u7eb8\u795e/413218", "title": "\u7b2c\u4e8c\u4e94\u4e5d\u7ae0\uff1a\u8fc7\u5206\u8ba4\u771f"}, {"id": 413215, "book_url": "\u7eb8\u795e/413215", "title": "\u7b2c\u4e8c\u4e94\u516d\u7ae0\uff1a\u53c8\u89c1\u706b\u62f3"}, {"id": 413219, "book_url": "\u7eb8\u795e/413219", "title": "\u7b2c\u4e8c\u516d\u96f6\u7ae0\uff1a\u65b0\u7684\u5b89\u6392"}, {"id": 413216, "book_url": "\u7eb8\u795e/413216", "title": "\u7b2c\u4e8c\u4e94\u4e03\u7ae0\uff1a\u4f2f\u4f84\u91ca\u5acc"}, {"id": 413220, "book_url": "\u7eb8\u795e/413220", "title": "\u7b2c\u4e8c\u516d\u4e00\u7ae0\uff1a\u6362\u5fc3\u4e4b\u6212"}, {"id": 413217, "book_url": "\u7eb8\u795e/413217", "title": "\u7b2c\u4e8c\u4e94\u516b\u7ae0\uff1a\u602a\u5f02\u5bdd\u5ba4"}, {"id": 413221, "book_url": "\u7eb8\u795e/413221", "title": "\u7b2c\u4e8c\u516d\u4e8c\u7ae0\uff1a\u518d\u9047\u6545\u4eba"}, {"id": 413222, "book_url": "\u7eb8\u795e/413222", "title": "\u7b2c\u4e8c\u516d\u4e09\u7ae0\uff1a\u9ad8\u5cf0\u5b9a\u5f8b"}, {"id": 413226, "book_url": "\u7eb8\u795e/413226", "title": "\u7b2c\u4e8c\u516d\u4e03\u7ae0\uff1a\u4e0b\u9a6c\u4e4b\u5a01"}, {"id": 413223, "book_url": "\u7eb8\u795e/413223", "title": "\u7b2c\u4e8c\u516d\u56db\u7ae0\uff1a\u706b\u62f3\u9047\u88ad"}, {"id": 413227, "book_url": "\u7eb8\u795e/413227", "title": "\u7b2c\u4e8c\u516d\u516b\u7ae0\uff1a\u4f55\u8c13\u5f3a\u8005"}, {"id": 413224, "book_url": "\u7eb8\u795e/413224", "title": "\u7b2c\u4e8c\u516d\u4e94\u7ae0\uff1a\u8f6f\u5f31\u7684\u5fc3"}, {"id": 413228, "book_url": "\u7eb8\u795e/413228", "title": "\u7b2c\u4e8c\u516d\u4e5d\u7ae0\uff1a\u81ea\u7531\u7ff1\u7fd4"}, {"id": 413225, "book_url": "\u7eb8\u795e/413225", "title": "\u7b2c\u4e8c\u516d\u516d\u7ae0\uff1a\u81ea\u89c6\u751a\u9ad8"}, {"id": 413229, "book_url": "\u7eb8\u795e/413229", "title": "\u7b2c\u4e8c\u4e03\u96f6\u7ae0\uff1a\u5c71\u95f4\u72c2\u5954"}, {"id": 413230, "book_url": "\u7eb8\u795e/413230", "title": "\u7b2c\u4e8c\u4e03\u4e00\u7ae0\uff1a\u4e71\u6597\u5f00\u59cb"}, {"id": 413234, "book_url": "\u7eb8\u795e/413234", "title": "\u7b2c\u4e8c\u4e03\u4e94\u7ae0\uff1a\u7edd\u4e0d\u9000\u7f29"}, {"id": 413231, "book_url": "\u7eb8\u795e/413231", "title": "\u7b2c\u4e8c\u4e03\u4e8c\u7ae0\uff1a\u4e0d\u8bb2\u4e49\u6c14"}, {"id": 413235, "book_url": "\u7eb8\u795e/413235", "title": "\u7b2c\u4e8c\u4e03\u516d\u7ae0\uff1a\u62d6\u5ef6\u65f6\u95f4"}, {"id": 413232, "book_url": "\u7eb8\u795e/413232", "title": "\u7b2c\u4e8c\u4e03\u4e09\u7ae0\uff1a\u96be\u4ee5\u5e73\u9759"}, {"id": 413236, "book_url": "\u7eb8\u795e/413236", "title": "\u7b2c\u4e8c\u4e03\u4e03\u7ae0\uff1a\u75af\u72c2\u8981\u6c42"}, {"id": 413233, "book_url": "\u7eb8\u795e/413233", "title": "\u7b2c\u4e8c\u4e03\u56db\u7ae0\uff1a\u8c08\u5224\u4e4b\u524d"}, {"id": 413237, "book_url": "\u7eb8\u795e/413237", "title": "\u7b2c\u4e8c\u4e03\u516b\u7ae0\uff1a\u5343\u94a7\u4e00\u53d1"}, {"id": 413238, "book_url": "\u7eb8\u795e/413238", "title": "\u7b2c\u4e8c\u4e03\u4e5d\u7ae0\uff1a\u540d\u4e3a\u6613\u4f18"}, {"id": 413242, "book_url": "\u7eb8\u795e/413242", "title": "\u7b2c\u4e8c\u516b\u4e09\u7ae0\uff1a\u81f4\u547d\u72d9\u51fb"}, {"id": 413239, "book_url": "\u7eb8\u795e/413239", "title": "\u7b2c\u4e8c\u516b\u96f6\u7ae0\uff1a\u5f62\u5f0f\u582a\u5fe7"}, {"id": 413243, "book_url": "\u7eb8\u795e/413243", "title": "\u7b2c\u4e8c\u516b\u56db\u7ae0\uff1a\u7279\u8bad\u4f0a\u59cb"}, {"id": 413240, "book_url": "\u7eb8\u795e/413240", "title": "\u7b2c\u4e8c\u516b\u4e00\u7ae0\uff1a\u7279\u8bad\u8003\u9a8c"}, {"id": 413244, "book_url": "\u7eb8\u795e/413244", "title": "\u7b2c\u4e8c\u516b\u4e94\u7ae0\uff1a\u80fd\u529b\u8fdb\u5316"}, {"id": 413241, "book_url": "\u7eb8\u795e/413241", "title": "\u7b2c\u4e8c\u516b\u4e8c\u7ae0\uff1a\u4e09\u9897\u5b50\u5f39"}, {"id": 413245, "book_url": "\u7eb8\u795e/413245", "title": "\u7b2c\u4e8c\u516b\u516d\u7ae0\uff1a\u591c\u534a\u60ca\u53d8"}, {"id": 413246, "book_url": "\u7eb8\u795e/413246", "title": "\u7b2c\u4e8c\u516b\u4e03\u7ae0\uff1a\u97f3\u6ce2\u4e4b\u6218"}, {"id": 413250, "book_url": "\u7eb8\u795e/413250", "title": "\u7b2c\u4e8c\u4e5d\u4e00\u7ae0\uff1a\u6355\u9f20\u884c\u52a8"}, {"id": 413247, "book_url": "\u7eb8\u795e/413247", "title": "\u7b2c\u4e8c\u516b\u516b\u7ae0\uff1a\u9634\u5f71\u4e4b\u7537"}, {"id": 413251, "book_url": "\u7eb8\u795e/413251", "title": "\u7b2c\u4e8c\u4e5d\u4e8c\u7ae0\uff1a\u6df1\u5165\u6d1e\u7a74"}, {"id": 413248, "book_url": "\u7eb8\u795e/413248", "title": "\u7b2c\u4e8c\u516b\u4e5d\u7ae0\uff1a\u906d\u9047\u4f0f\u5175"}, {"id": 413252, "book_url": "\u7eb8\u795e/413252", "title": "\u7b2c\u4e8c\u4e5d\u4e09\u7ae0\uff1a\u653b\u9632\u4e4b\u6218"}, {"id": 413249, "book_url": "\u7eb8\u795e/413249", "title": "\u7b2c\u4e8c\u4e5d\u96f6\u7ae0\uff1a\u5bbf\u547d\u5bf9\u51b3"}, {"id": 413253, "book_url": "\u7eb8\u795e/413253", "title": "\u7b2c\u4e8c\u4e5d\u56db\u7ae0\uff1a\u51e4\u7ffc\u65ad\u8db3"}, {"id": 413254, "book_url": "\u7eb8\u795e/413254", "title": "\u7b2c\u4e8c\u4e5d\u4e94\u7ae0\uff1a\u4e92\u76f8\u7b97\u8ba1"}, {"id": 413258, "book_url": "\u7eb8\u795e/413258", "title": "\u7b2c\u4e8c\u4e5d\u4e5d\u7ae0\uff1a\u4eba\u9020\u795e\u5175"}, {"id": 413255, "book_url": "\u7eb8\u795e/413255", "title": "\u7b2c\u4e8c\u4e5d\u516d\u7ae0\uff1a\u82b1\u94b1\u8ba1\u5212"}, {"id": 413259, "book_url": "\u7eb8\u795e/413259", "title": "\u7b2c\u4e09\u96f6\u96f6\u7ae0\uff1a\u73b0\u5b9e\u6e38\u620f"}, {"id": 413256, "book_url": "\u7eb8\u795e/413256", "title": "\u7b2c\u4e8c\u4e5d\u4e03\u7ae0\uff1a\u5f02\u80fd\u6295\u8d44"}, {"id": 413260, "book_url": "\u7eb8\u795e/413260", "title": "\u7b2c\u4e09\u96f6\u4e00\u7ae0\uff1a\u5305\u541b\u6ee1\u610f"}, {"id": 413257, "book_url": "\u7eb8\u795e/413257", "title": "\u7b2c\u4e8c\u4e5d\u516b\u7ae0\uff1a\u795e\u5175\u96be\u5f97"}, {"id": 413261, "book_url": "\u7eb8\u795e/413261", "title": "\u7b2c\u4e09\u96f6\u4e8c\u7ae0\uff1a\u4f63\u5175\u5f52\u6765"}, {"id": 413262, "book_url": "\u7eb8\u795e/413262", "title": "\u7b2c\u4e09\u96f6\u4e09\u7ae0\uff1a\u672c\u540d\u5c0f\u4e03"}, {"id": 413266, "book_url": "\u7eb8\u795e/413266", "title": "\u7b2c\u4e09\u96f6\u4e03\u7ae0\uff1a\u5347\u5b98\u53d1\u8d22"}, {"id": 413263, "book_url": "\u7eb8\u795e/413263", "title": "\u7b2c\u4e09\u96f6\u56db\u7ae0\uff1a\u91d1\u94c1\u7279\u8bad"}, {"id": 413267, "book_url": "\u7eb8\u795e/413267", "title": "\u7b2c\u4e09\u96f6\u516b\u7ae0\uff1a\u91d1\u521a\u4e4b\u609f"}, {"id": 413264, "book_url": "\u7eb8\u795e/413264", "title": "\u7b2c\u4e09\u96f6\u4e94\u7ae0\uff1a\u540c\u75c5\u76f8\u601c"}, {"id": 413268, "book_url": "\u7eb8\u795e/413268", "title": "\u7b2c\u4e09\u96f6\u4e5d\u7ae0\uff1a\u5408\u4f5c\u5927\u8ba1"}, {"id": 413265, "book_url": "\u7eb8\u795e/413265", "title": "\u7b2c\u4e09\u96f6\u516d\u7ae0\uff1a\u6551\u4eba\u4e00\u547d"}, {"id": 413269, "book_url": "\u7eb8\u795e/413269", "title": "\u7b2c\u4e09\u4e00\u96f6\u7ae0\uff1a\u795e\u5175\u730e\u624b"}, {"id": 413270, "book_url": "\u7eb8\u795e/413270", "title": "\u7b2c\u4e09\u4e00\u4e00\u7ae0\uff1a\u62cd\u5356\u6d88\u606f"}, {"id": 413274, "book_url": "\u7eb8\u795e/413274", "title": "\u7b2c\u4e09\u4e00\u4e94\u7ae0\uff1a\u8fd8\u662f\u6076\u4fd7"}, {"id": 413271, "book_url": "\u7eb8\u795e/413271", "title": "\u7b2c\u4e09\u4e00\u4e8c\u7ae0\uff1a\u76d7\u7248\u4e66\u5546"}, {"id": 413275, "book_url": "\u7eb8\u795e/413275", "title": "\u7b2c\u4e09\u4e00\u516d\u7ae0\uff1a\u795e\u5175\u5206\u88c2"}, {"id": 413272, "book_url": "\u7eb8\u795e/413272", "title": "\u7b2c\u4e09\u4e00\u4e09\u7ae0\uff1a\u795e\u4e4b\u6587\u5b57"}, {"id": 413276, "book_url": "\u7eb8\u795e/413276", "title": "\u7b2c\u4e09\u4e00\u4e03\u7ae0 \u6f5c\u5165\u8111\u57df"}, {"id": 413273, "book_url": "\u7eb8\u795e/413273", "title": "\u7b2c\u4e09\u4e00\u56db\u7ae0\uff1a\u6076\u4fd7\u6865\u6bb5"}, {"id": 413277, "book_url": "\u7eb8\u795e/413277", "title": "\u7b2c\u4e09\u4e00\u516b\u7ae0 \u4ee5\u4eba\u4e3a\u9274"}, {"id": 413278, "book_url": "\u7eb8\u795e/413278", "title": "\u7b2c\u4e09\u4e00\u4e5d\u7ae0 \u89d2\u8272\u626e\u6f14"}, {"id": 413282, "book_url": "\u7eb8\u795e/413282", "title": "\u7b2c\u4e09\u4e8c\u4e09\u7ae0\uff1a\u4fa6\u67e5\u864e\u7a74"}, {"id": 413279, "book_url": "\u7eb8\u795e/413279", "title": "\u7b2c\u4e09\u4e8c\u96f6\u7ae0 \u62a2\u52ab\u8ba1\u5212"}, {"id": 413283, "book_url": "\u7eb8\u795e/413283", "title": "\u7b2c\u4e09\u4e8c\u56db\u7ae0 \u5206\u8eab\u8fde\u63a5"}, {"id": 413280, "book_url": "\u7eb8\u795e/413280", "title": "\u7b2c\u4e09\u4e8c\u4e00\u7ae0\uff1a\u5e7d\u8c37\u4e4b\u8c1c"}, {"id": 413284, "book_url": "\u7eb8\u795e/413284", "title": "\u7b2c\u4e09\u4e8c\u4e94\u7ae0\uff1a\u5947\u602a\u80da\u80ce"}, {"id": 413281, "book_url": "\u7eb8\u795e/413281", "title": "\u7b2c\u4e09\u4e8c\u4e8c\u7ae0 \u5f3a\u608d\u79d8\u4e66"}, {"id": 413285, "book_url": "\u7eb8\u795e/413285", "title": "\u7b2c\u4e09\u4e8c\u516d\u7ae0\uff1a\u864e\u5934\u4eba\u8eab"}, {"id": 413286, "book_url": "\u7eb8\u795e/413286", "title": "\u7b2c\u4e09\u4e8c\u4e03\u7ae0\uff1a\u5f3a\u884c\u7a81\u7834"}, {"id": 413290, "book_url": "\u7eb8\u795e/413290", "title": "\u7b2c\u4e09\u4e09\u4e00\u7ae0\uff1a\u53d1\u5e03\u4efb\u52a1"}, {"id": 413287, "book_url": "\u7eb8\u795e/413287", "title": "\u7b2c\u4e09\u4e8c\u516b\u7ae0\uff1a\u5982\u864e\u6dfb\u7ffc"}, {"id": 413291, "book_url": "\u7eb8\u795e/413291", "title": "\u7b2c\u4e09\u4e09\u4e8c\u7ae0\uff1a\u591c\u8bbf\u4efb\u5e9c"}, {"id": 413288, "book_url": "\u7eb8\u795e/413288", "title": "\u7b2c\u4e09\u4e8c\u4e5d\u7ae0\uff1a\u5b89\u5168\u8fd4\u56de"}, {"id": 413292, "book_url": "\u7eb8\u795e/413292", "title": "\u7b2c\u4e09\u4e09\u4e09\u7ae0\uff1a\u62c9\u62e2\u4eba\u5fc3"}, {"id": 413289, "book_url": "\u7eb8\u795e/413289", "title": "\u7b2c\u4e09\u4e09\u96f6\u7ae0\uff1a\u7b56\u5212\u6551\u4eba"}, {"id": 413293, "book_url": "\u7eb8\u795e/413293", "title": "\u7b2c\u4e09\u4e09\u56db\u7ae0\uff1a\u5730\u4e0b\u6f5c\u5165"}, {"id": 413294, "book_url": "\u7eb8\u795e/413294", "title": "\u7b2c\u4e09\u4e09\u4e94\u7ae0\uff1a\u6210\u529f\u6551\u63f4"}, {"id": 413298, "book_url": "\u7eb8\u795e/413298", "title": "\u7b2c\u4e09\u4e09\u4e5d\u7ae0\uff1a\u70df\u96fe\u5f25\u6f2b"}, {"id": 413295, "book_url": "\u7eb8\u795e/413295", "title": "\u7b2c\u4e09\u4e09\u516d\u7ae0\uff1a\u5175\u5206\u4e24\u8def"}, {"id": 413299, "book_url": "\u7eb8\u795e/413299", "title": "\u7b2c\u4e09\u56db\u96f6\u7ae0\uff1a\u6210\u529f\u64a4\u9000"}, {"id": 413296, "book_url": "\u7eb8\u795e/413296", "title": "\u7b2c\u4e09\u4e09\u4e03\u7ae0\uff1a\u6740\u4eba\u6551\u4eba"}, {"id": 413300, "book_url": "\u7eb8\u795e/413300", "title": "\u7b2c\u4e09\u56db\u4e00\u7ae0\uff1a\u8d85\u7ea7\u9ebb\u70e6"}, {"id": 413297, "book_url": "\u7eb8\u795e/413297", "title": "\u7b2c\u4e09\u4e09\u516b\u7ae0\uff1a\u53cc\u65b9\u4f1a\u548c"}, {"id": 413301, "book_url": "\u7eb8\u795e/413301", "title": "\u7b2c\u4e09\u56db\u4e8c\u7ae0\uff1a\u6012\u65a5\u9752\u53d4"}, {"id": 413302, "book_url": "\u7eb8\u795e/413302", "title": "\u7b2c\u4e09\u56db\u4e09\u7ae0\uff1a\u4f34\u4f60\u5165\u7761"}, {"id": 413306, "book_url": "\u7eb8\u795e/413306", "title": "\u7b2c\u4e09\u56db\u4e03\u7ae0\uff1a\u5206\u5d29\u79bb\u6790"}, {"id": 413303, "book_url": "\u7eb8\u795e/413303", "title": "\u7b2c\u4e09\u56db\u56db\u7ae0\uff1a\u5e73\u9759\u5b66\u6821"}, {"id": 413307, "book_url": "\u7eb8\u795e/413307", "title": "\u7b2c\u4e09\u56db\u516b\u7ae0\uff1a\u6e38\u73a9\u524d\u5915"}, {"id": 413304, "book_url": "\u7eb8\u795e/413304", "title": "\u7b2c\u4e09\u56db\u4e94\u7ae0\uff1a\u6050\u5413\u5a01\u80c1"}, {"id": 413308, "book_url": "\u7eb8\u795e/413308", "title": "\u7b2c\u4e09\u56db\u4e5d\u7ae0\uff1a\u611f\u60c5\u82e6\u65c5"}, {"id": 413305, "book_url": "\u7eb8\u795e/413305", "title": "\u7b2c\u4e09\u56db\u516d\u7ae0\uff1a\u5a01\u903c\u6210\u529f"}, {"id": 413309, "book_url": "\u7eb8\u795e/413309", "title": "\u7b2c\u4e09\u4e94\u96f6\u7ae0\uff1a\u6d41\u4e91\u521d\u73b0"}, {"id": 413310, "book_url": "\u7eb8\u795e/413310", "title": "\u7b2c\u4e09\u4e94\u4e00\u7ae0\uff1a\u53cd\u6297\u7ec4\u7ec7"}, {"id": 413314, "book_url": "\u7eb8\u795e/413314", "title": "\u7b2c\u4e09\u4e94\u4e94\u7ae0\uff1a\u9ed1\u8863\u5f71\u6740"}, {"id": 413311, "book_url": "\u7eb8\u795e/413311", "title": "\u7b2c\u4e09\u4e94\u4e8c\u7ae0\uff1a\u8282\u65e5\u6c14\u6c1b"}, {"id": 413315, "book_url": "\u7eb8\u795e/413315", "title": "\u7b2c\u4e09\u4e94\u516d\u7ae0\uff1a\u5341\u8bc0\u5341\u6740"}, {"id": 413312, "book_url": "\u7eb8\u795e/413312", "title": "\u7b2c\u4e09\u4e94\u4e09\u7ae0\uff1a\u5c0f\u5c0f\u6311\u8845"}, {"id": 413316, "book_url": "\u7eb8\u795e/413316", "title": "\u7b2c\u4e09\u4e94\u4e03\u7ae0\uff1a\u9ed1\u8863\u8bc0\u522b"}, {"id": 413313, "book_url": "\u7eb8\u795e/413313", "title": "\u7b2c\u4e09\u4e94\u56db\u7ae0\uff1a\u5fae\u6709\u4e0d\u7766"}, {"id": 413317, "book_url": "\u7eb8\u795e/413317", "title": "\u7b2c\u4e09\u4e94\u516b\u7ae0\uff1a\u957f\u751f\u4e4b\u65c5"}, {"id": 413318, "book_url": "\u7eb8\u795e/413318", "title": "\u7b2c\u4e09\u4e94\u4e5d\u7ae0\uff1a\u540c\u7c7b\u7b3a\u6853"}, {"id": 413322, "book_url": "\u7eb8\u795e/413322", "title": "\u7b2c\u4e09\u516d\u4e09\u7ae0\uff1a\u8fd4\u8001\u8fd8\u7ae5"}, {"id": 413319, "book_url": "\u7eb8\u795e/413319", "title": "\u7b2c\u4e09\u516d\u96f6\u7ae0\uff1a\u8d85\u7ea7\u5996\u602a"}, {"id": 413323, "book_url": "\u7eb8\u795e/413323", "title": "\u7b2c\u4e09\u516d\u56db\u7ae0\uff1a\u5e7d\u8c37\u4e4b\u79d8"}, {"id": 413320, "book_url": "\u7eb8\u795e/413320", "title": "\u7b2c\u4e09\u516d\u4e00\u7ae0\uff1a\u9e21\u98de\u72d7\u8df3"}, {"id": 413324, "book_url": "\u7eb8\u795e/413324", "title": "\u7b2c\u4e09\u516d\u4e94\u7ae0\uff1a\u5144\u957f\u7559\u8a00"}, {"id": 413321, "book_url": "\u7eb8\u795e/413321", "title": "\u7b2c\u4e09\u516d\u4e8c\u7ae0\uff1a\u4fc3\u819d\u957f\u8c08"}, {"id": 413325, "book_url": "\u7eb8\u795e/413325", "title": "\u7b2c\u4e09\u516d\u516d\u7ae0\uff1a\u7ed3\u62dc\u5144\u5f1f"}, {"id": 413326, "book_url": "\u7eb8\u795e/413326", "title": "\u7b2c\u4e09\u516d\u4e03\u7ae0\uff1a\u4f2f\u4f84\u5b9a\u8ba1"}, {"id": 413330, "book_url": "\u7eb8\u795e/413330", "title": "\u7b2c\u4e09\u4e03\u4e00\u7ae0\uff1a\u8be1\u5f02\u4f20\u8a00"}, {"id": 413327, "book_url": "\u7eb8\u795e/413327", "title": "\u7b2c\u4e09\u516d\u516b\u7ae0\uff1a\u5357\u6d0b\u8ba1\u5212"}, {"id": 413331, "book_url": "\u7eb8\u795e/413331", "title": "\u7b2c\u4e09\u4e03\u4e8c\u7ae0\uff1a\u5175\u5206\u4e09\u8def"}, {"id": 413328, "book_url": "\u7eb8\u795e/413328", "title": "\u7b2c\u4e09\u516d\u4e5d\u7ae0\uff1a\u76ee\u6807\u5357\u6d0b"}, {"id": 413332, "book_url": "\u7eb8\u795e/413332", "title": "\u7b2c\u4e09\u4e03\u4e09\u7ae0\uff1a\u5b88\u682a\u5f85\u5154"}, {"id": 413329, "book_url": "\u7eb8\u795e/413329", "title": "\u7b2c\u4e09\u4e03\u96f6\u7ae0\uff1a\u6545\u5e03\u7591\u9635"}, {"id": 413333, "book_url": "\u7eb8\u795e/413333", "title": "\u7b2c\u4e09\u4e03\u56db\u7ae0\uff1a\u9644\u8eab\u80fd\u529b"}, {"id": 413334, "book_url": "\u7eb8\u795e/413334", "title": "\u7b2c\u4e09\u4e03\u4e94\u7ae0\uff1a\u5e7d\u9b42\u4e4b\u6218"}, {"id": 413338, "book_url": "\u7eb8\u795e/413338", "title": "\u7b2c\u4e09\u4e03\u4e5d\u7ae0\uff1a\u65b0\u7684\u95ee\u9898"}, {"id": 413335, "book_url": "\u7eb8\u795e/413335", "title": "\u7b2c\u4e09\u4e03\u516d\u7ae0\uff1a\u5e7d\u9b42\u9644\u8eab"}, {"id": 413339, "book_url": "\u7eb8\u795e/413339", "title": "\u7b2c\u4e09\u516b\u96f6\u7ae0\uff1a\u8d2d\u4e70\u8eab\u4efd"}, {"id": 413336, "book_url": "\u7eb8\u795e/413336", "title": "\u7b2c\u4e09\u4e03\u4e03\u7ae0\uff1a\u71c3\u70e7\u4e4b\u529b"}, {"id": 413340, "book_url": "\u7eb8\u795e/413340", "title": "\u7b2c\u4e09\u516b\u4e00\u7ae0\uff1a\u4ec7\u4eba\u89c1\u9762"}, {"id": 413337, "book_url": "\u7eb8\u795e/413337", "title": "\u7b2c\u4e09\u4e03\u516b\u7ae0\uff1a\u80fd\u529b\u4e4b\u6cb3"}, {"id": 413341, "book_url": "\u7eb8\u795e/413341", "title": "\u7b2c\u4e09\u516b\u4e8c\u7ae0\uff1a\u71c3\u70e7\u7684\u7eb8"}, {"id": 413342, "book_url": "\u7eb8\u795e/413342", "title": "\u7b2c\u4e09\u516b\u4e09\u7ae0\uff1a\u79bb\u4ead\u79bb\u6731"}, {"id": 413346, "book_url": "\u7eb8\u795e/413346", "title": "\u7b2c\u4e09\u516b\u4e03\u7ae0\uff1a\u9694\u5cb8\u89c2\u706b"}, {"id": 413343, "book_url": "\u7eb8\u795e/413343", "title": "\u7b2c\u4e09\u516b\u56db\u7ae0\uff1a\u795e\u79d8\u6c34\u67f1"}, {"id": 413347, "book_url": "\u7eb8\u795e/413347", "title": "\u7b2c\u4e09\u516b\u516b\u7ae0\uff1a\u7834\u5899\u800c\u5165"}, {"id": 413344, "book_url": "\u7eb8\u795e/413344", "title": "\u7b2c\u4e09\u516b\u4e94\u7ae0\uff1a\u4f5c\u5ba2\u53e4\u5821"}, {"id": 413348, "book_url": "\u7eb8\u795e/413348", "title": "\u7b2c\u4e09\u516b\u4e5d\u7ae0\uff1a\u5b9e\u529b\u5dee\u8ddd"}, {"id": 413345, "book_url": "\u7eb8\u795e/413345", "title": "\u7b2c\u4e09\u516b\u516d\u7ae0\uff1a\u518d\u6b21\u76f8\u89c1"}, {"id": 413349, "book_url": "\u7eb8\u795e/413349", "title": "\u7b2c\u4e09\u4e5d\u96f6\u7ae0\uff1a\u4e0e\u7280\u89d2\u529b"}, {"id": 413350, "book_url": "\u7eb8\u795e/413350", "title": "\u7b2c\u4e09\u4e5d\u4e00\u7ae0\uff1a\u62bd\u8eab\u800c\u9000"}, {"id": 413354, "book_url": "\u7eb8\u795e/413354", "title": "\u7b2c\u4e09\u4e5d\u4e94\u7ae0\uff1a\u79d8\u5bc6\u6f5c\u5165"}, {"id": 413351, "book_url": "\u7eb8\u795e/413351", "title": "\u7b2c\u4e09\u4e5d\u4e8c\u7ae0\uff1a\u8bf7\u541b\u7559\u6b65"}, {"id": 413355, "book_url": "\u7eb8\u795e/413355", "title": "\u7b2c\u4e09\u4e5d\u516d\u7ae0\uff1a\u5929\u73e0\u602a\u517d"}, {"id": 413352, "book_url": "\u7eb8\u795e/413352", "title": "\u7b2c\u4e09\u4e5d\u4e09\u7ae0\uff1a\u4e09\u5206\u5080\u5121"}, {"id": 413356, "book_url": "\u7eb8\u795e/413356", "title": "\u7b2c\u4e09\u4e5d\u4e03\u7ae0\uff1a\u6c34\u9f99\u9010\u9e64"}, {"id": 413353, "book_url": "\u7eb8\u795e/413353", "title": "\u7b2c\u4e09\u4e5d\u56db\u7ae0\uff1a\u518d\u5ea6\u6298\u8fd4"}, {"id": 413357, "book_url": "\u7eb8\u795e/413357", "title": "\u7b2c\u4e09\u4e5d\u516b\u7ae0\uff1a\u5730\u4e0b\u906d\u9047"}, {"id": 413358, "book_url": "\u7eb8\u795e/413358", "title": "\u7b2c\u4e09\u4e5d\u4e5d\u7ae0\uff1a\u9f99\u4e4b\u4e5d\u9996"}, {"id": 413362, "book_url": "\u7eb8\u795e/413362", "title": "\u7b2c\u56db\u96f6\u4e09\u7ae0\uff1a\u8d85\u7ea7\u4e4c\u9f9f"}, {"id": 413359, "book_url": "\u7eb8\u795e/413359", "title": "\u7b2c\u56db\u96f6\u96f6\u7ae0\uff1a\u6b63\u9762\u6297\u8861"}, {"id": 413363, "book_url": "\u7eb8\u795e/413363", "title": "\u7b2c\u56db\u96f6\u56db\u7ae0\uff1a\u5929\u73e0\u6218\u58eb"}, {"id": 413360, "book_url": "\u7eb8\u795e/413360", "title": "\u7b2c\u56db\u96f6\u4e00\u7ae0\uff1a\u5f85\u4ef7\u800c\u6cbd"}, {"id": 413364, "book_url": "\u7eb8\u795e/413364", "title": "\u7b2c\u56db\u96f6\u4e94\u7ae0\uff1a\u7384\u6b66\u89e3\u60d1"}, {"id": 413361, "book_url": "\u7eb8\u795e/413361", "title": "\u7b2c\u56db\u96f6\u4e8c\u7ae0\uff1a\u6fc0\u5149\u518d\u73b0"}, {"id": 413365, "book_url": "\u7eb8\u795e/413365", "title": "\u7b2c\u56db\u96f6\u516d\u7ae0\uff1a\u4e8b\u60c5\u59cb\u672b"}, {"id": 413366, "book_url": "\u7eb8\u795e/413366", "title": "\u7b2c\u56db\u96f6\u4e03\u7ae0\uff1a\u98de\u56de\u5927\u9646"}, {"id": 413370, "book_url": "\u7eb8\u795e/413370", "title": "\u7b2c\u56db\u4e00\u4e00\u7ae0\uff1a\u8d76\u56de\u4e91\u57ce"}, {"id": 413367, "book_url": "\u7eb8\u795e/413367", "title": "\u7b2c\u56db\u96f6\u516b\u7ae0\uff1a\u9634\u9519\u9633\u5dee"}, {"id": 413371, "book_url": "\u7eb8\u795e/413371", "title": "\u7b2c\u56db\u4e00\u4e8c\u7ae0\uff1a\u5343\u94a7\u4e00\u53d1"}, {"id": 413368, "book_url": "\u7eb8\u795e/413368", "title": "\u7b2c\u56db\u96f6\u4e5d\u7ae0\uff1a\u8fdb\u9000\u4e24\u96be"}, {"id": 413372, "book_url": "\u7eb8\u795e/413372", "title": "\u7b2c\u56db\u4e00\u4e09\u7ae0\uff1a\u5bb6\u5ead\u7ea0\u7eb7"}, {"id": 413369, "book_url": "\u7eb8\u795e/413369", "title": "\u7b2c\u56db\u4e00\u96f6\u7ae0\uff1a\u8840\u8089\u5d29\u6e83"}, {"id": 413373, "book_url": "\u7eb8\u795e/413373", "title": "\u7b2c\u56db\u4e00\u56db\u7ae0\uff1a\u9634\u9b3c\u5f31\u70b9"}, {"id": 413374, "book_url": "\u7eb8\u795e/413374", "title": "\u7b2c\u56db\u4e00\u4e94\u7ae0\uff1a\u6124\u6012\u6280\u5de7"}, {"id": 413378, "book_url": "\u7eb8\u795e/413378", "title": "\u7b2c\u56db\u4e00\u4e5d\u7ae0\uff1a\u4f5c\u8327\u81ea\u7f1a2"}, {"id": 413375, "book_url": "\u7eb8\u795e/413375", "title": "\u7b2c\u56db\u4e00\u516d\u7ae0\uff1a\u63a5\u53d7\u4e4b\u524d"}, {"id": 413379, "book_url": "\u7eb8\u795e/413379", "title": "\u7b2c\u56db\u4e8c\u96f6\u7ae0\uff1a\u5b8c\u7f8e\u9677\u9631"}, {"id": 413376, "book_url": "\u7eb8\u795e/413376", "title": "\u7b2c\u56db\u4e00\u4e03\u7ae0\uff1a\u4f2f\u7236\u5fe0\u8a00"}, {"id": 413380, "book_url": "\u7eb8\u795e/413380", "title": "\u7b2c\u56db\u4e8c\u4e00\u7ae0\uff1a\u540c\u6839\u76f8\u714e"}, {"id": 413377, "book_url": "\u7eb8\u795e/413377", "title": "\u7b2c\u56db\u4e00\u516b\u7ae0\uff1a\u4f5c\u8327\u81ea\u7f1a"}, {"id": 413381, "book_url": "\u7eb8\u795e/413381", "title": "\u7b2c\u56db\u4e8c\u4e8c\u7ae0\uff1a\u91d1\u521a\u4e4b\u6b7b"}, {"id": 413382, "book_url": "\u7eb8\u795e/413382", "title": "\u7b2c\u56db\u4e8c\u4e09\u7ae0\uff1a\u957f\u8857\u8840\u6218"}, {"id": 413386, "book_url": "\u7eb8\u795e/413386", "title": "\u7b2c\u56db\u4e8c\u4e03\u7ae0\uff1a\u5f02\u80fd\u5c0f\u4e03"}, {"id": 413383, "book_url": "\u7eb8\u795e/413383", "title": "\u7b2c\u56db\u4e8c\u56db\u7ae0\uff1a\u957f\u67aa\u78a7\u7130"}, {"id": 413387, "book_url": "\u7eb8\u795e/413387", "title": "\u7b2c\u56db\u4e8c\u516b\u7ae0\uff1a\u795e\u5175\u4e4b\u4e3b"}, {"id": 413384, "book_url": "\u7eb8\u795e/413384", "title": "\u7b2c\u56db\u4e8c\u4e94\u7ae0\uff1a\u7a7a\u95f4\u9ca8\u9c7c"}, {"id": 413388, "book_url": "\u7eb8\u795e/413388", "title": "\u7b2c\u56db\u4e8c\u4e5d\u7ae0\uff1a\u6c81\u5165\u5fc3\u6e56"}, {"id": 413385, "book_url": "\u7eb8\u795e/413385", "title": "\u7b2c\u56db\u4e8c\u516d\u7ae0\uff1a\u6240\u5411\u62ab\u9761"}, {"id": 413389, "book_url": "\u7eb8\u795e/413389", "title": "\u7b2c\u56db\u4e09\u96f6\u7ae0\uff1a\u4ebf\u4e07\u5206\u8eab"}, {"id": 413390, "book_url": "\u7eb8\u795e/413390", "title": "\u7b2c\u56db\u4e09\u4e00\u7ae0\uff1a\u6781\u9650\u52a0\u901f"}, {"id": 413394, "book_url": "\u7eb8\u795e/413394", "title": "\u7b2c\u56db\u4e09\u4e94\u7ae0\uff1a\u4ece\u5929\u800c\u964d"}, {"id": 413391, "book_url": "\u7eb8\u795e/413391", "title": "\u7b2c\u56db\u4e09\u4e8c\u7ae0\uff1a\u592a\u7a7a\u56da\u7b3c"}, {"id": 413395, "book_url": "\u7eb8\u795e/413395", "title": "\u7b2c\u56db\u4e09\u516d\u7ae0\uff1a\u6d41\u661f\u7740\u9646"}, {"id": 413392, "book_url": "\u7eb8\u795e/413392", "title": "\u7b2c\u56db\u4e09\u4e09\u7ae0\uff1a\u7ec8\u6781\u6740\u9635"}, {"id": 413396, "book_url": "\u7eb8\u795e/413396", "title": "\u7b2c\u56db\u4e09\u4e03\u7ae0\uff1a\u5929\u4f7f\u5f52\u6765"}, {"id": 413393, "book_url": "\u7eb8\u795e/413393", "title": "\u7b2c\u56db\u4e09\u56db\u7ae0\uff1a\u5fc3\u7684\u65b9\u5411"}, {"id": 413397, "book_url": "\u7eb8\u795e/413397", "title": "\u7b2c\u56db\u4e09\u516b\u7ae0\uff1a\u6b7b\u4ea1\u9634\u5f71"}, {"id": 413398, "book_url": "\u7eb8\u795e/413398", "title": "\u7b2c\u56db\u4e09\u4e5d\u7ae0\uff1a\u6069\u65ad\u60c5\u7edd"}, {"id": 413402, "book_url": "\u7eb8\u795e/413402", "title": "\u7b2c\u56db\u56db\u4e09\u7ae0\uff1a\u79bb\u4ead\u4e4b\u8bfa"}, {"id": 413399, "book_url": "\u7eb8\u795e/413399", "title": "\u7b2c\u56db\u56db\u96f6\u7ae0\uff1a\u8d85\u7ea7\u6c7d\u8f66"}, {"id": 413403, "book_url": "\u7eb8\u795e/413403", "title": "\u7b2c\u56db\u56db\u56db\u7ae0\uff1a\u5c0f\u96e8\u7ea2\u5a18"}, {"id": 413400, "book_url": "\u7eb8\u795e/413400", "title": "\u7b2c\u56db\u56db\u4e00\u7ae0\uff1a\u8fd4\u56de\u4efb\u5e9c"}, {"id": 413404, "book_url": "\u7eb8\u795e/413404", "title": "\u7b2c\u56db\u56db\u4e94\u7ae0\uff1a\u6f5c\u5165\u5e7d\u8c37"}, {"id": 413401, "book_url": "\u7eb8\u795e/413401", "title": "\u7b2c\u56db\u56db\u4e8c\u7ae0\uff1a\u98ce\u5e73\u6d6a\u9759"}, {"id": 413405, "book_url": "\u7eb8\u795e/413405", "title": "\u7b2c\u56db\u56db\u516d\u7ae0\uff1a\u7a81\u53d1\u5947\u60f3"}, {"id": 413406, "book_url": "\u7eb8\u795e/413406", "title": "\u7b2c\u56db\u56db\u4e03\u7ae0\uff1a\u6b3a\u9a97\u5c0f\u5b69"}, {"id": 413410, "book_url": "\u7eb8\u795e/413410", "title": "\u7b2c\u56db\u4e94\u4e00\u7ae0\uff1a\u6251\u6714\u8ff7\u79bb"}, {"id": 413407, "book_url": "\u7eb8\u795e/413407", "title": "\u7b2c\u56db\u56db\u516b\u7ae0\uff1a\u4f3c\u66fe\u76f8\u4f3c"}, {"id": 413411, "book_url": "\u7eb8\u795e/413411", "title": "\u7b2c\u56db\u4e94\u4e8c\u7ae0\uff1a\u5929\u95e8\u4e4b\u8def"}, {"id": 413408, "book_url": "\u7eb8\u795e/413408", "title": "\u7b2c\u56db\u56db\u4e5d\u7ae0\uff1a\u5982\u89c1\u6545\u4eba"}, {"id": 413412, "book_url": "\u7eb8\u795e/413412", "title": "\u7b2c\u56db\u4e94\u4e09\u7ae0\uff1a\u611f\u60c5\u7ea0\u845b"}, {"id": 413409, "book_url": "\u7eb8\u795e/413409", "title": "\u7b2c\u56db\u4e94\u96f6\u7ae0\uff1a\u5e7d\u8c37\u5f80\u4e8b"}, {"id": 413413, "book_url": "\u7eb8\u795e/413413", "title": "\u7b2c\u56db\u4e94\u56db\u7ae0\uff1a\u4e89\u593a\u94a5\u5319"}, {"id": 413414, "book_url": "\u7eb8\u795e/413414", "title": "\u7b2c\u56db\u4e94\u4e94\u7ae0\uff1a\u9519\u5931\u826f\u673a"}, {"id": 413418, "book_url": "\u7eb8\u795e/413418", "title": "\u7b2c\u56db\u4e94\u4e5d\u7ae0\uff1a\u5de8\u6728\u6276\u6851"}, {"id": 413415, "book_url": "\u7eb8\u795e/413415", "title": "\u7b2c\u56db\u4e94\u516d\u7ae0\uff1a\u7834\u77f3\u4e4b\u9547"}, {"id": 413419, "book_url": "\u7eb8\u795e/413419", "title": "\u7b2c\u56db\u516d\u96f6\u7ae0\uff1a\u6069\u65ad\u60c5\u7edd"}, {"id": 413416, "book_url": "\u7eb8\u795e/413416", "title": "\u7b2c\u56db\u4e94\u4e03\u7ae0\uff1a\u65ad\u8a00\u4e4b\u7ae0"}, {"id": 413420, "book_url": "\u7eb8\u795e/413420", "title": "\u7b2c\u56db\u516d\u4e00\u7ae0\uff1a\u96e8\u4e4b\u8bf7\u6c42"}, {"id": 413417, "book_url": "\u7eb8\u795e/413417", "title": "\u7b2c\u56db\u4e94\u516b\u7ae0\uff1a\u78a7\u7130\u518d\u73b0"}, {"id": 413421, "book_url": "\u7eb8\u795e/413421", "title": "\u7b2c\u56db\u516d\u4e8c\u7ae0\uff1a\u5de6\u53f3\u4e3a\u96be"}, {"id": 413422, "book_url": "\u7eb8\u795e/413422", "title": "\u7b2c\u56db\u516d\u4e09\u7ae0\uff1a\u9876\u7ea7\u80fd\u529b"}, {"id": 413426, "book_url": "\u7eb8\u795e/413426", "title": "\u7b2c\u56db\u516d\u4e03\u7ae0\uff1a\u6218\u6597\u4e4b\u97f3"}, {"id": 413423, "book_url": "\u7eb8\u795e/413423", "title": "\u7b2c\u56db\u516d\u56db\u7ae0\uff1a\u9876\u7ea7\u5bf9\u6218"}, {"id": 413427, "book_url": "\u7eb8\u795e/413427", "title": "\u7b2c\u56db\u516d\u516b\u7ae0\uff1a\u79c0\u7f8e\u989b\u59ec"}, {"id": 413424, "book_url": "\u7eb8\u795e/413424", "title": "\u7b2c\u56db\u516d\u4e94\u7ae0\uff1a\u989b\u59ec\u4e4b\u9080"}, {"id": 413428, "book_url": "\u7eb8\u795e/413428", "title": "\u7b2c\u56db\u516d\u4e5d\u7ae0\uff1a\u4e0d\u6b7b\u4e4b\u5370"}, {"id": 413425, "book_url": "\u7eb8\u795e/413425", "title": "\u7b2c\u56db\u516d\u516d\u7ae0\uff1a\u5c0f\u96e8\u5954\u6708"}, {"id": 413429, "book_url": "\u7eb8\u795e/413429", "title": "\u7b2c\u56db\u4e03\u96f6\u7ae0\uff1a\u989b\u59ec\u4f24\u60c5"}, {"id": 413430, "book_url": "\u7eb8\u795e/413430", "title": "\u7b2c\u56db\u4e03\u4e00\u7ae0\uff1a\u78a7\u6d77\u9752\u5929"}, {"id": 413434, "book_url": "\u7eb8\u795e/413434", "title": "\u56db\u4e03\u4e94\u7ae0\uff1a\u7b80\u5355\u5e78\u798f"}, {"id": 413431, "book_url": "\u7eb8\u795e/413431", "title": "\u7b2c\u56db\u4e03\u4e8c\u7ae0:\u4e00\u5239\u5149\u660e"}, {"id": 413435, "book_url": "\u7eb8\u795e/413435", "title": "\u56db\u4e03\u516d\u7ae0\uff1a\u5f53\u65ad\u5219\u65ad"}, {"id": 413432, "book_url": "\u7eb8\u795e/413432", "title": "\u7b2c\u56db\u4e03\u4e09\u7ae0\uff1a\u5929\u7a7a\u4e4b\u738b"}, {"id": 413436, "book_url": "\u7eb8\u795e/413436", "title": "\u56db\u4e03\u4e03\u7ae0\uff1a\u6bd4\u7ffc\u9f50\u98de"}, {"id": 413433, "book_url": "\u7eb8\u795e/413433", "title": "\u56db\u4e03\u56db\u7ae0\uff1a\u5c0f\u96e8\u5f52\u6765"}, {"id": 413437, "book_url": "\u7eb8\u795e/413437", "title": "\u56db\u4e03\u516b\u7ae0\uff1a\u5f97\u9047\u6545\u4eba"}, {"id": 413438, "book_url": "\u7eb8\u795e/413438", "title": "\u56db\u4e03\u4e5d\u7ae0\uff1a\u7ecf\u6d4e\u4e8b\u4ef6"}, {"id": 413442, "book_url": "\u7eb8\u795e/413442", "title": "\u56db\u516b\u4e09\u7ae0\uff1a\u706b\u62f3\u4e4b\u8bf7"}, {"id": 413439, "book_url": "\u7eb8\u795e/413439", "title": "\u56db\u516b\u96f6\u7ae0\uff1a\u6b22\u8fce\u56de\u6765"}, {"id": 413443, "book_url": "\u7eb8\u795e/413443", "title": "\u56db\u516b\u56db\u7ae0\uff1a\u8ffd\u8e2a\u730e\u4eba"}, {"id": 413440, "book_url": "\u7eb8\u795e/413440", "title": "\u56db\u516b\u4e00\u7ae0\uff1a\u91cd\u77b3\u6613\u592d"}, {"id": 413444, "book_url": "\u7eb8\u795e/413444", "title": "\u56db\u516b\u4e94\u7ae0\uff1a\u5927\u5730\u5012\u60ac"}, {"id": 413441, "book_url": "\u7eb8\u795e/413441", "title": "\u56db\u516b\u4e8c\u7ae0\uff1a\u771f\u5b9e\u4e4b\u773c"}, {"id": 413445, "book_url": "\u7eb8\u795e/413445", "title": "\u56db\u516b\u516d\u7ae0\uff1a\u795e\u5175\u6d77\u6d0b"}, {"id": 413446, "book_url": "\u7eb8\u795e/413446", "title": "\u56db\u516b\u4e03\u7ae0\uff1a\u6df7\u4e71\u5b66\u9662\u2014\u56db\u516b\u516b\u7ae0\uff1a\u52d2\u4ee4\u9000\u5b66"}, {"id": 413450, "book_url": "\u7eb8\u795e/413450", "title": "\u56db\u4e5d\u4e8c\u7ae0\uff1a\u5de5\u4f1a\u7f51\u5427"}, {"id": 413447, "book_url": "\u7eb8\u795e/413447", "title": "\u56db\u516b\u4e5d\u7ae0\uff1a\u6821\u957f\u5ba4\u5185"}, {"id": 413451, "book_url": "\u7eb8\u795e/413451", "title": "\u56db\u4e5d\u4e09\u7ae0\uff1a\u5de5\u4f1a\u7a0b\u5e8f"}, {"id": 413448, "book_url": "\u7eb8\u795e/413448", "title": "\u56db\u4e5d\u96f6\u7ae0\uff1a\u8c08\u5224\u6210\u529f"}, {"id": 413452, "book_url": "\u7eb8\u795e/413452", "title": "\u56db\u4e5d\u56db\u7ae0\uff1a\u730e\u72ac\u771f\u8eab"}, {"id": 413449, "book_url": "\u7eb8\u795e/413449", "title": "\u56db\u4e5d\u4e00\u7ae0\uff1a\u4e0d\u670d\u8005\u6b7b"}, {"id": 413453, "book_url": "\u7eb8\u795e/413453", "title": "\u56db\u4e5d\u4e94\u7ae0\uff1a\u7a81\u5165\u5927\u53a6"}, {"id": 413454, "book_url": "\u7eb8\u795e/413454", "title": "\u56db\u4e5d\u516d\u7ae0\uff1a\u51a4\u5bb6\u8def\u7a84"}, {"id": 413458, "book_url": "\u7eb8\u795e/413458", "title": "\u4e94\u767e\u7ae0\uff1a\u7559\u4f60\u4e00\u547d"}, {"id": 413455, "book_url": "\u7eb8\u795e/413455", "title": "\u56db\u4e5d\u4e03\u7ae0\uff1a\u5206\u9053\u626c\u9573"}, {"id": 413459, "book_url": "\u7eb8\u795e/413459", "title": "\u4e94\u96f6\u4e00\u7ae0\uff1a\u76f8\u62e5\u800c\u7720"}, {"id": 413456, "book_url": "\u7eb8\u795e/413456", "title": "\u56db\u4e5d\u516b\u7ae0\uff1a\u65e0\u5948\u4e4b\u4e3e"}, {"id": 413460, "book_url": "\u7eb8\u795e/413460", "title": "\u4e94\u96f6\u4e8c\u7ae0\uff1a\u5982\u6b64\u6bd4\u8bd5"}, {"id": 413457, "book_url": "\u7eb8\u795e/413457", "title": "\u56db\u4e5d\u4e5d\u7ae0\uff1a\u5e26\u4f60\u56de\u5bb6"}, {"id": 413461, "book_url": "\u7eb8\u795e/413461", "title": "\u4e94\u96f6\u4e09\u7ae0\uff1a\u4fbf\u5b9c\u5f92\u5f1f"}, {"id": 413462, "book_url": "\u7eb8\u795e/413462", "title": "\u4e94\u96f6\u56db\u7ae0\uff1a\u56de\u89c1\u83ab\u5947"}, {"id": 413466, "book_url": "\u7eb8\u795e/413466", "title": "\u4e94\u96f6\u516b\u7ae0\uff1a\u5f02\u80fd\u81ea\u6cbb"}, {"id": 413463, "book_url": "\u7eb8\u795e/413463", "title": "\u4e94\u96f6\u4e94\u7ae0\uff1a\u4f2a\u70bd\u5929\u4f7f"}, {"id": 413467, "book_url": "\u7eb8\u795e/413467", "title": "\u4e94\u96f6\u4e5d\u7ae0\uff1a\u795e\u5175\u4e4b\u5e9c"}, {"id": 413464, "book_url": "\u7eb8\u795e/413464", "title": "\u4e94\u96f6\u516d\u7ae0\uff1a\u6218\u529b\u5206\u6790"}, {"id": 413468, "book_url": "\u7eb8\u795e/413468", "title": "\u4e94\u4e00\u96f6\u7ae0\uff1a\u706f\u5e08\u73b0\u8eab"}, {"id": 413465, "book_url": "\u7eb8\u795e/413465", "title": "\u4e94\u96f6\u4e03\u7ae0\uff1a\u8ba8\u4ef7\u8fd8\u4ef7"}, {"id": 413469, "book_url": "\u7eb8\u795e/413469", "title": "\u4e94\u4e00\u4e00\u7ae0\uff1a\u8fdc\u53e4\u6d69\u52ab"}, {"id": 413470, "book_url": "\u7eb8\u795e/413470", "title": "\u4e94\u4e00\u4e8c\u7ae0\uff1a\u9010\u65e5\u98de\u884c"}, {"id": 413474, "book_url": "\u7eb8\u795e/413474", "title": "\u4e94\u4e00\u516d\u7ae0\uff1a\u5c0f\u96e8\u53c2\u6218"}, {"id": 413471, "book_url": "\u7eb8\u795e/413471", "title": "\u4e94\u4e00\u4e09\u7ae0\uff1a\u771f\u4f2a\u5bf9\u9635"}, {"id": 413475, "book_url": "\u7eb8\u795e/413475", "title": "\u4e94\u4e00\u4e03\u7ae0\uff1a\u610f\u5916\u7ebf\u7d22"}, {"id": 413472, "book_url": "\u7eb8\u795e/413472", "title": "\u4e94\u4e00\u56db\u7ae0\uff1a\u4e5d\u5929\u4e4b\u4e0a"}, {"id": 413476, "book_url": "\u7eb8\u795e/413476", "title": "\u4e94\u4e00\u516b\u7ae0\uff1a\u6545\u4f5c\u6d12\u8131"}, {"id": 413473, "book_url": "\u7eb8\u795e/413473", "title": "\u4e94\u4e00\u4e94\u7ae0\uff1a\u77ac\u95f4\u79fb\u52a8"}, {"id": 413477, "book_url": "\u7eb8\u795e/413477", "title": "\u4e94\u4e00\u4e5d\u7ae0\uff1a\u91d1\u521a\u9668\u843d"}, {"id": 413478, "book_url": "\u7eb8\u795e/413478", "title": "\u4e94\u4e8c\u96f6\u7ae0\uff1a\u6ca7\u6d77\u6851\u7530"}, {"id": 413482, "book_url": "\u7eb8\u795e/413482", "title": "\u4e94\u4e8c\u56db\u7ae0\uff1a\u5c0f\u96e8\u7684\u6b4c"}, {"id": 413479, "book_url": "\u7eb8\u795e/413479", "title": "\u4e94\u4e8c\u4e00\u7ae0\uff1a\u5c11\u5e74\u591a\u91d1"}, {"id": 413483, "book_url": "\u7eb8\u795e/413483", "title": "\u4e94\u4e8c\u4e94\u7ae0\uff1a\u7edd\u4e16\u65e0\u53cc"}, {"id": 413480, "book_url": "\u7eb8\u795e/413480", "title": "\u4e94\u4e8c\u4e8c\u7ae0\uff1a\u8bb0\u8005\u4e91\u96c6"}, {"id": 413484, "book_url": "\u7eb8\u795e/413484", "title": "\u4e94\u4e8c\u516d\u7ae0\uff1a\u65b0\u95fb\u53d1\u5e03"}, {"id": 413481, "book_url": "\u7eb8\u795e/413481", "title": "\u4e94\u4e8c\u4e09\u7ae0\uff1a\u8ba1\u8bae\u540e\u7740"}, {"id": 413485, "book_url": "\u7eb8\u795e/413485", "title": "\u4e94\u4e8c\u4e03\u7ae0\uff1a\u8774\u8776\u632f\u7fc5"}, {"id": 413486, "book_url": "\u7eb8\u795e/413486", "title": "\u4e94\u4e8c\u516b\u7ae0\uff1a\u5e73\u9759\u5f00\u7aef"}, {"id": 413490, "book_url": "\u7eb8\u795e/413490", "title": "\u4e94\u4e09\u4e8c\u7ae0\uff1a\u6b6a\u6253\u6b63\u7740"}, {"id": 413487, "book_url": "\u7eb8\u795e/413487", "title": "\u4e94\u4e8c\u4e5d\u7ae0\uff1a\u5bfb\u627e\u8fc7\u53bb"}, {"id": 413491, "book_url": "\u7eb8\u795e/413491", "title": "\u4e94\u4e09\u4e09\u7ae0\uff1a\u778e\u53d4\u7684\u773c"}, {"id": 413488, "book_url": "\u7eb8\u795e/413488", "title": "\u4e94\u4e09\u96f6\u7ae0\uff1a\u5192\u724c\u5c0f\u4e03"}, {"id": 413492, "book_url": "\u7eb8\u795e/413492", "title": "\u4e94\u4e09\u56db\u7ae0\uff1a\u7ebf\u7d22\u7a81\u73b0"}, {"id": 413489, "book_url": "\u7eb8\u795e/413489", "title": "\u4e94\u4e09\u4e00\u7ae0\uff1a\u51a5\u987d\u4e0d\u7075"}, {"id": 413493, "book_url": "\u7eb8\u795e/413493", "title": "\u4e94\u4e09\u4e94\u7ae0\uff1a\u4eba\u95f4\u84b8\u53d1"}, {"id": 413494, "book_url": "\u7eb8\u795e/413494", "title": "\u4e94\u4e09\u516d\u7ae0\uff1a\u5bfb\u627e\u9752\u53d4"}, {"id": 413498, "book_url": "\u7eb8\u795e/413498", "title": "\u4e94\u56db\u96f6\u7ae0\uff1a\u8f7b\u800c\u6613\u4e3e"}, {"id": 413495, "book_url": "\u7eb8\u795e/413495", "title": "\u4e94\u4e09\u4e03\u7ae0\uff1a\u8ffd\u8e2a\u6709\u679c"}, {"id": 413499, "book_url": "\u7eb8\u795e/413499", "title": "\u4e94\u56db\u4e00\u7ae0\uff1a\u7070\u767d\u767d\u7070"}, {"id": 413496, "book_url": "\u7eb8\u795e/413496", "title": "\u4e94\u4e09\u516b\u7ae0\uff1a\u8fde\u73af\u9677\u9631"}, {"id": 413500, "book_url": "\u7eb8\u795e/413500", "title": "\u4e94\u56db\u4e8c\u7ae0\uff1a\u9876\u7ea7\u4e4b\u79d8"}, {"id": 413497, "book_url": "\u7eb8\u795e/413497", "title": "\u4e94\u4e09\u4e5d\u7ae0\uff1a\u5927\u9884\u8a00\u5e08"}, {"id": 413501, "book_url": "\u7eb8\u795e/413501", "title": "\u4e94\u56db\u4e09\u7ae0\uff1a\u9884\u8a00\u80fd\u529b"}, {"id": 413502, "book_url": "\u7eb8\u795e/413502", "title": "\u4e94\u56db\u56db\u7ae0\uff1a\u88ab\u8bc5\u5492\u7684"}, {"id": 413506, "book_url": "\u7eb8\u795e/413506", "title": "\u4e94\u56db\u516b\u7ae0\uff1a\u6682\u505c\u884c\u52a8"}, {"id": 413503, "book_url": "\u7eb8\u795e/413503", "title": "\u4e94\u56db\u4e94\u7ae0\uff1a\u5bfb\u8e2a\u6e05\u6c49"}, {"id": 413507, "book_url": "\u7eb8\u795e/413507", "title": "\u4e94\u56db\u4e5d\u7ae0\uff1a\u67f3\u6697\u82b1\u660e"}, {"id": 413504, "book_url": "\u7eb8\u795e/413504", "title": "\u4e94\u56db\u516d\u7ae0\uff1a\u610f\u5916\u53d1\u73b0"}, {"id": 413508, "book_url": "\u7eb8\u795e/413508", "title": "\u4e94\u4e94\u96f6\u7ae0\uff1a\u53d8\u5f62\u91d1\u521a"}, {"id": 413505, "book_url": "\u7eb8\u795e/413505", "title": "\u4e94\u56db\u4e03\u7ae0\uff1a\u8d85\u7ea7\u707e\u96be"}, {"id": 413509, "book_url": "\u7eb8\u795e/413509", "title": "\u4e94\u4e94\u4e00\u7ae0\uff1a\u6700\u540e\u89c9\u609f"}, {"id": 413510, "book_url": "\u7eb8\u795e/413510", "title": "\u4e94\u4e94\u4e8c\u7ae0\uff1a\u7a81\u5165\u57fa\u5730"}, {"id": 413514, "book_url": "\u7eb8\u795e/413514", "title": "\u4e94\u4e94\u516d\u7ae0\uff1a\u56de\u4e61\u796d\u5960"}, {"id": 413511, "book_url": "\u7eb8\u795e/413511", "title": "\u4e94\u4e94\u4e09\u7ae0\uff1a\u5927\u4ec7\u5f97\u62a5"}, {"id": 413515, "book_url": "\u7eb8\u795e/413515", "title": "\u4e94\u4e94\u4e03\u7ae0\uff1a\u795e\u79d8\u767d\u8001"}, {"id": 413512, "book_url": "\u7eb8\u795e/413512", "title": "\u4e94\u4e94\u56db\u7ae0\uff1a\u5996\u5973\u6f5c\u9003"}, {"id": 413516, "book_url": "\u7eb8\u795e/413516", "title": "\u4e94\u4e94\u516b\u7ae0\uff1a\u5e7d\u8c37\u540e\u95e8"}, {"id": 413513, "book_url": "\u7eb8\u795e/413513", "title": "\u4e94\u4e94\u4e94\u7ae0\uff1a\u53cd\u653b\u5e8f\u66f2"}, {"id": 413517, "book_url": "\u7eb8\u795e/413517", "title": "\u4e94\u4e94\u4e5d\u7ae0\uff1a\u6c42\u5bff\u5e7d\u8c37\uff081\uff09"}, {"id": 413518, "book_url": "\u7eb8\u795e/413518", "title": "\u4e94\u516d\u96f6\u7ae0\uff1a\u9633\u5149\u88ab\u52ab"}, {"id": 413522, "book_url": "\u7eb8\u795e/413522", "title": "\u7ec8\u7ae0\uff1a\u9633\u5149\u4e4b\u96e8"}, {"id": 413519, "book_url": "\u7eb8\u795e/413519", "title": "\u4e94\u516d\u4e00\u7ae0\uff1a\u5165\u5929\u4e95\u5929"}, {"id": 413523, "book_url": "\u7eb8\u795e/413523", "title": "\u5c3e\u58f0\uff1a\u7eb8\u9e64\u96e8"}, {"id": 413520, "book_url": "\u7eb8\u795e/413520", "title": "\u4e94\u516d\u4e8c\u7ae0\uff1a\u6551\u5175\u4e91\u96c6"}, {"id": 413521, "book_url": "\u7eb8\u795e/413521", "title": "\u4e94\u516d\u4e09\u7ae0\uff1a\u5c0f\u96e8\u5230\u6765"}]}, "intro": "\u4e00\u672c\u771f\u6b63\u7684\u201c\u5f02\u80fd\u201d\u7c7b\u5c0f\u8bf4\uff0c\u53ea\u6709\u60f3\u4e0d\u5230\uff0c\u6ca1\u6709\u4e0d\u53ef\u80fd\u3002\r\n\u3000\u3000\u62e5\u6709\u5947\u602a\u80fd\u529b\u7684\u5c11\u5e74\u4efb\u6f5c\u60a0\uff0c\u4ece\u9694\u58c1\u7684\u9662\u5b50\u91cc\u62e3\u56de\u6765\u4e00\u4e2a\u795e\u79d8\u7684\u9ed1\u8863\u4eba\uff0c\u540c\u65f6\u76ee\u7779\u4e86\u4e00\u573a\u5b89\u9759\u800c\u9707\u64bc\u7684\u5927\u6218\u2026\u2026\r\n\u3000\u3000\u7136\u540e\uff0c\u5e73\u9759\u7684\u751f\u6d3b\u518d\u4e5f\u548c\u4ed6\u65e0\u7f18\uff0c\u4ed6\u6b65\u5165\u4e86\u4e00\u4e2a\u5c5e\u4e8e\u5f3a\u8005\u7684\u4e16\u754c\u3002\r\n\u3000\u3000\u201c\u5982\u81c2\u4f7f\u6307\u201d\u7684\u201c\u7eb8\u5203\u201d\uff0c\u201c\u7075\u9b42\u5206\u8eab\u201d\u7684\u201c\u7eb8\u9e64\u201d\uff0c\u201c\u7a7f\u900f\u7a7a\u95f4\u201d\u7684\u201c\u5077\u7aa5\u7b26\u201d\uff0c\u53ef\u4ee5\u6539\u53d8\u8eab\u4f53\u5e74\u9f84\u7684\u201c\u5c81\u6708\u8f6e\u56de\u201d\uff0c\u8eab\u4e0a\u6ca1\u6709\u4efb\u4f55\u51f6\u5668\u7684\u5c11\u5e74\uff0c\u5374\u662f\u8c01\u90fd\u4e0d\u6562\u5c0f\u89d1\u7684\u6050\u6016\u5b58\u5728\u3002\r\n\u3000\u3000\u8c01\u8bf4\u7eb8\u662f\u8106\u5f31\u7684\uff0c\u7075\u9b42\u662f\u865a\u65e0\u7684\uff0c\u65f6\u95f4\u548c\u7a7a\u95f4\u90fd\u662f\u65e0\u6cd5\u628a\u63e1\u7684\uff1f\r\n\u3000\u3000\u53ea\u662f\uff0c\u5f3a\u8005\u8d77\u521d\u90fd\u53ea\u662f\u5f31\u8005\u2026\u2026\r\n\u3000\u3000\u5f02\u80fd\u8005\u7684\u529b\u91cf\uff0c\u5374\u6709\u7740\u666e\u901a\u4eba\u7684\u5fc3\uff0c\u4f60\u6211\u90fd\u6709\u4e9b\u719f\u6089\u7684\u611f\u52a8......", "name": "\u7eb8\u795e"}