{"content": {"A": [{"id": 36992, "book_url": "\u9b54\u5e7b\u5f02\u95fb\u5f55/36992", "title": "\u5e8f\u7ae0 \u7edd\u5883"}, {"id": 36996, "book_url": "\u9b54\u5e7b\u5f02\u95fb\u5f55/36996", "title": "\u7b2c\u56db\u7ae0 \u9b54\u6cd5"}, {"id": 36993, "book_url": "\u9b54\u5e7b\u5f02\u95fb\u5f55/36993", "title": "\u7b2c\u4e00\u7ae0 \u65b0\u7684\u5f00\u59cb"}, {"id": 36997, "book_url": "\u9b54\u5e7b\u5f02\u95fb\u5f55/36997", "title": "\u7b2c\u4e94\u7ae0 \u540c\u884c"}, {"id": 36994, "book_url": "\u9b54\u5e7b\u5f02\u95fb\u5f55/36994", "title": "\u7b2c\u4e8c\u7ae0 \u521d\u6218"}, {"id": 36998, "book_url": "\u9b54\u5e7b\u5f02\u95fb\u5f55/36998", "title": "\u7b2c\u516d\u7ae0 \u5546\u961f"}, {"id": 36995, "book_url": "\u9b54\u5e7b\u5f02\u95fb\u5f55/36995", "title": "\u7b2c\u4e09\u7ae0 \u534f\u8bae"}, {"id": 36999, "book_url": "\u9b54\u5e7b\u5f02\u95fb\u5f55/36999", "title": "\u7b2c\u4e03\u7ae0 \u5e93\u83f2\u4e1d"}, {"id": 37000, "book_url": "\u9b54\u5e7b\u5f02\u95fb\u5f55/37000", "title": "\u7b2c\u516b\u7ae0 \u6218\u6597\u4e4b\u4eea"}, {"id": 37004, "book_url": "\u9b54\u5e7b\u5f02\u95fb\u5f55/37004", "title": "\u7b2c\u5341\u4e8c\u7ae0 \u76f8\u9047"}, {"id": 37001, "book_url": "\u9b54\u5e7b\u5f02\u95fb\u5f55/37001", "title": "\u7b2c\u4e5d\u7ae0 \u79bb\u5f00\u6c99\u6f20"}, {"id": 37005, "book_url": "\u9b54\u5e7b\u5f02\u95fb\u5f55/37005", "title": "\u7b2c\u5341\u4e09\u7ae0 \u81ea\u6211\u8ba4\u5b9a"}, {"id": 37002, "book_url": "\u9b54\u5e7b\u5f02\u95fb\u5f55/37002", "title": "\u7b2c\u5341\u7ae0 \u8d4f\u91d1\u6740\u624b"}, {"id": 37006, "book_url": "\u9b54\u5e7b\u5f02\u95fb\u5f55/37006", "title": "\u7b2c\u5341\u56db\u7ae0 \u6b7b\u7075\u4eba\u5076"}, {"id": 37003, "book_url": "\u9b54\u5e7b\u5f02\u95fb\u5f55/37003", "title": "\u7b2c\u5341\u4e00\u7ae0 \u8bf7\u6c42\u4e0e\u5b88\u62a4"}, {"id": 37007, "book_url": "\u9b54\u5e7b\u5f02\u95fb\u5f55/37007", "title": "\u7b2c\u5341\u4e94\u7ae0 \u8363\u8000\u57ce"}, {"id": 37008, "book_url": "\u9b54\u5e7b\u5f02\u95fb\u5f55/37008", "title": "\u7b2c\u5341\u516d\u7ae0 \u9aa4\u53d8"}, {"id": 37012, "book_url": "\u9b54\u5e7b\u5f02\u95fb\u5f55/37012", "title": "\u7b2c\u4e8c\u5341\u7ae0 \u539f\u5219\u95ee\u9898"}, {"id": 37009, "book_url": "\u9b54\u5e7b\u5f02\u95fb\u5f55/37009", "title": "\u7b2c\u5341\u4e03\u7ae0 \u5c0f\u4eba\u7269\u7684\u60b2\u5267"}, {"id": 37013, "book_url": "\u9b54\u5e7b\u5f02\u95fb\u5f55/37013", "title": "\u7b2c\u4e8c\u5341\u4e00\u7ae0 \u5b66\u9662"}, {"id": 37010, "book_url": "\u9b54\u5e7b\u5f02\u95fb\u5f55/37010", "title": "\u7b2c\u5341\u516b\u7ae0 \u5929\u8d4b\u5b88\u62a4\u8005"}, {"id": 37014, "book_url": "\u9b54\u5e7b\u5f02\u95fb\u5f55/37014", "title": "\u7b2c\u4e8c\u5341\u4e8c\u7ae0 \u5951\u7ea6"}, {"id": 37011, "book_url": "\u9b54\u5e7b\u5f02\u95fb\u5f55/37011", "title": "\u7b2c\u5341\u4e5d\u7ae0 \u78e8\u5408"}, {"id": 37015, "book_url": "\u9b54\u5e7b\u5f02\u95fb\u5f55/37015", "title": "\u7b2c\u4e8c\u5341\u4e09\u7ae0 \u521d\u6b21\u6d4b\u8bd5"}, {"id": 37016, "book_url": "\u9b54\u5e7b\u5f02\u95fb\u5f55/37016", "title": "\u7b2c\u4e8c\u5341\u56db\u7ae0 \u8fd9\u662f\u54ea\u91cc\uff1f"}, {"id": 37020, "book_url": "\u9b54\u5e7b\u5f02\u95fb\u5f55/37020", "title": "\u7b2c\u4e8c\u5341\u516b\u7ae0 \u672b\u8def\u4e4b\u521d"}, {"id": 37017, "book_url": "\u9b54\u5e7b\u5f02\u95fb\u5f55/37017", "title": "\u7b2c\u4e8c\u5341\u4e94\u7ae0 \u6f5c\u4f0f\u7684\u5371\u673a"}, {"id": 37021, "book_url": "\u9b54\u5e7b\u5f02\u95fb\u5f55/37021", "title": "\u7b2c\u4e8c\u5341\u4e5d\u7ae0 \u672b\u8def\u4e4b\u4e2d"}, {"id": 37018, "book_url": "\u9b54\u5e7b\u5f02\u95fb\u5f55/37018", "title": "\u7b2c\u4e8c\u5341\u516d\u7ae0 \u6b7b\u7075\u9a91\u58eb"}, {"id": 37022, "book_url": "\u9b54\u5e7b\u5f02\u95fb\u5f55/37022", "title": "\u7b2c\u4e09\u5341\u7ae0 \u672b\u8def\u4e4b\u7ec8"}, {"id": 37019, "book_url": "\u9b54\u5e7b\u5f02\u95fb\u5f55/37019", "title": "\u7b2c\u4e8c\u5341\u4e03\u7ae0 \u7591\u4e91"}, {"id": 37023, "book_url": "\u9b54\u5e7b\u5f02\u95fb\u5f55/37023", "title": "\u7b2c\u4e09\u5341\u4e00\u7ae0 \u4ea1\u7075\u57ce\u5821"}, {"id": 37024, "book_url": "\u9b54\u5e7b\u5f02\u95fb\u5f55/37024", "title": "\u7b2c\u4e09\u5341\u4e8c\u7ae0 \u4ea1\u7075\u6cd5\u5e08"}, {"id": 37028, "book_url": "\u9b54\u5e7b\u5f02\u95fb\u5f55/37028", "title": "\u7b2c\u4e09\u5341\u516d\u7ae0 \u4f2a\u9020\u7684\u8fc7\u53bb"}, {"id": 37025, "book_url": "\u9b54\u5e7b\u5f02\u95fb\u5f55/37025", "title": "\u7b2c\u4e09\u5341\u4e09\u7ae0 \u751f\u547d\u4e4b\u57ce"}, {"id": 37029, "book_url": "\u9b54\u5e7b\u5f02\u95fb\u5f55/37029", "title": "\u7b2c\u4e09\u5341\u4e03\u7ae0 \u56e0\u4e0e\u679c\u7684\u65e0\u9650"}, {"id": 37026, "book_url": "\u9b54\u5e7b\u5f02\u95fb\u5f55/37026", "title": "\u7b2c\u4e09\u5341\u56db\u7ae0 \u91cd\u65b0\u5f00\u59cb\u4e4b\u4e8c"}, {"id": 37030, "book_url": "\u9b54\u5e7b\u5f02\u95fb\u5f55/37030", "title": "\u7b2c\u4e09\u5341\u516b\u7ae0 \u5e7d\u6697\u4e4b\u5854\u7684\u6765\u5ba2"}, {"id": 37027, "book_url": "\u9b54\u5e7b\u5f02\u95fb\u5f55/37027", "title": "\u7b2c\u4e09\u5341\u4e94\u7ae0 \u5b88\u62a4\u4e4b\u8005"}, {"id": 37031, "book_url": "\u9b54\u5e7b\u5f02\u95fb\u5f55/37031", "title": "\u7b2c\u4e09\u5341\u4e5d\u7ae0 \u6b7b\u7075\u9b54\u6cd5"}, {"id": 37032, "book_url": "\u9b54\u5e7b\u5f02\u95fb\u5f55/37032", "title": "\u7b2c\u56db\u5341\u7ae0 \u8ff7\u56e0"}, {"id": 37036, "book_url": "\u9b54\u5e7b\u5f02\u95fb\u5f55/37036", "title": "\u7b2c\u56db\u5341\u56db\u7ae0 \u65e0\u804a\u7684\u9ebb\u70e6"}, {"id": 37033, "book_url": "\u9b54\u5e7b\u5f02\u95fb\u5f55/37033", "title": "\u7b2c\u56db\u5341\u4e00\u7ae0 \u4ea4\u6d89\u4e4b\u540e"}, {"id": 37037, "book_url": "\u9b54\u5e7b\u5f02\u95fb\u5f55/37037", "title": "\u7b2c\u56db\u5341\u4e94\u7ae0 \u6f5c\u4f0f"}, {"id": 37034, "book_url": "\u9b54\u5e7b\u5f02\u95fb\u5f55/37034", "title": "\u7b2c\u56db\u5341\u4e8c\u7ae0 \u65e0\u6cd5\u62d2\u7edd\u7684\u547d\u4ee4"}, {"id": 37038, "book_url": "\u9b54\u5e7b\u5f02\u95fb\u5f55/37038", "title": "\u7b2c\u56db\u5341\u516d\u7ae0 \u5e7d\u6697\u4e4b\u4e3b"}, {"id": 37035, "book_url": "\u9b54\u5e7b\u5f02\u95fb\u5f55/37035", "title": "\u7b2c\u56db\u5341\u4e09\u7ae0 \u4e00\u80dc\u4e00\u8d25"}, {"id": 37039, "book_url": "\u9b54\u5e7b\u5f02\u95fb\u5f55/37039", "title": "\u7b2c\u56db\u5341\u4e03\u7ae0 \u91cd\u7f6e"}, {"id": 37040, "book_url": "\u9b54\u5e7b\u5f02\u95fb\u5f55/37040", "title": "\u7b2c\u56db\u5341\u516b\u7ae0 \u6700\u7ec8\u51b3\u5b9a"}, {"id": 37044, "book_url": "\u9b54\u5e7b\u5f02\u95fb\u5f55/37044", "title": "\u7b2c\u4e94\u5341\u4e8c\u7ae0 \u4e0e\u5251\u4e3a\u654c"}, {"id": 37041, "book_url": "\u9b54\u5e7b\u5f02\u95fb\u5f55/37041", "title": "\u7b2c\u56db\u5341\u4e5d\u7ae0 \u65b0\u7684\u9009\u62e9"}, {"id": 37045, "book_url": "\u9b54\u5e7b\u5f02\u95fb\u5f55/37045", "title": "\u7b2c\u4e94\u5341\u4e09\u7ae0 \u9690\u7792\u4e4b\u8bc1"}, {"id": 37042, "book_url": "\u9b54\u5e7b\u5f02\u95fb\u5f55/37042", "title": "\u7b2c\u4e94\u5341\u7ae0 \u6539\u53d8"}, {"id": 37046, "book_url": "\u9b54\u5e7b\u5f02\u95fb\u5f55/37046", "title": "\u7b2c\u4e94\u5341\u56db\u7ae0 \u4e2d\u95f4\u6d3e\u7cfb"}, {"id": 37043, "book_url": "\u9b54\u5e7b\u5f02\u95fb\u5f55/37043", "title": "\u7b2c\u4e94\u5341\u4e00\u7ae0 \u8ba1\u5212"}, {"id": 37047, "book_url": "\u9b54\u5e7b\u5f02\u95fb\u5f55/37047", "title": "\u7b2c\u4e94\u5341\u4e94\u7ae0 \u8ff7\u5931"}, {"id": 37048, "book_url": "\u9b54\u5e7b\u5f02\u95fb\u5f55/37048", "title": "\u7b2c\u4e94\u5341\u516d\u7ae0 \u9a84\u50b2\u4e0e\u4fe1\u8d56"}, {"id": 37052, "book_url": "\u9b54\u5e7b\u5f02\u95fb\u5f55/37052", "title": "\u7b2c\u516d\u5341\u7ae0 \u5b66\u9662\u8bc4\u8bae\u4f1a"}, {"id": 37049, "book_url": "\u9b54\u5e7b\u5f02\u95fb\u5f55/37049", "title": "\u7b2c\u4e94\u5341\u4e03\u7ae0 \u665a\u5bb4"}, {"id": 37053, "book_url": "\u9b54\u5e7b\u5f02\u95fb\u5f55/37053", "title": "\u7b2c\u516d\u5341\u4e00\u7ae0 \u96c6\u5408"}, {"id": 37050, "book_url": "\u9b54\u5e7b\u5f02\u95fb\u5f55/37050", "title": "\u7b2c\u4e94\u5341\u516b\u7ae0 \u4e09\u91cd\u8eab\u4efd"}, {"id": 37054, "book_url": "\u9b54\u5e7b\u5f02\u95fb\u5f55/37054", "title": "\u7b2c\u516d\u5341\u4e8c\u7ae0 \u7ade\u6280"}, {"id": 37051, "book_url": "\u9b54\u5e7b\u5f02\u95fb\u5f55/37051", "title": "\u7b2c\u4e94\u5341\u4e5d\u7ae0 \u4e0d\u5165\u864e\u7a74"}, {"id": 37055, "book_url": "\u9b54\u5e7b\u5f02\u95fb\u5f55/37055", "title": "\u7b2c\u516d\u5341\u4e09\u7ae0 \u518d\u6b21\u9047\u654c"}, {"id": 37056, "book_url": "\u9b54\u5e7b\u5f02\u95fb\u5f55/37056", "title": "\u7b2c\u516d\u5341\u56db\u7ae0 \u75af\u72c2\u7684\u62a5\u590d"}, {"id": 37060, "book_url": "\u9b54\u5e7b\u5f02\u95fb\u5f55/37060", "title": "\u7b2c\u516d\u5341\u516b\u7ae0 \u521d\u5165\u68ee\u6797"}, {"id": 37057, "book_url": "\u9b54\u5e7b\u5f02\u95fb\u5f55/37057", "title": "\u7b2c\u516d\u5341\u4e94\u7ae0 \u5728\u8def\u4e0a"}, {"id": 37061, "book_url": "\u9b54\u5e7b\u5f02\u95fb\u5f55/37061", "title": "\u7b2c\u516d\u5341\u4e5d\u7ae0 \u6839\u636e\u5730"}, {"id": 37058, "book_url": "\u9b54\u5e7b\u5f02\u95fb\u5f55/37058", "title": "\u7b2c\u516d\u5341\u516d\u7ae0 \u5b88\u591c"}, {"id": 37062, "book_url": "\u9b54\u5e7b\u5f02\u95fb\u5f55/37062", "title": "\u7b2c\u4e03\u5341\u7ae0 \u65b0\u7684\u51b2\u7a81"}, {"id": 37059, "book_url": "\u9b54\u5e7b\u5f02\u95fb\u5f55/37059", "title": "\u7b2c\u516d\u5341\u4e03\u7ae0 \u5fae\u5999\u7684\u52a8\u6447"}, {"id": 37063, "book_url": "\u9b54\u5e7b\u5f02\u95fb\u5f55/37063", "title": "\u7b2c\u4e03\u5341\u4e00\u7ae0 \u5bc6\u8c0b"}, {"id": 37064, "book_url": "\u9b54\u5e7b\u5f02\u95fb\u5f55/37064", "title": "\u7b2c\u4e03\u5341\u4e8c\u7ae0 \u771f\u610f"}, {"id": 37068, "book_url": "\u9b54\u5e7b\u5f02\u95fb\u5f55/37068", "title": "\u7b2c\u4e03\u5341\u516d\u7ae0 \u8ba1\u5212\u4e4b\u5185"}, {"id": 37065, "book_url": "\u9b54\u5e7b\u5f02\u95fb\u5f55/37065", "title": "\u7b2c\u4e03\u5341\u4e09\u7ae0 \u5251\u4e4b\u4f7f\u8005"}, {"id": 37069, "book_url": "\u9b54\u5e7b\u5f02\u95fb\u5f55/37069", "title": "\u7b2c\u4e03\u5341\u4e03\u7ae0 \u6697\u6f6e\u6d8c\u52a8\u4e0b"}, {"id": 37066, "book_url": "\u9b54\u5e7b\u5f02\u95fb\u5f55/37066", "title": "\u7b2c\u4e03\u5341\u56db\u7ae0 \u6df1\u591c\u6b7b\u6597"}, {"id": 37070, "book_url": "\u9b54\u5e7b\u5f02\u95fb\u5f55/37070", "title": "\u7b2c\u4e03\u5341\u516b\u7ae0 \u6f5c\u4f0f\u4e4b\u7269"}, {"id": 37067, "book_url": "\u9b54\u5e7b\u5f02\u95fb\u5f55/37067", "title": "\u7b2c\u4e03\u5341\u4e94\u7ae0 \u5b88\u682a\u5f85\u5154"}, {"id": 37071, "book_url": "\u9b54\u5e7b\u5f02\u95fb\u5f55/37071", "title": "\u7b2c\u4e03\u5341\u4e5d\u7ae0 \u9ed1\u7ffc\u4e4b\u9f99"}, {"id": 37072, "book_url": "\u9b54\u5e7b\u5f02\u95fb\u5f55/37072", "title": "\u7b2c\u516b\u5341\u7ae0 \u7f6a\u5b7d\u6b66\u88c5"}, {"id": 37076, "book_url": "\u9b54\u5e7b\u5f02\u95fb\u5f55/37076", "title": "\u7b2c\u516b\u5341\u56db\u7ae0 \u65b0\u7684\u8bbf\u5ba2"}, {"id": 37073, "book_url": "\u9b54\u5e7b\u5f02\u95fb\u5f55/37073", "title": "\u7b2c\u516b\u5341\u4e00\u7ae0 \u5026\u6020\u7684\u4f11\u606f"}, {"id": 37077, "book_url": "\u9b54\u5e7b\u5f02\u95fb\u5f55/37077", "title": "\u7b2c\u516b\u5341\u4e94\u7ae0 \u4e34\u65f6\u9886\u4e3b"}, {"id": 37074, "book_url": "\u9b54\u5e7b\u5f02\u95fb\u5f55/37074", "title": "\u7b2c\u516b\u5341\u4e8c\u7ae0 \u95f4\u9699"}, {"id": 37078, "book_url": "\u9b54\u5e7b\u5f02\u95fb\u5f55/37078", "title": "\u7b2c\u516b\u5341\u516d\u7ae0 \u5947\u601d\u602a\u60f3"}, {"id": 37075, "book_url": "\u9b54\u5e7b\u5f02\u95fb\u5f55/37075", "title": "\u7b2c\u516b\u5341\u4e09\u7ae0 \u96e8\u4e2d\u591c\u4e0b"}, {"id": 37079, "book_url": "\u9b54\u5e7b\u5f02\u95fb\u5f55/37079", "title": "\u7b2c\u516b\u5341\u4e03\u7ae0 \u81ea\u8fdc\u65b9\u6765"}, {"id": 37080, "book_url": "\u9b54\u5e7b\u5f02\u95fb\u5f55/37080", "title": "\u7b2c\u516b\u5341\u516b\u7ae0 \u6700\u5f31\u72b6\u6001"}, {"id": 37084, "book_url": "\u9b54\u5e7b\u5f02\u95fb\u5f55/37084", "title": "\u7b2c\u4e5d\u5341\u4e8c\u7ae0 \u6761\u4ef6"}, {"id": 37081, "book_url": "\u9b54\u5e7b\u5f02\u95fb\u5f55/37081", "title": "\u7b2c\u516b\u5341\u4e5d\u7ae0 \u82b1\u9e1f\u98ce\u6708"}, {"id": 37085, "book_url": "\u9b54\u5e7b\u5f02\u95fb\u5f55/37085", "title": "\u7b2c\u4e5d\u5341\u4e09\u7ae0 \u4f60\u6b7b\u6211\u6d3b"}, {"id": 37082, "book_url": "\u9b54\u5e7b\u5f02\u95fb\u5f55/37082", "title": "\u7b2c\u4e5d\u5341\u7ae0 \u5f02\u5e38\u62f7\u95ee"}, {"id": 37086, "book_url": "\u9b54\u5e7b\u5f02\u95fb\u5f55/37086", "title": "\u7b2c\u4e5d\u5341\u56db\u7ae0 \u5e7b\u8c61\u4e16\u754c"}, {"id": 37083, "book_url": "\u9b54\u5e7b\u5f02\u95fb\u5f55/37083", "title": "\u7b2c\u4e5d\u5341\u4e00\u7ae0 \u5e55\u540e\u4e0e\u53f0\u524d"}, {"id": 37087, "book_url": "\u9b54\u5e7b\u5f02\u95fb\u5f55/37087", "title": "\u7b2c\u4e5d\u5341\u4e94\u7ae0 \u7981\u5fcc\u9b54\u7075"}, {"id": 37088, "book_url": "\u9b54\u5e7b\u5f02\u95fb\u5f55/37088", "title": "\u7b2c\u4e5d\u5341\u516d\u7ae0 \u5df2\u7ecf\u6b7b\u4e86"}, {"id": 37092, "book_url": "\u9b54\u5e7b\u5f02\u95fb\u5f55/37092", "title": "\u7b2c\u4e00\u767e\u7ae0 \u5947\u7279\u7684\u4f63\u5175\u56e2"}, {"id": 37089, "book_url": "\u9b54\u5e7b\u5f02\u95fb\u5f55/37089", "title": "\u7b2c\u4e5d\u5341\u4e03\u7ae0 \u987a\u6c34\u63a8\u821f"}, {"id": 37093, "book_url": "\u9b54\u5e7b\u5f02\u95fb\u5f55/37093", "title": "\u7b2c\u4e00\u767e\u96f6\u4e00\u7ae0 \u8fd0\u7528"}, {"id": 37090, "book_url": "\u9b54\u5e7b\u5f02\u95fb\u5f55/37090", "title": "\u7b2c\u4e5d\u5341\u516b\u7ae0 \u98a4\u52a8\u4e4b\u97f3"}, {"id": 37094, "book_url": "\u9b54\u5e7b\u5f02\u95fb\u5f55/37094", "title": "\u7b2c\u4e00\u767e\u96f6\u4e8c\u7ae0 \u6000\u7591\u7684\u79cd\u5b50"}, {"id": 37091, "book_url": "\u9b54\u5e7b\u5f02\u95fb\u5f55/37091", "title": "\u7b2c\u4e5d\u5341\u4e5d\u7ae0 \u517d\u4eba\u4f63\u5175"}, {"id": 37095, "book_url": "\u9b54\u5e7b\u5f02\u95fb\u5f55/37095", "title": "\u7b2c\u4e00\u767e\u96f6\u4e09\u7ae0 \u52a8\u8361\u7684\u5f00\u59cb"}, {"id": 37096, "book_url": "\u9b54\u5e7b\u5f02\u95fb\u5f55/37096", "title": "\u7b2c\u4e00\u767e\u96f6\u56db\u7ae0 \u9003\u72af"}, {"id": 37100, "book_url": "\u9b54\u5e7b\u5f02\u95fb\u5f55/37100", "title": "\u7b2c\u4e00\u767e\u96f6\u516b\u7ae0 \u8bd5\u63a2"}, {"id": 37097, "book_url": "\u9b54\u5e7b\u5f02\u95fb\u5f55/37097", "title": "\u7b2c\u4e00\u767e\u96f6\u4e94\u7ae0 \u4e0d\u51c6\u53cd\u6297"}, {"id": 37101, "book_url": "\u9b54\u5e7b\u5f02\u95fb\u5f55/37101", "title": "\u7b2c\u4e00\u767e\u96f6\u4e5d\u7ae0 \u8ff7\u96fe"}, {"id": 37098, "book_url": "\u9b54\u5e7b\u5f02\u95fb\u5f55/37098", "title": "\u7b2c\u4e00\u767e\u96f6\u516d\u7ae0 \u5080\u5121\u4e4b\u5fc3"}, {"id": 37102, "book_url": "\u9b54\u5e7b\u5f02\u95fb\u5f55/37102", "title": "\u7b2c\u4e00\u767e\u4e00\u5341\u7ae0 \u665a\u5bb4"}, {"id": 37099, "book_url": "\u9b54\u5e7b\u5f02\u95fb\u5f55/37099", "title": "\u7b2c\u4e00\u767e\u96f6\u4e03\u7ae0 \u6697\u4e2d\u5e03\u5c40"}, {"id": 37103, "book_url": "\u9b54\u5e7b\u5f02\u95fb\u5f55/37103", "title": "\u7b2c\u4e00\u767e\u4e00\u5341\u4e00\u7ae0 \u6df7\u4e71\u7684\u9634\u8c0b"}, {"id": 37104, "book_url": "\u9b54\u5e7b\u5f02\u95fb\u5f55/37104", "title": "\u7b2c\u4e00\u767e\u4e00\u5341\u4e8c\u7ae0 \u591c\u88ad"}, {"id": 37108, "book_url": "\u9b54\u5e7b\u5f02\u95fb\u5f55/37108", "title": "\u7b2c\u4e00\u767e\u4e00\u5341\u516d\u7ae0 \u8ba1\u5212"}, {"id": 37105, "book_url": "\u9b54\u5e7b\u5f02\u95fb\u5f55/37105", "title": "\u7b2c\u4e00\u767e\u4e00\u5341\u4e09\u7ae0 \u6df7\u6218"}, {"id": 37109, "book_url": "\u9b54\u5e7b\u5f02\u95fb\u5f55/37109", "title": "\u7b2c\u4e00\u767e\u4e00\u5341\u4e03\u7ae0 \u4e00\u8def\u5411\u5317"}, {"id": 37106, "book_url": "\u9b54\u5e7b\u5f02\u95fb\u5f55/37106", "title": "\u7b2c\u4e00\u767e\u4e00\u5341\u56db\u7ae0 \u618e\u6076\u4e4b\u6e90"}, {"id": 37110, "book_url": "\u9b54\u5e7b\u5f02\u95fb\u5f55/37110", "title": "\u7b2c\u4e00\u767e\u4e00\u5341\u516b\u7ae0 \u7b2c\u4e09\u4eba"}, {"id": 37107, "book_url": "\u9b54\u5e7b\u5f02\u95fb\u5f55/37107", "title": "\u7b2c\u4e00\u767e\u4e00\u5341\u4e94\u7ae0 \u79d8\u62a5"}, {"id": 37111, "book_url": "\u9b54\u5e7b\u5f02\u95fb\u5f55/37111", "title": "\u7b2c\u4e00\u767e\u4e00\u5341\u4e5d\u7ae0 \u5c60\u57ce"}, {"id": 37112, "book_url": "\u9b54\u5e7b\u5f02\u95fb\u5f55/37112", "title": "\u7b2c\u4e00\u767e\u4e8c\u5341\u7ae0 \u51b0\u9c7c"}, {"id": 37116, "book_url": "\u9b54\u5e7b\u5f02\u95fb\u5f55/37116", "title": "\u7b2c\u4e00\u767e\u4e8c\u5341\u56db\u7ae0 \u4e3a\u4e86\u81ea\u5df1"}, {"id": 37113, "book_url": "\u9b54\u5e7b\u5f02\u95fb\u5f55/37113", "title": "\u7b2c\u4e00\u767e\u4e8c\u5341\u4e00\u7ae0 \u8ba1\u5212\u66f4\u65b0"}, {"id": 37117, "book_url": "\u9b54\u5e7b\u5f02\u95fb\u5f55/37117", "title": "\u7b2c\u4e00\u767e\u4e8c\u5341\u4e94\u7ae0 \u7a81\u88ad\u6218"}, {"id": 37114, "book_url": "\u9b54\u5e7b\u5f02\u95fb\u5f55/37114", "title": "\u7b2c\u4e00\u767e\u4e8c\u5341\u4e8c\u7ae0 \u70ae\u7070"}, {"id": 37118, "book_url": "\u9b54\u5e7b\u5f02\u95fb\u5f55/37118", "title": "\u7b2c\u4e00\u767e\u4e8c\u5341\u516d\u7ae0 \u6784\u88c5\u6b66\u5668"}, {"id": 37115, "book_url": "\u9b54\u5e7b\u5f02\u95fb\u5f55/37115", "title": "\u7b2c\u4e00\u767e\u4e8c\u5341\u4e09\u7ae0 \u80fd\u529b"}, {"id": 37119, "book_url": "\u9b54\u5e7b\u5f02\u95fb\u5f55/37119", "title": "\u7b2c\u4e00\u767e\u4e8c\u5341\u4e03\u7ae0 \u5341\u9762\u57cb\u4f0f"}, {"id": 37120, "book_url": "\u9b54\u5e7b\u5f02\u95fb\u5f55/37120", "title": "\u7b2c\u4e00\u767e\u4e8c\u5341\u516b\u7ae0 \u95f4\u9699"}, {"id": 37124, "book_url": "\u9b54\u5e7b\u5f02\u95fb\u5f55/37124", "title": "\u7b2c\u4e00\u767e\u4e09\u5341\u4e8c\u7ae0 \u6df1\u591c\u8425\u5730"}, {"id": 37121, "book_url": "\u9b54\u5e7b\u5f02\u95fb\u5f55/37121", "title": "\u7b2c\u4e00\u767e\u4e8c\u5341\u4e5d\u7ae0 \u57fa\u7840\u953b\u70bc"}, {"id": 37125, "book_url": "\u9b54\u5e7b\u5f02\u95fb\u5f55/37125", "title": "\u7b2c\u4e00\u767e\u4e09\u5341\u4e09\u7ae0 \u6708\u4e0b\u7684\u8d5e\u7f8e\u8bd7"}, {"id": 37122, "book_url": "\u9b54\u5e7b\u5f02\u95fb\u5f55/37122", "title": "\u7b2c\u4e00\u767e\u4e09\u5341\u7ae0 \u4e0d\u660e\u6240\u4ee5"}, {"id": 37126, "book_url": "\u9b54\u5e7b\u5f02\u95fb\u5f55/37126", "title": "\u7b2c\u4e00\u767e\u4e09\u5341\u56db\u7ae0 \u4f20\u5947\u5251\u672f\u58eb"}, {"id": 37123, "book_url": "\u9b54\u5e7b\u5f02\u95fb\u5f55/37123", "title": "\u7b2c\u4e00\u767e\u4e09\u5341\u4e00\u7ae0 \u4e45\u8fdc\u7684\u8fc7\u53bb"}, {"id": 37127, "book_url": "\u9b54\u5e7b\u5f02\u95fb\u5f55/37127", "title": "\u7b2c\u4e00\u767e\u4e09\u5341\u56db\u7ae0 \u4f20\u5947\u5251\u672f\u58eb"}, {"id": 37128, "book_url": "\u9b54\u5e7b\u5f02\u95fb\u5f55/37128", "title": "\u7b2c\u4e00\u767e\u4e09\u5341\u4e94\u7ae0 \u72c2\u6218"}, {"id": 37132, "book_url": "\u9b54\u5e7b\u5f02\u95fb\u5f55/37132", "title": "\u7b2c\u4e00\u767e\u4e09\u5341\u4e5d\u7ae0 \u6df1\u7b97"}, {"id": 37129, "book_url": "\u9b54\u5e7b\u5f02\u95fb\u5f55/37129", "title": "\u7b2c\u4e00\u767e\u4e09\u5341\u516d\u7ae0 \u4e8c\u5bf9\u4e00"}, {"id": 37133, "book_url": "\u9b54\u5e7b\u5f02\u95fb\u5f55/37133", "title": "\u7b2c\u4e00\u767e\u56db\u5341\u7ae0 \u91ce\u706b"}, {"id": 37130, "book_url": "\u9b54\u5e7b\u5f02\u95fb\u5f55/37130", "title": "\u7b2c\u4e00\u767e\u4e09\u5341\u4e03\u7ae0 \u7ed3\u675f\u4e4b\u540e"}, {"id": 37134, "book_url": "\u9b54\u5e7b\u5f02\u95fb\u5f55/37134", "title": "\u7b2c\u4e00\u767e\u56db\u5341\u4e00\u7ae0 \u6563\u64ad\u7684\u4e0d\u5b89"}, {"id": 37131, "book_url": "\u9b54\u5e7b\u5f02\u95fb\u5f55/37131", "title": "\u7b2c\u4e00\u767e\u4e09\u5341\u516b\u7ae0 \u7591\u95ee"}, {"id": 37135, "book_url": "\u9b54\u5e7b\u5f02\u95fb\u5f55/37135", "title": "\u7b2c\u4e00\u767e\u56db\u5341\u4e8c\u7ae0 \u4f20\u8bf4\u7684\u5c01\u5370"}, {"id": 37136, "book_url": "\u9b54\u5e7b\u5f02\u95fb\u5f55/37136", "title": "\u7b2c\u4e00\u767e\u56db\u5341\u4e09\u7ae0 \u5bc2\u9759\u4e4b\u591c"}, {"id": 37140, "book_url": "\u9b54\u5e7b\u5f02\u95fb\u5f55/37140", "title": "\u7b2c\u4e00\u767e\u56db\u5341\u4e03\u7ae0 \u8fde\u9501\u53cd\u5e94"}, {"id": 37137, "book_url": "\u9b54\u5e7b\u5f02\u95fb\u5f55/37137", "title": "\u7b2c\u4e00\u767e\u56db\u5341\u56db\u7ae0 \u5fc5\u987b\u5e78\u5b58"}, {"id": 37141, "book_url": "\u9b54\u5e7b\u5f02\u95fb\u5f55/37141", "title": "\u7b2c\u4e00\u767e\u56db\u5341\u516b\u7ae0 \u7ebf\u7d22"}, {"id": 37138, "book_url": "\u9b54\u5e7b\u5f02\u95fb\u5f55/37138", "title": "\u7b2c\u4e00\u767e\u56db\u5341\u4e94\u7ae0 \u865a\u5c40"}, {"id": 37142, "book_url": "\u9b54\u5e7b\u5f02\u95fb\u5f55/37142", "title": "\u7b2c\u4e00\u767e\u56db\u5341\u4e5d\u7ae0 \u7f57\u7433\u4e4b\u4f24"}, {"id": 37139, "book_url": "\u9b54\u5e7b\u5f02\u95fb\u5f55/37139", "title": "\u7b2c\u4e00\u767e\u56db\u5341\u516d\u7ae0 \u6f6e\u6c50\u4e4b\u524d"}, {"id": 37143, "book_url": "\u9b54\u5e7b\u5f02\u95fb\u5f55/37143", "title": "\u7b2c\u4e00\u767e\u4e94\u5341\u7ae0 \u5b88\u62a4\u7cbe\u7075"}, {"id": 37144, "book_url": "\u9b54\u5e7b\u5f02\u95fb\u5f55/37144", "title": "\u7b2c\u4e00\u767e\u4e94\u5341\u4e00\u7ae0 \u4f20\u5947\u4e4b\u5973"}, {"id": 37148, "book_url": "\u9b54\u5e7b\u5f02\u95fb\u5f55/37148", "title": "\u7b2c\u4e00\u767e\u4e94\u5341\u4e94\u7ae0 \u6536\u62fe\u5584\u540e"}, {"id": 37145, "book_url": "\u9b54\u5e7b\u5f02\u95fb\u5f55/37145", "title": "\u7b2c\u4e00\u767e\u4e94\u5341\u4e8c\u7ae0 \u585e\u4f2f\u62c9\u65af\u4e4b\u7259"}, {"id": 37149, "book_url": "\u9b54\u5e7b\u5f02\u95fb\u5f55/37149", "title": "\u7b2c\u4e00\u767e\u4e94\u5341\u516d\u7ae0 \u8fb9\u5883\u4f11\u5047"}, {"id": 37146, "book_url": "\u9b54\u5e7b\u5f02\u95fb\u5f55/37146", "title": "\u7b2c\u4e00\u767e\u4e94\u5341\u4e09\u7ae0 \u71c3\u70e7\u795e\u9524"}, {"id": 37150, "book_url": "\u9b54\u5e7b\u5f02\u95fb\u5f55/37150", "title": "\u7b2c\u4e00\u767e\u4e94\u5341\u4e03\u7ae0 \u4e09\u5341\u4e5d\u53f7"}, {"id": 37147, "book_url": "\u9b54\u5e7b\u5f02\u95fb\u5f55/37147", "title": "\u7b2c\u4e00\u767e\u4e94\u5341\u56db\u7ae0 \u4e07\u7269\u85d0\u89c6"}, {"id": 37151, "book_url": "\u9b54\u5e7b\u5f02\u95fb\u5f55/37151", "title": "\u7b2c\u4e00\u767e\u4e94\u5341\u516b\u7ae0 \u5348\u540e\u8336\u4f1a"}, {"id": 37152, "book_url": "\u9b54\u5e7b\u5f02\u95fb\u5f55/37152", "title": "\u7b2c\u4e00\u767e\u4e94\u5341\u4e5d\u7ae0 \u590d\u6742\u5173\u7cfb"}, {"id": 37156, "book_url": "\u9b54\u5e7b\u5f02\u95fb\u5f55/37156", "title": "\u7b2c\u4e00\u767e\u516d\u5341\u4e09\u7ae0 \u82cd\u5929\u4e4b\u5854"}, {"id": 37153, "book_url": "\u9b54\u5e7b\u5f02\u95fb\u5f55/37153", "title": "\u7b2c\u4e00\u767e\u516d\u5341\u7ae0 \u5c0f\u8d35\u65cf"}, {"id": 37157, "book_url": "\u9b54\u5e7b\u5f02\u95fb\u5f55/37157", "title": "\u7b2c\u4e00\u767e\u516d\u5341\u56db\u7ae0 \u5931\u53bb\u7684\u5c01\u5370"}, {"id": 37154, "book_url": "\u9b54\u5e7b\u5f02\u95fb\u5f55/37154", "title": "\u7b2c\u4e00\u767e\u516d\u5341\u4e00\u7ae0 \u9b54\u6cd5\u4e4b\u7075"}, {"id": 37158, "book_url": "\u9b54\u5e7b\u5f02\u95fb\u5f55/37158", "title": "\u7b2c\u4e00\u767e\u516d\u5341\u4e94\u7ae0 \u65b0\u7684\u5b88\u62a4\u8005"}, {"id": 37155, "book_url": "\u9b54\u5e7b\u5f02\u95fb\u5f55/37155", "title": "\u7b2c\u4e00\u767e\u516d\u5341\u4e8c\u7ae0 \u91cd\u56de\u738b\u57ce"}, {"id": 37159, "book_url": "\u9b54\u5e7b\u5f02\u95fb\u5f55/37159", "title": "\u7b2c\u4e00\u767e\u516d\u5341\u516d\u7ae0 \u5bf9\u6297"}, {"id": 37160, "book_url": "\u9b54\u5e7b\u5f02\u95fb\u5f55/37160", "title": "\u7b2c\u4e00\u767e\u516d\u5341\u4e03\u7ae0 \u65e0\u5948"}, {"id": 37164, "book_url": "\u9b54\u5e7b\u5f02\u95fb\u5f55/37164", "title": "\u7b2c\u4e00\u767e\u4e03\u5341\u4e00\u7ae0 \u5e1d\u56fd\u4e4b\u79d8"}, {"id": 37161, "book_url": "\u9b54\u5e7b\u5f02\u95fb\u5f55/37161", "title": "\u7b2c\u4e00\u767e\u516d\u5341\u516b\u7ae0 \u738b\u5bab\u821e\u4f1a"}, {"id": 37165, "book_url": "\u9b54\u5e7b\u5f02\u95fb\u5f55/37165", "title": "\u7b2c\u4e00\u767e\u4e03\u5341\u4e8c\u7ae0 \u6700\u7ec8\u5175\u5668"}, {"id": 37162, "book_url": "\u9b54\u5e7b\u5f02\u95fb\u5f55/37162", "title": "\u7b2c\u4e00\u767e\u516d\u5341\u4e5d\u7ae0 \u6765\u8005\u4e0d\u5584"}, {"id": 37166, "book_url": "\u9b54\u5e7b\u5f02\u95fb\u5f55/37166", "title": "\u7b2c\u4e00\u767e\u4e03\u5341\u4e09\u7ae0 \u5f15\u706b\u70e7\u8eab"}, {"id": 37163, "book_url": "\u9b54\u5e7b\u5f02\u95fb\u5f55/37163", "title": "\u7b2c\u4e00\u767e\u4e03\u5341\u7ae0 \u77ed\u6682\u7684\u51b3\u6597"}, {"id": 37167, "book_url": "\u9b54\u5e7b\u5f02\u95fb\u5f55/37167", "title": "\u7b2c\u4e00\u767e\u4e03\u5341\u56db\u7ae0 \u53ea\u662f\u5f00\u59cb"}, {"id": 37168, "book_url": "\u9b54\u5e7b\u5f02\u95fb\u5f55/37168", "title": "\u7b2c\u4e00\u767e\u4e03\u5341\u4e94\u7ae0 \u4fdd\u6301\u6c89\u9ed8"}, {"id": 37172, "book_url": "\u9b54\u5e7b\u5f02\u95fb\u5f55/37172", "title": "\u7b2c\u4e00\u767e\u4e03\u5341\u4e5d\u7ae0 \u51b3\u6597\u5f00\u59cb"}, {"id": 37169, "book_url": "\u9b54\u5e7b\u5f02\u95fb\u5f55/37169", "title": "\u7b2c\u4e00\u767e\u4e03\u5341\u516d\u7ae0 \u517b\u7cbe\u84c4\u9510"}, {"id": 37173, "book_url": "\u9b54\u5e7b\u5f02\u95fb\u5f55/37173", "title": "\u7b2c\u4e00\u767e\u516b\u5341\u7ae0 \u9b54\u6cd5\u5e08\u7684\u51b3\u6597"}, {"id": 37170, "book_url": "\u9b54\u5e7b\u5f02\u95fb\u5f55/37170", "title": "\u7b2c\u4e00\u767e\u4e03\u5341\u4e03\u7ae0 \u5e1d\u56fd\u9b54\u6cd5\u9a91\u58eb\u56e2"}, {"id": 37174, "book_url": "\u9b54\u5e7b\u5f02\u95fb\u5f55/37174", "title": "\u7b2c\u4e00\u767e\u516b\u5341\u4e00\u7ae0 \u4e09\u722a\u75d5"}, {"id": 37171, "book_url": "\u9b54\u5e7b\u5f02\u95fb\u5f55/37171", "title": "\u7b2c\u4e00\u767e\u4e03\u5341\u516b\u7ae0 \u4e00\u6b21\u201c\u516c\u5e73\u201d\u7684\u51b3\u6597"}, {"id": 37175, "book_url": "\u9b54\u5e7b\u5f02\u95fb\u5f55/37175", "title": "\u7b2c\u4e00\u767e\u516b\u5341\u4e8c\u7ae0 \u664b\u7ea7"}, {"id": 37176, "book_url": "\u9b54\u5e7b\u5f02\u95fb\u5f55/37176", "title": "\u7b2c\u4e00\u767e\u516b\u5341\u4e09\u7ae0 \u795e\u79d8\u7684\u70bc\u91d1\u672f\u58eb"}, {"id": 37180, "book_url": "\u9b54\u5e7b\u5f02\u95fb\u5f55/37180", "title": "\u7b2c\u4e00\u767e\u516b\u5341\u4e03\u7ae0 \u5f97\u529b\u52a9\u624b"}, {"id": 37177, "book_url": "\u9b54\u5e7b\u5f02\u95fb\u5f55/37177", "title": "\u7b2c\u4e00\u767e\u516b\u5341\u56db\u7ae0 \u6f5c\u4f0f\u4e8e\u6c34\u9762\u4e4b\u4e0b"}, {"id": 37181, "book_url": "\u9b54\u5e7b\u5f02\u95fb\u5f55/37181", "title": "\u7b2c\u4e00\u767e\u516b\u5341\u516b\u7ae0 \u53c8\u4e00\u4efd\u5947\u602a\u7684\u7533\u8bf7"}, {"id": 37178, "book_url": "\u9b54\u5e7b\u5f02\u95fb\u5f55/37178", "title": "\u7b2c\u4e00\u767e\u516b\u5341\u4e94\u7ae0 \u968f\u4ece"}, {"id": 37182, "book_url": "\u9b54\u5e7b\u5f02\u95fb\u5f55/37182", "title": "\u7b2c\u4e00\u767e\u516b\u5341\u4e5d\u7ae0 \u9690\u85cf\u4e4b\u4eba"}, {"id": 37179, "book_url": "\u9b54\u5e7b\u5f02\u95fb\u5f55/37179", "title": "\u7b2c\u4e00\u767e\u516b\u5341\u516d\u7ae0 \u9732\u5e0c\u96c5"}, {"id": 37183, "book_url": "\u9b54\u5e7b\u5f02\u95fb\u5f55/37183", "title": "\u7b2c\u4e00\u767e\u4e5d\u5341\u7ae0 \u56de\u5bb6"}, {"id": 37184, "book_url": "\u9b54\u5e7b\u5f02\u95fb\u5f55/37184", "title": "\u7b2c\u4e00\u767e\u4e5d\u5341\u4e00\u7ae0 \u57cb\u4f0f"}, {"id": 37188, "book_url": "\u9b54\u5e7b\u5f02\u95fb\u5f55/37188", "title": "\u7b2c\u4e00\u767e\u4e5d\u5341\u4e94\u7ae0 \u91cd\u56de\u963f\u7956\u65af"}, {"id": 37185, "book_url": "\u9b54\u5e7b\u5f02\u95fb\u5f55/37185", "title": "\u7b2c\u4e00\u767e\u4e5d\u5341\u4e8c\u7ae0 \u4e8b\u540e\u5904\u7406"}, {"id": 37189, "book_url": "\u9b54\u5e7b\u5f02\u95fb\u5f55/37189", "title": "\u7b2c\u4e00\u767e\u4e5d\u5341\u516d\u7ae0 \u8c08\u5224\u7ed3\u675f"}, {"id": 37186, "book_url": "\u9b54\u5e7b\u5f02\u95fb\u5f55/37186", "title": "\u7b2c\u4e00\u767e\u4e5d\u5341\u4e09\u7ae0 \u6708\u5149\u57ce"}, {"id": 37190, "book_url": "\u9b54\u5e7b\u5f02\u95fb\u5f55/37190", "title": "\u7b2c\u4e00\u767e\u4e5d\u5341\u4e03\u7ae0 \u4e8b\u6001\u4e25\u91cd"}, {"id": 37187, "book_url": "\u9b54\u5e7b\u5f02\u95fb\u5f55/37187", "title": "\u7b2c\u4e00\u767e\u4e5d\u5341\u56db\u7ae0 \u9884\u8c0b"}, {"id": 37191, "book_url": "\u9b54\u5e7b\u5f02\u95fb\u5f55/37191", "title": "\u7b2c\u4e00\u767e\u4e5d\u5341\u516b\u7ae0 \u8ff7\u60d1\u7684\u8ba1\u5212"}, {"id": 37192, "book_url": "\u9b54\u5e7b\u5f02\u95fb\u5f55/37192", "title": "\u7b2c\u4e00\u767e\u4e5d\u5341\u4e5d\u7ae0 \u7cbe\u7075\u9057\u8ff9"}, {"id": 37196, "book_url": "\u9b54\u5e7b\u5f02\u95fb\u5f55/37196", "title": "\u7b2c\u4e8c\u767e\u96f6\u4e09\u7ae0 \u6094\u7ea6"}, {"id": 37193, "book_url": "\u9b54\u5e7b\u5f02\u95fb\u5f55/37193", "title": "\u7b2c\u4e8c\u767e\u7ae0 \u7cbe\u7075\u4ea1\u8005"}, {"id": 37197, "book_url": "\u9b54\u5e7b\u5f02\u95fb\u5f55/37197", "title": "\u7b2c\u4e8c\u767e\u96f6\u56db\u7ae0 \u65e0\u4eba\u533a"}, {"id": 37194, "book_url": "\u9b54\u5e7b\u5f02\u95fb\u5f55/37194", "title": "\u7b2c\u4e8c\u767e\u96f6\u4e00\u7ae0 \u7b2c\u4e8c\u5341\u4e00\u4efb\u5927\u9886\u4e3b"}, {"id": 37198, "book_url": "\u9b54\u5e7b\u5f02\u95fb\u5f55/37198", "title": "\u7b2c\u4e8c\u767e\u96f6\u4e94\u7ae0 \u64a4\u79bb"}, {"id": 37195, "book_url": "\u9b54\u5e7b\u5f02\u95fb\u5f55/37195", "title": "\u7b2c\u4e8c\u767e\u96f6\u4e8c\u7ae0 \u6536\u83b7"}, {"id": 37199, "book_url": "\u9b54\u5e7b\u5f02\u95fb\u5f55/37199", "title": "\u7b2c\u4e8c\u767e\u96f6\u516d\u7ae0 \u8fb9\u5883\u653f\u6cbb"}, {"id": 37200, "book_url": "\u9b54\u5e7b\u5f02\u95fb\u5f55/37200", "title": "\u7b2c\u4e8c\u767e\u96f6\u4e03\u7ae0 \u8054\u5408\u6f14\u594f"}, {"id": 37204, "book_url": "\u9b54\u5e7b\u5f02\u95fb\u5f55/37204", "title": "\u7b2c\u4e8c\u767e\u4e00\u5341\u4e00\u7ae0 \u9690\u85cf\u7684\u5371\u5bb3"}, {"id": 37201, "book_url": "\u9b54\u5e7b\u5f02\u95fb\u5f55/37201", "title": "\u7b2c\u4e8c\u767e\u96f6\u516b\u7ae0 \u611f\u8c22\u7684\u5fc3\u60c5"}, {"id": 37205, "book_url": "\u9b54\u5e7b\u5f02\u95fb\u5f55/37205", "title": "\u7b2c\u4e8c\u767e\u4e00\u5341\u4e8c\u7ae0 \u5371\u9669\u7684\u6839\u6e90"}, {"id": 37202, "book_url": "\u9b54\u5e7b\u5f02\u95fb\u5f55/37202", "title": "\u7b2c\u4e8c\u767e\u96f6\u4e5d\u7ae0 \u5230\u6765\u4e4b\u4eba"}, {"id": 37206, "book_url": "\u9b54\u5e7b\u5f02\u95fb\u5f55/37206", "title": "\u7b2c\u4e8c\u767e\u4e00\u5341\u4e09\u7ae0 \u6700\u5927\u7684\u65b0\u95fb"}, {"id": 37203, "book_url": "\u9b54\u5e7b\u5f02\u95fb\u5f55/37203", "title": "\u7b2c\u4e8c\u767e\u4e00\u5341\u7ae0 \u7ec3\u4e60\u6bd4\u8d5b"}, {"id": 37207, "book_url": "\u9b54\u5e7b\u5f02\u95fb\u5f55/37207", "title": "\u7b2c\u4e8c\u767e\u4e00\u5341\u56db\u7ae0 \u6b8b\u5fcd\u7684\u56de\u5fc6"}, {"id": 37208, "book_url": "\u9b54\u5e7b\u5f02\u95fb\u5f55/37208", "title": "\u7b2c\u4e8c\u767e\u4e00\u5341\u4e94\u7ae0 \u7acb\u573a"}, {"id": 37212, "book_url": "\u9b54\u5e7b\u5f02\u95fb\u5f55/37212", "title": "\u7b2c\u4e8c\u767e\u4e00\u5341\u4e5d\u7ae0 \u59d0\u59b9"}, {"id": 37209, "book_url": "\u9b54\u5e7b\u5f02\u95fb\u5f55/37209", "title": "\u7b2c\u4e8c\u767e\u4e00\u5341\u516d\u7ae0 \u4f63\u5175\u8ba1\u5212"}, {"id": 37213, "book_url": "\u9b54\u5e7b\u5f02\u95fb\u5f55/37213", "title": "\u7b2c\u4e8c\u767e\u4e8c\u5341\u7ae0 \u6b63\u4e49\u7684\u4f19\u4f34"}, {"id": 37210, "book_url": "\u9b54\u5e7b\u5f02\u95fb\u5f55/37210", "title": "\u7b2c\u4e8c\u767e\u4e00\u5341\u4e03\u7ae0 \u5e7b\u5f71\u4e4b\u5149"}, {"id": 37214, "book_url": "\u9b54\u5e7b\u5f02\u95fb\u5f55/37214", "title": "\u7b2c\u4e8c\u767e\u4e8c\u5341\u4e00\u7ae0 \u5728\u8def\u4e0a"}, {"id": 37211, "book_url": "\u9b54\u5e7b\u5f02\u95fb\u5f55/37211", "title": "\u7b2c\u4e8c\u767e\u4e00\u5341\u516b\u7ae0 \u518d\u9047\u6545\u4eba"}, {"id": 37215, "book_url": "\u9b54\u5e7b\u5f02\u95fb\u5f55/37215", "title": "\u7b2c\u4e8c\u767e\u4e8c\u5341\u4e8c\u7ae0 \u5c01\u9501\u4ee4"}, {"id": 37216, "book_url": "\u9b54\u5e7b\u5f02\u95fb\u5f55/37216", "title": "\u7b2c\u4e8c\u767e\u4e8c\u5341\u4e09\u7ae0 \u6bd4\u8bd5"}, {"id": 37220, "book_url": "\u9b54\u5e7b\u5f02\u95fb\u5f55/37220", "title": "\u7b2c\u4e8c\u767e\u4e8c\u5341\u4e03\u7ae0 \u5206\u6b67"}, {"id": 37217, "book_url": "\u9b54\u5e7b\u5f02\u95fb\u5f55/37217", "title": "\u7b2c\u4e8c\u767e\u4e8c\u5341\u56db\u7ae0 \u7edd\u5bc6\u5185\u5bb9"}, {"id": 37221, "book_url": "\u9b54\u5e7b\u5f02\u95fb\u5f55/37221", "title": "\u7b2c\u4e8c\u767e\u4e8c\u5341\u516b\u7ae0 \u795e\u79d8\u7684\u7a7a\u95f4"}, {"id": 37218, "book_url": "\u9b54\u5e7b\u5f02\u95fb\u5f55/37218", "title": "\u7b2c\u4e8c\u767e\u4e8c\u5341\u4e94\u7ae0 \u7ea0\u7eb7\u4e0d\u65ad"}, {"id": 37222, "book_url": "\u9b54\u5e7b\u5f02\u95fb\u5f55/37222", "title": "\u7b2c\u4e8c\u767e\u4e8c\u5341\u4e5d\u7ae0 \u751f\u547d\u4e4b\u82b1"}, {"id": 37219, "book_url": "\u9b54\u5e7b\u5f02\u95fb\u5f55/37219", "title": "\u7b2c\u4e8c\u767e\u4e8c\u5341\u516d\u7ae0 \u5bfb\u8e2a"}, {"id": 37223, "book_url": "\u9b54\u5e7b\u5f02\u95fb\u5f55/37223", "title": "\u7b2c\u4e8c\u767e\u4e09\u5341\u7ae0 \u9a71\u9010"}, {"id": 37224, "book_url": "\u9b54\u5e7b\u5f02\u95fb\u5f55/37224", "title": "\u7b2c\u4e8c\u767e\u4e09\u5341\u4e00\u7ae0 \u785d\u70df\u5f25\u6f2b"}, {"id": 37228, "book_url": "\u9b54\u5e7b\u5f02\u95fb\u5f55/37228", "title": "\u7b2c\u4e8c\u767e\u4e09\u5341\u4e94\u7ae0 \u5de7\u9047"}, {"id": 37225, "book_url": "\u9b54\u5e7b\u5f02\u95fb\u5f55/37225", "title": "\u7b2c\u4e8c\u767e\u4e09\u5341\u4e8c\u7ae0 \u4fe1\u606f\u4e0d\u660e"}, {"id": 37229, "book_url": "\u9b54\u5e7b\u5f02\u95fb\u5f55/37229", "title": "\u7b2c\u4e8c\u767e\u4e09\u5341\u516d\u7ae0 \u518d\u89c1\u5e93\u83f2\u65af"}, {"id": 37226, "book_url": "\u9b54\u5e7b\u5f02\u95fb\u5f55/37226", "title": "\u7b2c\u4e8c\u767e\u4e09\u5341\u4e09\u7ae0 \u62b5\u8fbe\u90fd\u57ce"}, {"id": 37230, "book_url": "\u9b54\u5e7b\u5f02\u95fb\u5f55/37230", "title": "\u7b2c\u4e8c\u767e\u4e09\u5341\u4e03\u7ae0 \u4e3b\u52a8\u51fa\u51fb"}, {"id": 37227, "book_url": "\u9b54\u5e7b\u5f02\u95fb\u5f55/37227", "title": "\u7b2c\u4e8c\u767e\u4e09\u5341\u56db\u7ae0 \u5965\u5c14\u5179"}, {"id": 37231, "book_url": "\u9b54\u5e7b\u5f02\u95fb\u5f55/37231", "title": "\u7b2c\u4e8c\u767e\u4e09\u5341\u516b\u7ae0 \u5371\u9669\u7684\u591c\u665a"}, {"id": 37232, "book_url": "\u9b54\u5e7b\u5f02\u95fb\u5f55/37232", "title": "\u7b2c\u4e8c\u767e\u4e09\u5341\u4e5d\u7ae0 \u6b8b\u5b58\u7684\u86c7"}, {"id": 37236, "book_url": "\u9b54\u5e7b\u5f02\u95fb\u5f55/37236", "title": "\u7b2c\u4e8c\u767e\u56db\u5341\u4e09\u7ae0 \u9634\u8c0b\u8bba"}, {"id": 37233, "book_url": "\u9b54\u5e7b\u5f02\u95fb\u5f55/37233", "title": "\u7b2c\u4e8c\u767e\u56db\u5341\u7ae0 \u7cbe\u7075\u8d22\u5b9d"}, {"id": 37237, "book_url": "\u9b54\u5e7b\u5f02\u95fb\u5f55/37237", "title": "\u7b2c\u4e8c\u767e\u56db\u5341\u56db\u7ae0 \u795e\u5723\u7684\u9a91\u58eb"}, {"id": 37234, "book_url": "\u9b54\u5e7b\u5f02\u95fb\u5f55/37234", "title": "\u7b2c\u4e8c\u767e\u56db\u5341\u4e00\u7ae0 \u98ce\u96e8\u6b32\u6765"}, {"id": 37238, "book_url": "\u9b54\u5e7b\u5f02\u95fb\u5f55/37238", "title": "\u7b2c\u4e8c\u767e\u56db\u5341\u4e94\u7ae0 \u53d1\u82bd"}, {"id": 37235, "book_url": "\u9b54\u5e7b\u5f02\u95fb\u5f55/37235", "title": "\u7b2c\u4e8c\u767e\u56db\u5341\u4e8c\u7ae0 \u95f9\u5267"}, {"id": 37239, "book_url": "\u9b54\u5e7b\u5f02\u95fb\u5f55/37239", "title": "\u7b2c\u4e8c\u767e\u56db\u5341\u516d\u7ae0 \u5371\u673a"}, {"id": 37240, "book_url": "\u9b54\u5e7b\u5f02\u95fb\u5f55/37240", "title": "\u7b2c\u4e8c\u767e\u56db\u5341\u4e03\u7ae0 \u738b\u4e0e\u540e"}, {"id": 37244, "book_url": "\u9b54\u5e7b\u5f02\u95fb\u5f55/37244", "title": "\u7b2c\u4e8c\u767e\u4e94\u5341\u4e00\u7ae0 \u9b54\u6cd5\u5e08\u4e4b\u6218"}, {"id": 37241, "book_url": "\u9b54\u5e7b\u5f02\u95fb\u5f55/37241", "title": "\u7b2c\u4e8c\u767e\u56db\u5341\u516b\u7ae0 \u7edd\u5bf9\u4e4b\u58f0"}, {"id": 37245, "book_url": "\u9b54\u5e7b\u5f02\u95fb\u5f55/37245", "title": "\u7b2c\u4e8c\u767e\u4e94\u5341\u4e8c\u7ae0 \u65e0\u6cd5\u89e3\u7b54"}, {"id": 37242, "book_url": "\u9b54\u5e7b\u5f02\u95fb\u5f55/37242", "title": "\u7b2c\u4e8c\u767e\u56db\u5341\u4e5d\u7ae0 \u771f\u7684\u5047\u8c61"}, {"id": 37246, "book_url": "\u9b54\u5e7b\u5f02\u95fb\u5f55/37246", "title": "\u7b2c\u4e8c\u767e\u4e94\u5341\u4e09\u7ae0 \u8fdf\u5230\u7684\u5ba1\u5224"}, {"id": 37243, "book_url": "\u9b54\u5e7b\u5f02\u95fb\u5f55/37243", "title": "\u7b2c\u4e8c\u767e\u4e94\u5341\u7ae0 \u4ea1\u7075\u7684\u590d\u4ec7"}, {"id": 37247, "book_url": "\u9b54\u5e7b\u5f02\u95fb\u5f55/37247", "title": "\u7b2c\u4e8c\u767e\u4e94\u5341\u56db\u7ae0 \u4e0d\u8be6\u7684\u9884\u8a00"}, {"id": 37248, "book_url": "\u9b54\u5e7b\u5f02\u95fb\u5f55/37248", "title": "\u7b2c\u4e8c\u767e\u4e94\u5341\u4e94\u7ae0 \u5f52\u9014\u65c5\u7a0b"}, {"id": 37252, "book_url": "\u9b54\u5e7b\u5f02\u95fb\u5f55/37252", "title": "\u7b2c\u4e8c\u767e\u516d\u5341\u7ae0 \u5e7d\u6697\u7684\u5fc3"}, {"id": 37249, "book_url": "\u9b54\u5e7b\u5f02\u95fb\u5f55/37249", "title": "\u7b2c\u4e8c\u767e\u4e94\u5341\u516d\u7ae0 \u5947\u602a\u7684\u5f71\u5b50"}, {"id": 37253, "book_url": "\u9b54\u5e7b\u5f02\u95fb\u5f55/37253", "title": "\u7b2c\u4e8c\u767e\u516d\u5341\u4e00\u7ae0 \u540c\u4f34\u7684\u610f\u4e49"}, {"id": 37250, "book_url": "\u9b54\u5e7b\u5f02\u95fb\u5f55/37250", "title": "\u7b2c\u4e8c\u767e\u4e94\u5341\u516b\u7ae0 \u6ca1\u6709\u9009\u62e9"}, {"id": 37254, "book_url": "\u9b54\u5e7b\u5f02\u95fb\u5f55/37254", "title": "\u7b2c\u4e8c\u767e\u516d\u5341\u4e8c\u7ae0 \u5404\u6709\u6240\u601d"}, {"id": 37251, "book_url": "\u9b54\u5e7b\u5f02\u95fb\u5f55/37251", "title": "\u7b2c\u4e8c\u767e\u4e94\u5341\u4e5d\u7ae0 \u65e0\u4ece\u4e0b\u624b"}, {"id": 37255, "book_url": "\u9b54\u5e7b\u5f02\u95fb\u5f55/37255", "title": "\u7b2c\u4e8c\u767e\u516d\u5341\u4e09\u7ae0 \u8be5\u6b7b\u7684\u4f20\u7edf"}, {"id": 37256, "book_url": "\u9b54\u5e7b\u5f02\u95fb\u5f55/37256", "title": "\u7b2c\u4e8c\u767e\u516d\u5341\u56db\u7ae0 \u8fdc\u65b9\u7684\u6765\u5ba2"}, {"id": 37260, "book_url": "\u9b54\u5e7b\u5f02\u95fb\u5f55/37260", "title": "\u7b2c\u4e8c\u767e\u4e94\u5341\u4e03\u7ae0 \u9634\u6697\u4e4b\u5f71"}, {"id": 37257, "book_url": "\u9b54\u5e7b\u5f02\u95fb\u5f55/37257", "title": "\u7b2c\u4e8c\u767e\u516d\u5341\u4e94\u7ae0 \u5357\u65b9\u9886\u4e3b"}, {"id": 37261, "book_url": "\u9b54\u5e7b\u5f02\u95fb\u5f55/37261", "title": "\u7b2c\u4e8c\u767e\u516d\u5341\u516b\u7ae0 \u6bd2\u86fe"}, {"id": 37258, "book_url": "\u9b54\u5e7b\u5f02\u95fb\u5f55/37258", "title": "\u7b2c\u4e8c\u767e\u516d\u5341\u516d\u7ae0 \u7531\u4e0b\u800c\u4e0a\u7684\u5371\u673a"}, {"id": 37262, "book_url": "\u9b54\u5e7b\u5f02\u95fb\u5f55/37262", "title": "\u7b2c\u4e8c\u767e\u516d\u5341\u4e5d\u7ae0 \u62f7\u95ee"}, {"id": 37259, "book_url": "\u9b54\u5e7b\u5f02\u95fb\u5f55/37259", "title": "\u7b2c\u4e8c\u767e\u516d\u5341\u4e03\u7ae0 \u6bd2\u7269\u4e4b\u6e90"}, {"id": 37263, "book_url": "\u9b54\u5e7b\u5f02\u95fb\u5f55/37263", "title": "\u7b2c\u4e8c\u767e\u4e03\u5341\u7ae0 \u6076\u9b54\u4e4b\u7259"}, {"id": 37264, "book_url": "\u9b54\u5e7b\u5f02\u95fb\u5f55/37264", "title": "\u7b2c\u4e8c\u767e\u4e03\u5341\u4e00\u7ae0 \u840c\u82bd\u72b6\u6001"}, {"id": 37268, "book_url": "\u9b54\u5e7b\u5f02\u95fb\u5f55/37268", "title": "\u7b2c\u4e8c\u767e\u4e03\u5341\u4e94\u7ae0 \u60f9\u706b"}, {"id": 37265, "book_url": "\u9b54\u5e7b\u5f02\u95fb\u5f55/37265", "title": "\u7b2c\u4e8c\u767e\u4e03\u5341\u4e8c\u7ae0 \u4e00\u4e2a\u65c5\u4f34"}, {"id": 37269, "book_url": "\u9b54\u5e7b\u5f02\u95fb\u5f55/37269", "title": "\u7b2c\u4e8c\u767e\u4e03\u5341\u516d\u7ae0 \u7fe0\u9e1f\u65c5\u5e97"}, {"id": 37266, "book_url": "\u9b54\u5e7b\u5f02\u95fb\u5f55/37266", "title": "\u7b2c\u4e8c\u767e\u4e03\u5341\u4e09\u7ae0 \u7acb\u573a\u4e0d\u540c"}, {"id": 37270, "book_url": "\u9b54\u5e7b\u5f02\u95fb\u5f55/37270", "title": "\u7b2c\u4e8c\u767e\u4e03\u5341\u4e03\u7ae0 \u795e\u79d8\u7684\u5931\u8e2a"}, {"id": 37267, "book_url": "\u9b54\u5e7b\u5f02\u95fb\u5f55/37267", "title": "\u7b2c\u4e8c\u767e\u4e03\u5341\u56db\u7ae0 \u4e00\u573a\u610f\u5916"}, {"id": 37271, "book_url": "\u9b54\u5e7b\u5f02\u95fb\u5f55/37271", "title": "\u7b2c\u4e8c\u767e\u4e03\u5341\u516b\u7ae0 \u9b54\u5e7b\u82b1\u7684\u4f20\u8bf4"}, {"id": 37272, "book_url": "\u9b54\u5e7b\u5f02\u95fb\u5f55/37272", "title": "\u7b2c\u4e8c\u767e\u4e03\u5341\u4e5d\u7ae0 \u66fe\u7ecf\u7684\u9519\u8bef"}, {"id": 37276, "book_url": "\u9b54\u5e7b\u5f02\u95fb\u5f55/37276", "title": "\u7b2c\u4e8c\u767e\u516b\u5341\u4e09\u7ae0 \u6df1\u5165\u5176\u4e2d"}, {"id": 37273, "book_url": "\u9b54\u5e7b\u5f02\u95fb\u5f55/37273", "title": "\u7b2c\u4e8c\u767e\u516b\u5341\u7ae0 \u5931\u53bb\u7684\u4eba"}, {"id": 37277, "book_url": "\u9b54\u5e7b\u5f02\u95fb\u5f55/37277", "title": "\u7b2c\u4e8c\u767e\u516b\u5341\u56db\u7ae0 \u9677\u843d"}, {"id": 37274, "book_url": "\u9b54\u5e7b\u5f02\u95fb\u5f55/37274", "title": "\u7b2c\u4e8c\u767e\u516b\u5341\u4e00\u7ae0 \u6708\u5149\u4e4b\u4e0b"}, {"id": 37278, "book_url": "\u9b54\u5e7b\u5f02\u95fb\u5f55/37278", "title": "\u7b2c\u4e8c\u767e\u516b\u5341\u4e94\u7ae0 \u8c01\u8d62\u8c01\u8f93\uff1f"}, {"id": 37275, "book_url": "\u9b54\u5e7b\u5f02\u95fb\u5f55/37275", "title": "\u7b2c\u4e8c\u767e\u516b\u5341\u4e8c\u7ae0 \u672b\u65e5\u5c71\u8109"}, {"id": 37279, "book_url": "\u9b54\u5e7b\u5f02\u95fb\u5f55/37279", "title": "\u7b2c\u4e8c\u767e\u516b\u5341\u516d\u7ae0 \u65e0"}, {"id": 37280, "book_url": "\u9b54\u5e7b\u5f02\u95fb\u5f55/37280", "title": "\u7b2c\u4e8c\u767e\u516b\u5341\u4e03\u7ae0 \u5168\u7a0b\u62a4\u9001"}, {"id": 37284, "book_url": "\u9b54\u5e7b\u5f02\u95fb\u5f55/37284", "title": "\u7b2c\u4e8c\u767e\u4e5d\u5341\u4e00\u7ae0 \u6c34\u5f88\u6df1"}, {"id": 37281, "book_url": "\u9b54\u5e7b\u5f02\u95fb\u5f55/37281", "title": "\u7b2c\u4e8c\u767e\u516b\u5341\u516b\u7ae0 \u6f5c\u4f0f\u7684\u86c7"}, {"id": 37285, "book_url": "\u9b54\u5e7b\u5f02\u95fb\u5f55/37285", "title": "\u7b2c\u4e8c\u767e\u4e5d\u5341\u4e8c\u7ae0 \u83f2\u5c14\u5fb7\u5c3c\u7684\u884c\u52a8"}, {"id": 37282, "book_url": "\u9b54\u5e7b\u5f02\u95fb\u5f55/37282", "title": "\u7b2c\u4e8c\u767e\u516b\u5341\u4e5d\u7ae0 \u5201\u96be"}, {"id": 37286, "book_url": "\u9b54\u5e7b\u5f02\u95fb\u5f55/37286", "title": "\u7b2c\u4e8c\u767e\u4e5d\u5341\u4e09\u7ae0 \u5251\u4e0e\u4eba"}, {"id": 37283, "book_url": "\u9b54\u5e7b\u5f02\u95fb\u5f55/37283", "title": "\u7b2c\u4e8c\u767e\u4e5d\u5341\u7ae0 \u4e00\u4e2a\u7537\u4eba"}, {"id": 37287, "book_url": "\u9b54\u5e7b\u5f02\u95fb\u5f55/37287", "title": "\u7b2c\u4e8c\u767e\u4e5d\u5341\u56db\u7ae0 \u5f3a\u529b\u6e05\u626b"}, {"id": 37288, "book_url": "\u9b54\u5e7b\u5f02\u95fb\u5f55/37288", "title": "\u7b2c\u4e8c\u767e\u4e5d\u5341\u4e94\u7ae0 \u83f2\u5c14\u5fb7\u5c3c\u4e4b\u65c5"}, {"id": 37292, "book_url": "\u9b54\u5e7b\u5f02\u95fb\u5f55/37292", "title": "\u7b2c\u4e8c\u767e\u4e5d\u5341\u4e5d\u7ae0 \u6b63\u4e49\u7684\u5ba1\u5224"}, {"id": 37289, "book_url": "\u9b54\u5e7b\u5f02\u95fb\u5f55/37289", "title": "\u7b2c\u4e8c\u767e\u4e5d\u5341\u516d\u7ae0 \u771f\u7684\u597d\u5de7"}, {"id": 37293, "book_url": "\u9b54\u5e7b\u5f02\u95fb\u5f55/37293", "title": "\u7b2c\u4e09\u767e\u7ae0 \u96ea\u4e2d\u591c\u8272"}, {"id": 37290, "book_url": "\u9b54\u5e7b\u5f02\u95fb\u5f55/37290", "title": "\u7b2c\u4e8c\u767e\u4e5d\u5341\u4e03\u7ae0 \u6697\u8c0b\u5bc6\u5212"}, {"id": 37294, "book_url": "\u9b54\u5e7b\u5f02\u95fb\u5f55/37294", "title": "\u7b2c\u4e09\u767e\u96f6\u4e00\u7ae0 \u51b0\u4e0e\u5fc3"}, {"id": 37291, "book_url": "\u9b54\u5e7b\u5f02\u95fb\u5f55/37291", "title": "\u7b2c\u4e8c\u767e\u4e5d\u5341\u516b\u7ae0 \u64e6\u80a9\u800c\u8fc7"}, {"id": 37295, "book_url": "\u9b54\u5e7b\u5f02\u95fb\u5f55/37295", "title": "\u7b2c\u4e09\u767e\u96f6\u4e8c\u7ae0 \u53ec\u5524"}, {"id": 37296, "book_url": "\u9b54\u5e7b\u5f02\u95fb\u5f55/37296", "title": "\u7b2c\u4e09\u767e\u96f6\u4e09\u7ae0 \u91cd\u9022"}, {"id": 37300, "book_url": "\u9b54\u5e7b\u5f02\u95fb\u5f55/37300", "title": "\u7b2c\u4e09\u767e\u96f6\u4e03\u7ae0 \u6050\u6016\u884c\u52a8\u8ba1\u5212\u7b2c\u4e09\u7ae0"}, {"id": 37297, "book_url": "\u9b54\u5e7b\u5f02\u95fb\u5f55/37297", "title": "\u7b2c\u4e09\u767e\u96f6\u56db\u7ae0 \u6050\u6016\u884c\u52a8\u8ba1\u5212\u5e8f\u7ae0"}, {"id": 37301, "book_url": "\u9b54\u5e7b\u5f02\u95fb\u5f55/37301", "title": "\u7b2c\u4e09\u767e\u96f6\u516b\u7ae0 \u6050\u6016\u884c\u52a8\u8ba1\u5212\u7b2c\u56db\u7ae0"}, {"id": 37298, "book_url": "\u9b54\u5e7b\u5f02\u95fb\u5f55/37298", "title": "\u7b2c\u4e09\u767e\u96f6\u4e94\u7ae0 \u6050\u6016\u884c\u52a8\u8ba1\u5212"}, {"id": 37302, "book_url": "\u9b54\u5e7b\u5f02\u95fb\u5f55/37302", "title": "\u7b2c\u4e09\u767e\u96f6\u4e5d\u7ae0 \u6697\u5fc3\u7591\u9b3c"}, {"id": 37299, "book_url": "\u9b54\u5e7b\u5f02\u95fb\u5f55/37299", "title": "\u7b2c\u4e09\u767e\u96f6\u516d\u7ae0 \u6050\u6016\u884c\u52a8\u8ba1\u5212\u7b2c\u4e8c\u7ae0"}, {"id": 37303, "book_url": "\u9b54\u5e7b\u5f02\u95fb\u5f55/37303", "title": "\u7b2c\u4e09\u767e\u4e00\u5341\u7ae0 \u9ed1\u6697\u7684\u4fe1\u4f7f"}, {"id": 37304, "book_url": "\u9b54\u5e7b\u5f02\u95fb\u5f55/37304", "title": "\u7b2c\u4e09\u767e\u4e00\u5341\u4e00\u7ae0 \u56db\u9762\u5f00\u82b1"}, {"id": 37308, "book_url": "\u9b54\u5e7b\u5f02\u95fb\u5f55/37308", "title": "\u7b2c\u4e09\u767e\u4e00\u5341\u4e94\u7ae0 \u8d70\u51fa\u53bb"}, {"id": 37305, "book_url": "\u9b54\u5e7b\u5f02\u95fb\u5f55/37305", "title": "\u7b2c\u4e09\u767e\u4e00\u5341\u4e8c\u7ae0 \u5931\u8bef"}, {"id": 37309, "book_url": "\u9b54\u5e7b\u5f02\u95fb\u5f55/37309", "title": "\u7b2c\u4e09\u767e\u4e00\u5341\u516d\u7ae0 \u64ad\u6492\u7684\u79cd\u5b50"}, {"id": 37306, "book_url": "\u9b54\u5e7b\u5f02\u95fb\u5f55/37306", "title": "\u7b2c\u4e09\u767e\u4e00\u5341\u4e09\u7ae0 \u96ea\u591c\u7684\u56de\u5fc6"}, {"id": 37310, "book_url": "\u9b54\u5e7b\u5f02\u95fb\u5f55/37310", "title": "\u7b2c\u4e09\u767e\u4e00\u5341\u4e03\u7ae0 \u5927\u6e05\u6d17"}, {"id": 37307, "book_url": "\u9b54\u5e7b\u5f02\u95fb\u5f55/37307", "title": "\u7b2c\u4e09\u767e\u4e00\u5341\u56db\u7ae0 \u5fc3\u4e4b\u58f0"}, {"id": 37311, "book_url": "\u9b54\u5e7b\u5f02\u95fb\u5f55/37311", "title": "\u7b2c\u4e09\u767e\u4e00\u5341\u516b\u7ae0 \u6697\u4f0f"}, {"id": 37312, "book_url": "\u9b54\u5e7b\u5f02\u95fb\u5f55/37312", "title": "\u7b2c\u4e09\u767e\u4e00\u5341\u4e5d\u7ae0 \u738b\u5ba4\u4e4b\u8c0b"}, {"id": 37316, "book_url": "\u9b54\u5e7b\u5f02\u95fb\u5f55/37316", "title": "\u7b2c\u4e09\u767e\u4e8c\u5341\u4e09\u7ae0 \u90aa\u6076\u9b54\u7075"}, {"id": 37313, "book_url": "\u9b54\u5e7b\u5f02\u95fb\u5f55/37313", "title": "\u7b2c\u4e09\u767e\u4e8c\u5341\u7ae0 \u4f63\u5175\u533a"}, {"id": 37317, "book_url": "\u9b54\u5e7b\u5f02\u95fb\u5f55/37317", "title": "\u7b2c\u4e09\u767e\u4e8c\u5341\u56db\u7ae0 \u80cc\u79bb\u7684\u80ce\u52a8"}, {"id": 37314, "book_url": "\u9b54\u5e7b\u5f02\u95fb\u5f55/37314", "title": "\u7b2c\u4e09\u767e\u4e8c\u5341\u4e00\u7ae0 \u63f4\u519b"}, {"id": 37318, "book_url": "\u9b54\u5e7b\u5f02\u95fb\u5f55/37318", "title": "\u7b2c\u4e09\u767e\u4e8c\u5341\u4e94\u7ae0 \u6218\u4e89\u4e4b\u738b"}, {"id": 37315, "book_url": "\u9b54\u5e7b\u5f02\u95fb\u5f55/37315", "title": "\u7b2c\u4e09\u767e\u4e8c\u5341\u4e8c\u7ae0 \u4e00\u9a91\u5f53\u5343"}, {"id": 37319, "book_url": "\u9b54\u5e7b\u5f02\u95fb\u5f55/37319", "title": "\u7b2c\u4e09\u767e\u4e8c\u5341\u516d\u7ae0 \u65b0\u7684\u4efb\u547d"}, {"id": 37320, "book_url": "\u9b54\u5e7b\u5f02\u95fb\u5f55/37320", "title": "\u7b2c\u4e09\u767e\u4e8c\u5341\u4e03\u7ae0 \u5411\u5357\u53bb"}, {"id": 37324, "book_url": "\u9b54\u5e7b\u5f02\u95fb\u5f55/37324", "title": "\u7b2c\u4e09\u767e\u4e09\u5341\u4e00\u7ae0 \u624b\u672f"}, {"id": 37321, "book_url": "\u9b54\u5e7b\u5f02\u95fb\u5f55/37321", "title": "\u7b2c\u4e09\u767e\u4e8c\u5341\u516b\u7ae0 \u4f60\u662f\u8c01\uff1f"}, {"id": 37325, "book_url": "\u9b54\u5e7b\u5f02\u95fb\u5f55/37325", "title": "\u7b2c\u4e09\u767e\u4e09\u5341\u4e00\u7ae0 \u624b\u672f"}, {"id": 37322, "book_url": "\u9b54\u5e7b\u5f02\u95fb\u5f55/37322", "title": "\u7b2c\u4e09\u767e\u4e8c\u5341\u4e5d\u7ae0 \u6ca1\u6709\u6b63\u4e49"}, {"id": 37326, "book_url": "\u9b54\u5e7b\u5f02\u95fb\u5f55/37326", "title": "\u7b2c\u4e09\u767e\u4e09\u5341\u4e8c\u7ae0 \u4e0d\u53d7\u6b22\u8fce\u7684\u6765\u5ba2"}, {"id": 37323, "book_url": "\u9b54\u5e7b\u5f02\u95fb\u5f55/37323", "title": "\u7b2c\u4e09\u767e\u4e09\u5341\u7ae0 \u4e00\u4e2a\u9009\u62e9"}, {"id": 37327, "book_url": "\u9b54\u5e7b\u5f02\u95fb\u5f55/37327", "title": "\u7b2c\u4e09\u767e\u4e09\u5341\u4e09\u7ae0 \u770b\u6e05\u5f62\u5f0f"}, {"id": 37328, "book_url": "\u9b54\u5e7b\u5f02\u95fb\u5f55/37328", "title": "\u7b2c\u4e09\u767e\u4e09\u5341\u56db\u7ae0 \u524d\u594f"}, {"id": 37332, "book_url": "\u9b54\u5e7b\u5f02\u95fb\u5f55/37332", "title": "\u7b2c\u4e09\u767e\u4e09\u5341\u516b\u7ae0 \u62b5\u8fbe\u9a6c\u53ef\u738b\u56fd"}, {"id": 37329, "book_url": "\u9b54\u5e7b\u5f02\u95fb\u5f55/37329", "title": "\u7b2c\u4e09\u767e\u4e09\u5341\u4e94\u7ae0 \u79bb\u5fc3\u4e4b\u8a00"}, {"id": 37333, "book_url": "\u9b54\u5e7b\u5f02\u95fb\u5f55/37333", "title": "\u7b2c\u4e09\u767e\u4e09\u5341\u4e5d\u7ae0 \u4f7f\u8282\u4eec"}, {"id": 37330, "book_url": "\u9b54\u5e7b\u5f02\u95fb\u5f55/37330", "title": "\u7b2c\u4e09\u767e\u4e09\u5341\u516d\u7ae0 \u8bf4\u5230\u505a\u5230"}, {"id": 37334, "book_url": "\u9b54\u5e7b\u5f02\u95fb\u5f55/37334", "title": "\u7b2c\u4e09\u767e\u56db\u5341\u7ae0 \u72ec\u7acb\u80dc\u5178"}, {"id": 37331, "book_url": "\u9b54\u5e7b\u5f02\u95fb\u5f55/37331", "title": "\u7b2c\u4e09\u767e\u4e09\u5341\u4e03\u7ae0 \u4f0a\u660e\u7684\u7591\u95ee"}, {"id": 37335, "book_url": "\u9b54\u5e7b\u5f02\u95fb\u5f55/37335", "title": "\u7b2c\u4e09\u767e\u56db\u5341\u4e00\u7ae0 \u8840\u796d"}, {"id": 37336, "book_url": "\u9b54\u5e7b\u5f02\u95fb\u5f55/37336", "title": "\u7b2c\u4e09\u767e\u56db\u5341\u4e8c\u7ae0 \u827e\u59ae\u7684\u51b3\u5b9a"}, {"id": 37340, "book_url": "\u9b54\u5e7b\u5f02\u95fb\u5f55/37340", "title": "\u7b2c\u4e09\u767e\u56db\u5341\u516d\u7ae0 \u5760\u843d\u4e4b\u540e"}, {"id": 37337, "book_url": "\u9b54\u5e7b\u5f02\u95fb\u5f55/37337", "title": "\u7b2c\u4e09\u767e\u56db\u5341\u4e09\u7ae0 \u90aa\u6076\u7684\u9080\u8bf7"}, {"id": 37341, "book_url": "\u9b54\u5e7b\u5f02\u95fb\u5f55/37341", "title": "\u7b2c\u4e09\u767e\u56db\u5341\u4e03\u7ae0 \u5bc2\u9759\u4e4b\u9547"}, {"id": 37338, "book_url": "\u9b54\u5e7b\u5f02\u95fb\u5f55/37338", "title": "\u7b2c\u4e09\u767e\u56db\u5341\u56db\u7ae0 \u4e00\u573a\u6076\u68a6"}, {"id": 37342, "book_url": "\u9b54\u5e7b\u5f02\u95fb\u5f55/37342", "title": "\u7b2c\u4e09\u767e\u56db\u5341\u516b\u7ae0 \u5f02\u5e38\u7684\u8054\u7cfb"}, {"id": 37339, "book_url": "\u9b54\u5e7b\u5f02\u95fb\u5f55/37339", "title": "\u7b2c\u4e09\u767e\u56db\u5341\u4e94\u7ae0 \u5730\u9762\u88ad\u51fb"}, {"id": 37343, "book_url": "\u9b54\u5e7b\u5f02\u95fb\u5f55/37343", "title": "\u7b2c\u4e09\u767e\u56db\u5341\u4e5d\u7ae0 \u56fa\u6267\u7684\u575a\u6301"}, {"id": 37344, "book_url": "\u9b54\u5e7b\u5f02\u95fb\u5f55/37344", "title": "\u7b2c\u4e09\u767e\u4e94\u5341\u7ae0 \u5e76\u4e0d\u5bb9\u6613"}, {"id": 37348, "book_url": "\u9b54\u5e7b\u5f02\u95fb\u5f55/37348", "title": "\u7b2c\u4e09\u767e\u4e94\u5341\u56db\u7ae0 \u7edd\u4e0d\u597d\u8fc7"}, {"id": 37345, "book_url": "\u9b54\u5e7b\u5f02\u95fb\u5f55/37345", "title": "\u7b2c\u4e09\u767e\u4e94\u5341\u4e00\u7ae0 \u5206\u6563\u884c\u52a8"}, {"id": 37349, "book_url": "\u9b54\u5e7b\u5f02\u95fb\u5f55/37349", "title": "\u7b2c\u4e09\u767e\u4e94\u5341\u4e94\u7ae0 \u544a\u767d\uff1f"}, {"id": 37346, "book_url": "\u9b54\u5e7b\u5f02\u95fb\u5f55/37346", "title": "\u7b2c\u4e09\u767e\u4e94\u5341\u4e8c\u7ae0 \u5371\u673a\u524d\u5915"}, {"id": 37350, "book_url": "\u9b54\u5e7b\u5f02\u95fb\u5f55/37350", "title": "\u7b2c\u4e09\u767e\u4e94\u5341\u516d\u7ae0 \u89c1\u9762\u4e86"}, {"id": 37347, "book_url": "\u9b54\u5e7b\u5f02\u95fb\u5f55/37347", "title": "\u7b2c\u4e09\u767e\u4e94\u5341\u4e09\u7ae0 \u7f6a\u5b7d\u6b66\u88c5\u7684\u771f\u5b9e\u5f62\u6001"}, {"id": 37351, "book_url": "\u9b54\u5e7b\u5f02\u95fb\u5f55/37351", "title": "\u7b2c\u4e09\u767e\u4e94\u5341\u4e03\u7ae0 \u65e0\u53ef\u5948\u4f55"}, {"id": 37352, "book_url": "\u9b54\u5e7b\u5f02\u95fb\u5f55/37352", "title": "\u7b2c\u4e09\u767e\u4e94\u5341\u516b\u7ae0 \u627e\u6b7b\u7684\u4eba"}, {"id": 37356, "book_url": "\u9b54\u5e7b\u5f02\u95fb\u5f55/37356", "title": "\u7b2c\u4e09\u767e\u516d\u5341\u4e8c\u7ae0 \u79d8\u5bc6\u4e0e\u771f\u76f8"}, {"id": 37353, "book_url": "\u9b54\u5e7b\u5f02\u95fb\u5f55/37353", "title": "\u7b2c\u4e09\u767e\u4e94\u5341\u4e5d\u7ae0 \u5706\u684c\u4f1a\u8bae"}, {"id": 37357, "book_url": "\u9b54\u5e7b\u5f02\u95fb\u5f55/37357", "title": "\u7b2c\u4e09\u767e\u516d\u5341\u4e09\u7ae0 \u8fb9\u5883\u53d8\u52a8"}, {"id": 37354, "book_url": "\u9b54\u5e7b\u5f02\u95fb\u5f55/37354", "title": "\u7b2c\u4e09\u767e\u516d\u5341\u7ae0 \u5c11\u5973\u7684\u79d8\u5bc6"}, {"id": 37358, "book_url": "\u9b54\u5e7b\u5f02\u95fb\u5f55/37358", "title": "\u7b2c\u4e09\u767e\u516d\u5341\u56db\u7ae0 \u5c40\u90e8\u6469\u64e6"}, {"id": 37355, "book_url": "\u9b54\u5e7b\u5f02\u95fb\u5f55/37355", "title": "\u7b2c\u4e09\u767e\u516d\u5341\u4e00\u7ae0 \u8ff7\u9898"}, {"id": 37359, "book_url": "\u9b54\u5e7b\u5f02\u95fb\u5f55/37359", "title": "\u7b2c\u4e09\u767e\u516d\u5341\u4e94\u7ae0 \u5192\u9669\u8005\u4eec"}, {"id": 37360, "book_url": "\u9b54\u5e7b\u5f02\u95fb\u5f55/37360", "title": "\u7b2c\u4e09\u767e\u516d\u5341\u516d\u7ae0 \u4f20\u8bf4\u4e2d\u7684\u9a91\u5175"}, {"id": 37364, "book_url": "\u9b54\u5e7b\u5f02\u95fb\u5f55/37364", "title": "\u7b2c\u4e09\u767e\u4e03\u5341\u7ae0 \u5bfc\u706b\u7d22"}, {"id": 37361, "book_url": "\u9b54\u5e7b\u5f02\u95fb\u5f55/37361", "title": "\u7b2c\u4e09\u767e\u516d\u5341\u4e03\u7ae0 \u5e78\u5b58\u8005"}, {"id": 37365, "book_url": "\u9b54\u5e7b\u5f02\u95fb\u5f55/37365", "title": "\u7b2c\u4e09\u767e\u4e03\u5341\u4e00\u7ae0 \u8fdb\u653b\u524d\u5915"}, {"id": 37362, "book_url": "\u9b54\u5e7b\u5f02\u95fb\u5f55/37362", "title": "\u7b2c\u4e09\u767e\u516d\u5341\u516b\u7ae0 \u7269\u662f\u4eba\u975e"}, {"id": 37366, "book_url": "\u9b54\u5e7b\u5f02\u95fb\u5f55/37366", "title": "\u7b2c\u4e09\u767e\u4e03\u5341\u4e8c\u7ae0 \u5f3a\u88ad"}, {"id": 37363, "book_url": "\u9b54\u5e7b\u5f02\u95fb\u5f55/37363", "title": "\u7b2c\u4e09\u767e\u516d\u5341\u4e5d\u7ae0 \u7cbe\u7075\u9a91\u5175"}, {"id": 37367, "book_url": "\u9b54\u5e7b\u5f02\u95fb\u5f55/37367", "title": "\u7b2c\u4e09\u767e\u4e03\u5341\u4e09\u7ae0 \u60ca\u95fb"}, {"id": 37368, "book_url": "\u9b54\u5e7b\u5f02\u95fb\u5f55/37368", "title": "\u7b2c\u4e09\u767e\u4e03\u5341\u56db\u7ae0 \u4f60\u770b\u4e0d\u89c1\u6211\uff0c\u4f60\u770b\u4e0d\u89c1\u6211"}, {"id": 37372, "book_url": "\u9b54\u5e7b\u5f02\u95fb\u5f55/37372", "title": "\u7b2c\u4e09\u767e\u4e03\u5341\u516b\u7ae0 \u8981\u585e\u7684\u6765\u5ba2"}, {"id": 37369, "book_url": "\u9b54\u5e7b\u5f02\u95fb\u5f55/37369", "title": "\u7b2c\u4e09\u767e\u4e03\u5341\u4e94\u7ae0 \u65e0\u5f62\u4e4b\u519b"}, {"id": 37373, "book_url": "\u9b54\u5e7b\u5f02\u95fb\u5f55/37373", "title": "\u7b2c\u4e09\u767e\u4e03\u5341\u4e5d\u7ae0 \u517d\u65cf\u76df\u7ea6"}, {"id": 37370, "book_url": "\u9b54\u5e7b\u5f02\u95fb\u5f55/37370", "title": "\u7b2c\u4e09\u767e\u4e03\u5341\u516d\u7ae0 \u90aa\u9b54\u6b6a\u9053"}, {"id": 37374, "book_url": "\u9b54\u5e7b\u5f02\u95fb\u5f55/37374", "title": "\u7b2c\u4e09\u767e\u516b\u5341\u7ae0 \u730e\u9b54\u5251"}, {"id": 37371, "book_url": "\u9b54\u5e7b\u5f02\u95fb\u5f55/37371", "title": "\u7b2c\u4e09\u767e\u4e03\u5341\u4e03\u7ae0 \u9634\u8c0b\u7684\u4e00\u89d2"}, {"id": 37375, "book_url": "\u9b54\u5e7b\u5f02\u95fb\u5f55/37375", "title": "\u7b2c\u4e09\u767e\u516b\u5341\u4e00\u7ae0 \u5185\u7591"}, {"id": 37376, "book_url": "\u9b54\u5e7b\u5f02\u95fb\u5f55/37376", "title": "\u7b2c\u4e09\u767e\u516b\u5341\u4e8c\u7ae0 \u706d\u9b54\u56e2"}, {"id": 37380, "book_url": "\u9b54\u5e7b\u5f02\u95fb\u5f55/37380", "title": "\u7b2c\u4e09\u767e\u516b\u5341\u516d\u7ae0 \u6c38\u6052\u4e4b\u529b"}, {"id": 37377, "book_url": "\u9b54\u5e7b\u5f02\u95fb\u5f55/37377", "title": "\u7b2c\u4e09\u767e\u516b\u5341\u4e09\u7ae0 \u51fa\u4e4e\u610f\u6599"}, {"id": 37381, "book_url": "\u9b54\u5e7b\u5f02\u95fb\u5f55/37381", "title": "\u7b2c\u4e09\u767e\u516b\u5341\u4e03\u7ae0 \u65b0\u7684\u5c55\u5f00"}, {"id": 37378, "book_url": "\u9b54\u5e7b\u5f02\u95fb\u5f55/37378", "title": "\u7b2c\u4e09\u767e\u516b\u5341\u56db\u7ae0 \u575a\u6bc5\u7684\u51b3\u5fc3"}, {"id": 37382, "book_url": "\u9b54\u5e7b\u5f02\u95fb\u5f55/37382", "title": "\u7b2c\u4e09\u767e\u516b\u5341\u516b\u7ae0 \u5f52\u6765\u7684\u5b89\u9038"}, {"id": 37379, "book_url": "\u9b54\u5e7b\u5f02\u95fb\u5f55/37379", "title": "\u7b2c\u4e09\u767e\u516b\u5341\u4e94\u7ae0 \u8fdb\u653b\uff01\u8fdb\u653b\uff01"}, {"id": 37383, "book_url": "\u9b54\u5e7b\u5f02\u95fb\u5f55/37383", "title": "\u7b2c\u4e09\u767e\u516b\u5341\u4e5d\u7ae0 \u6012\u6c14\u51b2\u5929"}, {"id": 37384, "book_url": "\u9b54\u5e7b\u5f02\u95fb\u5f55/37384", "title": "\u7b2c\u4e09\u767e\u4e5d\u5341\u7ae0 \u8c01\u662f\u4e3b\u5bb0"}, {"id": 37388, "book_url": "\u9b54\u5e7b\u5f02\u95fb\u5f55/37388", "title": "\u7b2c\u4e09\u767e\u4e5d\u5341\u56db\u7ae0 \u51fa\u73b0\u76ee\u6807"}, {"id": 37385, "book_url": "\u9b54\u5e7b\u5f02\u95fb\u5f55/37385", "title": "\u7b2c\u4e09\u767e\u4e5d\u5341\u4e00\u7ae0 \u62c6\u8fc1\uff1f"}, {"id": 37389, "book_url": "\u9b54\u5e7b\u5f02\u95fb\u5f55/37389", "title": "\u7b2c\u4e09\u767e\u4e5d\u5341\u4e94\u7ae0 \u6240\u8c13\u60e9\u7f5a"}, {"id": 37386, "book_url": "\u9b54\u5e7b\u5f02\u95fb\u5f55/37386", "title": "\u7b2c\u4e09\u767e\u4e5d\u5341\u4e8c\u7ae0 \u773c\u8272\u5f88\u91cd\u8981"}, {"id": 37390, "book_url": "\u9b54\u5e7b\u5f02\u95fb\u5f55/37390", "title": "\u7b2c\u4e09\u767e\u4e5d\u5341\u516d\u7ae0 \u6210"}, {"id": 37387, "book_url": "\u9b54\u5e7b\u5f02\u95fb\u5f55/37387", "title": "\u7b2c\u4e09\u767e\u4e5d\u5341\u4e09\u7ae0 \u9003\u96be\u4e4b\u65c5"}, {"id": 37391, "book_url": "\u9b54\u5e7b\u5f02\u95fb\u5f55/37391", "title": "\u7b2c\u4e09\u767e\u4e5d\u5341\u4e03\u7ae0 \u5e73\u51e1\u7684\u751f\u6d3b"}, {"id": 37392, "book_url": "\u9b54\u5e7b\u5f02\u95fb\u5f55/37392", "title": "\u7b2c\u4e09\u767e\u4e5d\u5341\u516b\u7ae0 \u4e71\u5165\u8005\u4eec"}, {"id": 37396, "book_url": "\u9b54\u5e7b\u5f02\u95fb\u5f55/37396", "title": "\u7b2c\u56db\u767e\u96f6\u4e8c\u7ae0 \u7eb7\u4e89\u4e0d\u65ad"}, {"id": 37393, "book_url": "\u9b54\u5e7b\u5f02\u95fb\u5f55/37393", "title": "\u7b2c\u4e09\u767e\u4e5d\u5341\u4e5d\u7ae0 \u68d8\u624b\u7684\u5bf9\u6218"}, {"id": 37397, "book_url": "\u9b54\u5e7b\u5f02\u95fb\u5f55/37397", "title": "\u7b2c\u56db\u767e\u96f6\u4e09\u7ae0 \u4e0d\u662f\u65f6\u5019"}, {"id": 37394, "book_url": "\u9b54\u5e7b\u5f02\u95fb\u5f55/37394", "title": "\u7b2c\u56db\u767e\u7ae0 \u6765\u81ea\u9065\u8fdc\u7684\u5730\u65b9"}, {"id": 37398, "book_url": "\u9b54\u5e7b\u5f02\u95fb\u5f55/37398", "title": "\u7b2c\u56db\u767e\u96f6\u56db\u7ae0 \u8352\u539f\u4e4b\u707e"}, {"id": 37395, "book_url": "\u9b54\u5e7b\u5f02\u95fb\u5f55/37395", "title": "\u7b2c\u56db\u767e\u96f6\u4e00\u7ae0 \u8fd9\u662f\u8ba1\u5212"}, {"id": 37399, "book_url": "\u9b54\u5e7b\u5f02\u95fb\u5f55/37399", "title": "\u7b2c\u56db\u767e\u96f6\u4e94\u7ae0 \u8fc7\u5883"}, {"id": 37400, "book_url": "\u9b54\u5e7b\u5f02\u95fb\u5f55/37400", "title": "\u7b2c\u56db\u767e\u96f6\u516d\u7ae0 \u901a\u5f80\u51b0\u539f\u4e4b\u8def"}, {"id": 37404, "book_url": "\u9b54\u5e7b\u5f02\u95fb\u5f55/37404", "title": "]\u7b2c\u56db\u767e\u4e00\u5341\u7ae0 \u7ade\u6280\u5927\u4f1a"}, {"id": 37401, "book_url": "\u9b54\u5e7b\u5f02\u95fb\u5f55/37401", "title": "\u7b2c\u56db\u767e\u96f6\u4e03\u7ae0 \u8fdb\u5165\u51b0\u539f"}, {"id": 37405, "book_url": "\u9b54\u5e7b\u5f02\u95fb\u5f55/37405", "title": "\u7b2c\u56db\u767e\u4e00\u5341\u4e00\u7ae0 \u963f\u62c9\u5e0c"}, {"id": 37402, "book_url": "\u9b54\u5e7b\u5f02\u95fb\u5f55/37402", "title": "\u7b2c\u56db\u767e\u96f6\u516b\u7ae0 \u7ea0\u7eb7"}, {"id": 37406, "book_url": "\u9b54\u5e7b\u5f02\u95fb\u5f55/37406", "title": "\u7b2c\u56db\u767e\u4e00\u5341\u4e8c\u7ae0 \u6218\u6b4c\u9152\u9986"}, {"id": 37403, "book_url": "\u9b54\u5e7b\u5f02\u95fb\u5f55/37403", "title": "\u7b2c\u56db\u767e\u96f6\u4e5d\u7ae0 \u517d\u4eba\u6751\u843d"}, {"id": 37407, "book_url": "\u9b54\u5e7b\u5f02\u95fb\u5f55/37407", "title": "\u7b2c\u56db\u767e\u4e00\u5341\u4e09\u7ae0 \u96be\u4ee5\u9884\u6d4b"}, {"id": 37408, "book_url": "\u9b54\u5e7b\u5f02\u95fb\u5f55/37408", "title": "\u56db\u767e\u4e00\u5341\u56db\u7ae0 \u65af\u8482\u6cd5\u5c14\u7684\u6218\u6597"}, {"id": 37412, "book_url": "\u9b54\u5e7b\u5f02\u95fb\u5f55/37412", "title": "\u7b2c\u56db\u767e\u4e00\u5341\u516b\u7ae0 \u53cc\u751f\u4e4b\u5b50"}, {"id": 37409, "book_url": "\u9b54\u5e7b\u5f02\u95fb\u5f55/37409", "title": "\u7b2c\u56db\u767e\u4e00\u5341\u4e94\u7ae0 \u6289\u62e9"}, {"id": 37413, "book_url": "\u9b54\u5e7b\u5f02\u95fb\u5f55/37413", "title": "\u7b2c\u56db\u767e\u4e00\u5341\u4e5d\u7ae0 \u5965\u7279\u5170\u514b\u5c71\u8c37\u4e4b\u6218"}, {"id": 37410, "book_url": "\u9b54\u5e7b\u5f02\u95fb\u5f55/37410", "title": "\u7b2c\u56db\u767e\u4e00\u5341\u516d\u7ae0 \u9690\u853d\u7684\u80cc\u540e"}, {"id": 37414, "book_url": "\u9b54\u5e7b\u5f02\u95fb\u5f55/37414", "title": "\u7b2c\u56db\u767e\u4e8c\u5341\u7ae0 \u5145\u6ee1\u7591\u60d1\u7684\u5931\u8d25"}, {"id": 37411, "book_url": "\u9b54\u5e7b\u5f02\u95fb\u5f55/37411", "title": "\u7b2c\u56db\u767e\u4e00\u5341\u4e03\u7ae0 \u4e34\u8fd1\u4e4b\u65e5"}, {"id": 37415, "book_url": "\u9b54\u5e7b\u5f02\u95fb\u5f55/37415", "title": "\u7b2c\u56db\u767e\u4e8c\u5341\u4e00\u7ae0 \u6b7b\u7075\u6cd5\u5e08"}, {"id": 37416, "book_url": "\u9b54\u5e7b\u5f02\u95fb\u5f55/37416", "title": "\u7b2c\u56db\u767e\u4e8c\u5341\u4e8c\u7ae0 \u8ffd\u5bfb\u8e2a\u8ff9"}, {"id": 37420, "book_url": "\u9b54\u5e7b\u5f02\u95fb\u5f55/37420", "title": "\u7b2c\u56db\u767e\u4e8c\u5341\u516d\u7ae0 \u6bc1\u706d\u7684\u5e8f\u7ae0"}, {"id": 37417, "book_url": "\u9b54\u5e7b\u5f02\u95fb\u5f55/37417", "title": "\u7b2c\u56db\u767e\u4e8c\u5341\u4e09\u7ae0 \u975e\u8054\u5408\u6218\u7ebf"}, {"id": 37421, "book_url": "\u9b54\u5e7b\u5f02\u95fb\u5f55/37421", "title": "\u7b2c\u56db\u767e\u4e8c\u5341\u4e03\u7ae0 \u771f\u771f\u5047\u5047 \u5c0f\u8bf4\u5c4b"}, {"id": 37418, "book_url": "\u9b54\u5e7b\u5f02\u95fb\u5f55/37418", "title": "\u7b2c\u56db\u767e\u4e8c\u5341\u56db\u7ae0\u4e2a\u9677\u9631\uff0c\u4e24\u4e2a\u9677\u9631"}, {"id": 37422, "book_url": "\u9b54\u5e7b\u5f02\u95fb\u5f55/37422", "title": "\u7b2c\u56db\u767e\u4e8c\u5341\u516b\u7ae0 \u4e0d\u540c\u7684\u9053\u8def"}, {"id": 37419, "book_url": "\u9b54\u5e7b\u5f02\u95fb\u5f55/37419", "title": "\u7b2c\u56db\u767e\u4e8c\u5341\u4e94\u7ae0 \u7d22\u65af\u4e4b\u6218"}, {"id": 37423, "book_url": "\u9b54\u5e7b\u5f02\u95fb\u5f55/37423", "title": "\u7b2c\u56db\u767e\u4e8c\u5341\u4e5d\u7ae0 \u51fa\u4e4e\u610f\u6599\u7684\u7231"}, {"id": 37424, "book_url": "\u9b54\u5e7b\u5f02\u95fb\u5f55/37424", "title": "\u7b2c\u56db\u767e\u4e09\u5341\u7ae0 \u68a6\u5883\u661f\u8fb0"}, {"id": 37428, "book_url": "\u9b54\u5e7b\u5f02\u95fb\u5f55/37428", "title": "\u7b2c\u56db\u767e\u4e09\u5341\u56db\u7ae0 \u7ed1\u7968"}, {"id": 37425, "book_url": "\u9b54\u5e7b\u5f02\u95fb\u5f55/37425", "title": "\u7b2c\u56db\u767e\u4e09\u5341\u4e00\u7ae0 \u6d41\u901d\u4e4b\u661f"}, {"id": 37429, "book_url": "\u9b54\u5e7b\u5f02\u95fb\u5f55/37429", "title": "\u7b2c\u56db\u767e\u4e09\u5341\u4e94\u7ae0 \u8f6c\u6298\u70b9"}, {"id": 37426, "book_url": "\u9b54\u5e7b\u5f02\u95fb\u5f55/37426", "title": "\u7b2c\u56db\u767e\u4e09\u5341\u4e8c\u7ae0 \u611a\u8822\u7684\u5bf9\u6297"}, {"id": 37430, "book_url": "\u9b54\u5e7b\u5f02\u95fb\u5f55/37430", "title": "\u7b2c\u56db\u767e\u4e09\u5341\u516d\u7ae0 \u4fe1\u4f7f\u5230\u8bbf"}, {"id": 37427, "book_url": "\u9b54\u5e7b\u5f02\u95fb\u5f55/37427", "title": "\u7b2c\u56db\u767e\u4e09\u5341\u4e09\u7ae0 \u5404\u53d6\u6240\u9700"}, {"id": 37431, "book_url": "\u9b54\u5e7b\u5f02\u95fb\u5f55/37431", "title": "\u7b2c\u56db\u767e\u4e09\u5341\u4e03\u7ae0 \u7b49\u5f85"}, {"id": 37432, "book_url": "\u9b54\u5e7b\u5f02\u95fb\u5f55/37432", "title": "\u7b2c\u56db\u767e\u4e09\u5341\u516b\u7ae0 \u5ba1\u5224\u4f1a\u8bae"}, {"id": 37436, "book_url": "\u9b54\u5e7b\u5f02\u95fb\u5f55/37436", "title": "\u7b2c\u56db\u767e\u56db\u5341\u4e00\u7ae0 \u6bcf\u4e2a\u4eba"}, {"id": 37433, "book_url": "\u9b54\u5e7b\u5f02\u95fb\u5f55/37433", "title": "\u7b2c\u56db\u767e\u4e09\u5341\u4e5d\u7ae0 \u53ea\u662f\u5982\u6b64"}, {"id": 37437, "book_url": "\u9b54\u5e7b\u5f02\u95fb\u5f55/37437", "title": "\u7b2c\u56db\u767e\u56db\u5341\u4e8c\u7ae0 \u5165\u4fb5\u7684\u53f7\u89d2"}, {"id": 37434, "book_url": "\u9b54\u5e7b\u5f02\u95fb\u5f55/37434", "title": "\u7b2c\u56db\u767e\u56db\u5341\u7ae0 \u663e\u5f62"}, {"id": 37438, "book_url": "\u9b54\u5e7b\u5f02\u95fb\u5f55/37438", "title": "\u7b2c\u56db\u767e\u56db\u5341\u4e09\u7ae0 \u540c\u76df\u6218\u7ebf"}, {"id": 37435, "book_url": "\u9b54\u5e7b\u5f02\u95fb\u5f55/37435", "title": "\u7b2c\u56db\u767e\u4e94\u5341\u4e03\u7ae0 \u7a7a\u88ad"}, {"id": 37439, "book_url": "\u9b54\u5e7b\u5f02\u95fb\u5f55/37439", "title": "\u7b2c\u56db\u767e\u56db\u5341\u56db\u7ae0 \u5080\u5121\u5019\u8865"}, {"id": 37440, "book_url": "\u9b54\u5e7b\u5f02\u95fb\u5f55/37440", "title": "\u7b2c\u56db\u767e\u56db\u5341\u4e94\u7ae0 \u540e\u65b9\u6218\u7565"}, {"id": 37444, "book_url": "\u9b54\u5e7b\u5f02\u95fb\u5f55/37444", "title": "\u7b2c\u56db\u767e\u56db\u5341\u4e5d\u7ae0 \u52a8\u8361\u5f00\u59cb"}, {"id": 37441, "book_url": "\u9b54\u5e7b\u5f02\u95fb\u5f55/37441", "title": "\u7b2c\u56db\u767e\u56db\u5341\u516d\u7ae0 \u5bfb\u8e2a\u89c5\u8ff9"}, {"id": 37445, "book_url": "\u9b54\u5e7b\u5f02\u95fb\u5f55/37445", "title": "\u7b2c\u56db\u767e\u4e94\u5341\u7ae0 \u9003\u4e0d\u6389\u4e86"}, {"id": 37442, "book_url": "\u9b54\u5e7b\u5f02\u95fb\u5f55/37442", "title": "\u7b2c\u56db\u767e\u56db\u5341\u4e03\u7ae0 \u5236\u9020\u82f1\u96c4"}, {"id": 37446, "book_url": "\u9b54\u5e7b\u5f02\u95fb\u5f55/37446", "title": "\u7b2c\u56db\u767e\u4e94\u5341\u4e00\u7ae0 \u538b\u5236"}, {"id": 37443, "book_url": "\u9b54\u5e7b\u5f02\u95fb\u5f55/37443", "title": "\u7b2c\u56db\u767e\u56db\u5341\u516b\u7ae0 \u4e24\u6761\u6218\u7ebf"}, {"id": 37447, "book_url": "\u9b54\u5e7b\u5f02\u95fb\u5f55/37447", "title": "\u7b2c\u56db\u767e\u4e94\u5341\u4e8c\u7ae0 \u9006\u8f6c\u9635\u8425"}, {"id": 37448, "book_url": "\u9b54\u5e7b\u5f02\u95fb\u5f55/37448", "title": "\u7b2c\u56db\u767e\u4e94\u5341\u4e09\u7ae0 \u5185\u9b3c"}, {"id": 37452, "book_url": "\u9b54\u5e7b\u5f02\u95fb\u5f55/37452", "title": "\u7b2c\u56db\u767e\u516d\u5341\u7ae0 \u9009\u62e9\u4e4b\u524d"}, {"id": 37449, "book_url": "\u9b54\u5e7b\u5f02\u95fb\u5f55/37449", "title": "\u7b2c\u56db\u767e\u4e94\u5341\u56db\u7ae0 \u516c\u5f00\u5904\u5211"}, {"id": 37453, "book_url": "\u9b54\u5e7b\u5f02\u95fb\u5f55/37453", "title": "\u7b2c\u56db\u767e\u516d\u5341\u4e8c\u7ae0 \u7b2c\u4e00\u5175\u56e2"}, {"id": 37450, "book_url": "\u9b54\u5e7b\u5f02\u95fb\u5f55/37450", "title": "\u7b2c\u56db\u767e\u4e94\u5341\u4e94\u7ae0 \u8054\u5408\u7edf\u4e00\u6218\u7ebf"}, {"id": 37454, "book_url": "\u9b54\u5e7b\u5f02\u95fb\u5f55/37454", "title": "\u7b2c\u56db\u767e\u516d\u5341\u4e09\u7ae0\u6c34\u9762\u4e0b\u7684\u6ce2\u52a8"}, {"id": 37451, "book_url": "\u9b54\u5e7b\u5f02\u95fb\u5f55/37451", "title": "\u7b2c\u56db\u767e\u4e94\u5341\u516b\u7ae0 \u4f1a\u9762"}, {"id": 37455, "book_url": "\u9b54\u5e7b\u5f02\u95fb\u5f55/37455", "title": "\u7b2c\u56db\u767e\u516d\u5341\u56db\u7ae0\u5f3a\u8feb\u548c\u8c10"}, {"id": 37456, "book_url": "\u9b54\u5e7b\u5f02\u95fb\u5f55/37456", "title": "\u7b2c\u56db\u767e\u516d\u5341\u4e94\u7ae0\u5fc5\u8981\u7684\u5931\u8d25"}, {"id": 37460, "book_url": "\u9b54\u5e7b\u5f02\u95fb\u5f55/37460", "title": "\u7b2c\u56db\u767e\u516d\u5341\u4e5d\u7ae0 \u4e89\u8bae"}, {"id": 37457, "book_url": "\u9b54\u5e7b\u5f02\u95fb\u5f55/37457", "title": "\u7b2c\u56db\u767e\u516d\u5341\u516d\u7ae0\u5c0f\u5c0f\u7684\u8bd5\u9a8c"}, {"id": 37461, "book_url": "\u9b54\u5e7b\u5f02\u95fb\u5f55/37461", "title": "\u7b2c\u56db\u767e\u4e03\u5341\u7ae0\u5feb\u8fdb"}, {"id": 37458, "book_url": "\u9b54\u5e7b\u5f02\u95fb\u5f55/37458", "title": "\u7b2c\u56db\u767e\u516d\u5341\u4e03\u7ae0\u6218\u6597\u524d\u591c"}, {"id": 37462, "book_url": "\u9b54\u5e7b\u5f02\u95fb\u5f55/37462", "title": "\u7b2c\u56db\u767e\u4e03\u5341\u4e00\u7ae0\u52a8\u6447"}, {"id": 37459, "book_url": "\u9b54\u5e7b\u5f02\u95fb\u5f55/37459", "title": "\u7b2c\u56db\u767e\u516d\u5341\u516b\u7ae0 \u5f00\u6218"}, {"id": 37463, "book_url": "\u9b54\u5e7b\u5f02\u95fb\u5f55/37463", "title": "\u7b2c\u56db\u767e\u4e03\u5341\u4e8c\u7ae0\u50f5\u6301"}, {"id": 37464, "book_url": "\u9b54\u5e7b\u5f02\u95fb\u5f55/37464", "title": "\u7b2c\u56db\u767e\u4e03\u5341\u4e09\u7ae0\u540e\u5bab\u6559\u5b66PAT1"}, {"id": 37468, "book_url": "\u9b54\u5e7b\u5f02\u95fb\u5f55/37468", "title": "\u7b2c\u56db\u767e\u4e03\u5341\u4e03\u7ae0\u9677\u9631"}, {"id": 37465, "book_url": "\u9b54\u5e7b\u5f02\u95fb\u5f55/37465", "title": "\u7b2c\u56db\u767e\u4e03\u5341\u56db\u7ae0\u540e\u5bab\u6559\u5b66PAT2"}, {"id": 37469, "book_url": "\u9b54\u5e7b\u5f02\u95fb\u5f55/37469", "title": "\u7b2c\u56db\u767e\u4e03\u5341\u516b\u7ae0\u4e0e\u864e\u8c0b\u76ae"}, {"id": 37466, "book_url": "\u9b54\u5e7b\u5f02\u95fb\u5f55/37466", "title": "\u7b2c\u56db\u767e\u4e03\u5341\u4e94\u7ae0\u504f\u79fb"}, {"id": 37470, "book_url": "\u9b54\u5e7b\u5f02\u95fb\u5f55/37470", "title": "\u7b2c\u56db\u767e\u4e03\u5341\u4e5d\u7ae0\u5185\u8ba7"}, {"id": 37467, "book_url": "\u9b54\u5e7b\u5f02\u95fb\u5f55/37467", "title": "\u7b2c\u56db\u767e\u4e03\u5341\u516d\u7ae0\u5f02\u52a8"}, {"id": 37471, "book_url": "\u9b54\u5e7b\u5f02\u95fb\u5f55/37471", "title": "\u7b2c\u56db\u767e\u516b\u5341\u7ae0\u6218\u8d25"}, {"id": 37472, "book_url": "\u9b54\u5e7b\u5f02\u95fb\u5f55/37472", "title": "\u7b2c\u56db\u767e\u516b\u5341\u4e00\u7ae0\u653b\u575a"}, {"id": 37476, "book_url": "\u9b54\u5e7b\u5f02\u95fb\u5f55/37476", "title": "\u7b2c\u56db\u767e\u516b\u5341\u516d\u7ae0\u6c38\u6052\u534f\u8c03"}, {"id": 37473, "book_url": "\u9b54\u5e7b\u5f02\u95fb\u5f55/37473", "title": "\u7b2c\u56db\u767e\u516b\u5341\u4e8c\u7ae0\u65e0\u5c3d\u7684\u534e\u5c14\u51790"}, {"id": 37477, "book_url": "\u9b54\u5e7b\u5f02\u95fb\u5f55/37477", "title": "\u7b2c\u56db\u767e\u516b\u5341\u4e03\u7ae0\u4e8b\u60017941\u5316.."}, {"id": 37474, "book_url": "\u9b54\u5e7b\u5f02\u95fb\u5f55/37474", "title": "\u7b2c\u56db\u767e\u516b\u5341\u4e09\u7ae0\u6c89\u9ed8\u591a\u6570"}, {"id": 37478, "book_url": "\u9b54\u5e7b\u5f02\u95fb\u5f55/37478", "title": "\u7b2c\u56db\u767e\u516b\u5341\u516b\u7ae0\u6289\u62e9\u4e0e\u7b49\u5f85"}, {"id": 37475, "book_url": "\u9b54\u5e7b\u5f02\u95fb\u5f55/37475", "title": "\u7b2c\u56db\u767e\u516b\u5341\u56db\u7ae0\u6d6e\u7a7a\u57ce"}, {"id": 37479, "book_url": "\u9b54\u5e7b\u5f02\u95fb\u5f55/37479", "title": "\u7b2c\u56db\u767e\u516b\u5341\u4e5d\u7ae0\u56de\u5e94\u4e4b\u5fc3"}, {"id": 37480, "book_url": "\u9b54\u5e7b\u5f02\u95fb\u5f55/37480", "title": "\u7b2c\u56db\u767e\u516b\u5341\u4e5d\u7ae0\u56de\u5e94\u4e4b\u5fc3"}, {"id": 37481, "book_url": "\u9b54\u5e7b\u5f02\u95fb\u5f55/37481", "title": "\u6700\u7ec8\u7ae0\u8e0f\u4e0a\u65c5\u9014"}]}, "intro": "\u4e24\u4e2a\u56e0\u4e3a\u4e8b\u6545\u800c\u7a7f\u8d8a\u7684\u5c11\u5e74\u5c11\u5973,\r\n  \u5728\u8fd9\u4e2a\u964c\u751f\u7684\u5927\u9646.\r\n  \u4ed6\u4eec\u53d1\u73b0\u81ea\u5df1\u5c06\u8981\u9762\u5bf9\u67d0\u79cd\u8d85\u8d8a\u73b0\u5b9e\u7684\u5e7b\u60f3\u5b58\u5728,\r\n  \u9b54\u6cd5\u7684\u4e16\u754c.\r\n  \u4f46\u662f\u4ed6\u4eec\u5374\u5e76\u4e0d\u611f\u5230\u60ca\u8bb6\u6216\u6050\u60e7\r\n  \u56e0\u4e3a\u4e24\u4eba\u540c\u6837\u62e5\u6709\u7740\u8d85\u8d8a\u73b0\u5b9e\u7684\u5e7b\u60f3\r\n  \u4ed6\u4eec\u662f\u5f02\u80fd\u8005\r\n  \u5728\u8fd9\u7247\u9b54\u6cd5\u5927\u9646\u4e0a,\u5f02\u80fd\u4e0e\u9b54\u6cd5\u7684\u78b0\u649e,\u7a76\u7adf\u4f1a\u4ea7\u751f\u4ec0\u4e48\u6837\u7684\u706b\u82b1?\r\n   \u800c\u4ed6\u4eec,\u53c8\u5c06\u4f1a\u5851\u9020\u4ec0\u4e48\u6837\u7684\u4f20\u5947?", "name": "\u9b54\u5e7b\u5f02\u95fb\u5f55"}